Workbook

Sheet Sheet1
A1: ProductID | B1: Title | C1: Photo | D1: BodyRegular | E1: BodyDiscounted | F1: PriceRegular | G1: PriceDiscounted | H1: IsDiscounted | I1: DiscountedUntil | J1: IsPublished | K1: LastModified | L1: Coverage | M1: Product type | N1: Term | O1: Grade level | P1: Package type | Q1: Days | R1: Items | S1: Pieces
A2: GA-QA-HP | B2: Printable Handouts for Grades 7 and 9 | C2: https://res.cloudinary.com/dadubemrv/image/upload/v1771470535/pv600hy73vw3w5yfrdrm.jpg | E2: =CONCATENATE(_xlfn._LONGTEXT("Nabibigatan ka ba sa laptop at projector para sa PowerPoint presentations mo, KasaMath? Tinatamad ka ba, walang time, o nahihirapang gumawa ng PowerPoint? I-download mo na itong ating **FREE printable Math handouts** para: - **Tipid ka sa oras** at ma","kapag-focus ka sa lesson planning mo. - **Maganda at consistent ang formatting** ng figures at mathematical expressions. - **Magaan na ang dala mong gamit** sa classroom dahil wala nang laptop at projector. - **Di na problema ang ipapa-seatwork at a","ctivity** dahil meron na sa handouts. - **Mas focused ang bata** dahil di na sila titingin sa visual aids na nasa board pag nagsusulat. Kung gusto mo namang suportahan ang mission ko na pagbibigay ng FREE Math teaching resources, pwede kang [mag-dona","te](https://texmathpro.github.io/donate/), KasaMath. ## 📥 Download the Handouts"), CHAR(10), CHAR(10), _xlfn.TEXTJOIN(CHAR(10), TRUE, Sheet2!G10:'Sheet2'!J13)," --- Kung gusto mo namang maging updated sa promos, FREEBIES, discounts, at Math-related content, mag-subscribe ka lang sa ating mailing list. Mag-email ka lang ng **SUBSCRIBE** sa [texmathpro@gmail.com](mailto:texmathpro@gmail.com?subject=Subscribe&"&"body=SUBSCRIBE). --- **Happy teaching, KasaMath!** [Jonathan Bacolod](https://texmathpro.github.io/about/) Owner and CEO [TeXMathPro](https://texmathpro.github.io/): Math Teaching Beautified [texmathpro@gmail.com](mailto:texmathpro@gmail.com?subj"&"ect=Subscribe&body=SUBSCRIBE)", "{{< adsense >}}") -> Nabibigatan ka ba sa laptop at projector para sa PowerPoint presentations mo, KasaMath? Tinatamad ka ba, walang time, o nahihirapang gumawa ng PowerPoint? I-download mo na itong ating **FREE printable Math handouts** para: - **Tipid ka sa oras** at makapag-focus ka sa lesson planning mo. - **Maganda at consistent ang formatting** ng figures at mathematical expressions. - **Magaan na ang dala mong gamit** sa classroom dahil wala nang laptop at projector. - **Di na problema ang ipapa-seatwork at activity** dahil meron na sa handouts. - **Mas focused ang bata** dahil di na sila titingin sa visual aids na nasa board pag nagsusulat. Kung gusto mo namang suportahan ang mission ko na pagbibigay ng FREE Math teaching resources, pwede kang [mag-donate](https://texmathpro.github.io/donate/), KasaMath. ## 📥 Download the Handouts - [Grade 7 Handouts for the 1st Term](https://drive.google.com/file/d/150NUP_Nq2tev-Qn00VInZTAaPrUAssmQ/view?usp=drivesdk) - [Grade 9 Handouts for the 1st Term](https://drive.google.com/file/d/1x4fsJFRIZ1vsqPk6OXbzsGErE1XdDNJQ/view?usp=drivesdk) - [Grade 7 Handouts for the 2nd Term](https://drive.google.com/file/d/1-KDJsZditKS4m47wiWkkrUHdmr6OGHRS/view?usp=drivesdk) - [Grade 9 Handouts for the 2nd Term](https://drive.google.com/file/d/1EE_6jJP56HUvwmqvAvF3kXdhOI1EKpPi/view?usp=drivesdk) --- Kung gusto mo namang maging updated sa promos, FREEBIES, discounts, at Math-related content, mag-subscribe ka lang sa ating mailing list. Mag-email ka lang ng **SUBSCRIBE** sa [texmathpro@gmail.com](mailto:texmathpro@gmail.com?subject=Subscribe&body=SUBSCRIBE). --- **Happy teaching, KasaMath!** [Jonathan Bacolod](https://texmathpro.github.io/about/) Owner and CEO [TeXMathPro](https://texmathpro.github.io/): Math Teaching Beautified [texmathpro@gmail.com](mailto:texmathpro@gmail.com?subject=Subscribe&body=SUBSCRIBE){{< adsense >}} | F2: 500 | G2: 0 | H2: TRUE | I2: 46172 | J2: TRUE | K2: 46178
A4: G7-T3-S1-BP | B4: Grade 7 T3 First Summative Test + TOS + Answer Key (Basic) | C4: https://i.imgur.com/DKwxWes.jpeg | D4: =Sheet2!$D$2 -> 0 | E4: =Sheet2!$A$2 -> 0 | F4: 120 | G4: 84 | H4: FALSE | I4: 46176 | J4: FALSE | K4: 46176
A5: G7-T3-S1-SP | B5: Grade 7 T3 First Summative Test + TOS + Answer Key (Standard) | C5: https://i.imgur.com/DKwxWes.jpeg | D5: =Sheet2!$E$2 -> 0 | E5: =Sheet2!$B$2 -> 0 | F5: 165 | G5: 115 | H5: FALSE | I5: 46176 | J5: FALSE | K5: 46176
A6: G7-T3-S1-CP | B6: Grade 7 T3 First Summative Test + TOS + Answer Key (Custom) | C6: https://i.imgur.com/DKwxWes.jpeg | D6: =Sheet2!$F$2 -> 0 | E6: =Sheet2!$C$2 -> 0 | F6: 350 | G6: 245 | H6: FALSE | I6: 46176 | J6: FALSE | K6: 46176
A7: G8-T3-S1-BP | B7: Grade 8 T3 First Summative Test + TOS + Answer Key (Basic) | C7: https://i.imgur.com/taq0wC7.jpeg | D7: =Sheet2!$D$2 -> 0 | E7: =Sheet2!$A$2 -> 0 | F7: 120 | G7: 84 | H7: FALSE | I7: 46176 | J7: FALSE | K7: 46176
A8: G8-T3-S1-SP | B8: Grade 8 T3 First Summative Test + TOS + Answer Key (Standard) | C8: https://i.imgur.com/taq0wC7.jpeg | D8: =Sheet2!$E$2 -> 0 | E8: =Sheet2!$B$2 -> 0 | F8: 165 | G8: 115 | H8: FALSE | I8: 46176 | J8: FALSE | K8: 46176
A9: G8-T3-S1-CP | B9: Grade 8 T3 First Summative Test + TOS + Answer Key (Custom) | C9: https://i.imgur.com/taq0wC7.jpeg | D9: =Sheet2!$F$2 -> 0 | E9: =Sheet2!$C$2 -> 0 | F9: 350 | G9: 245 | H9: FALSE | I9: 46176 | J9: FALSE | K9: 46176
A10: G9-T3-S1-BP | B10: Grade 9 T3 First Summative Test + TOS + Answer Key (Basic) | C10: https://i.imgur.com/GzJQ9w9.jpeg | D10: =Sheet2!$D$2 -> 0 | E10: =Sheet2!$A$2 -> 0 | F10: 120 | G10: 84 | H10: FALSE | I10: 46176 | J10: FALSE | K10: 46176
A11: G9-T3-S1-SP | B11: Grade 9 T3 First Summative Test + TOS + Answer Key (Standard) | C11: https://i.imgur.com/GzJQ9w9.jpeg | D11: =Sheet2!$E$2 -> 0 | E11: =Sheet2!$B$2 -> 0 | F11: 165 | G11: 115 | H11: FALSE | I11: 46176 | J11: FALSE | K11: 46176
A12: G9-T3-S1-CP | B12: Grade 9 T3 First Summative Test + TOS + Answer Key (Custom) | C12: https://i.imgur.com/GzJQ9w9.jpeg | D12: =Sheet2!$F$2 -> 0 | E12: =Sheet2!$C$2 -> 0 | F12: 350 | G12: 245 | H12: FALSE | I12: 46176 | J12: FALSE | K12: 46176
A13: G10-T3-S1-BP | B13: Grade 10 T3 First Summative Test + TOS + Answer Key (Basic) | C13: https://i.imgur.com/IXUG78E.jpeg | D13: =Sheet2!$D$2 -> 0 | E13: =Sheet2!$A$2 -> 0 | F13: 120 | G13: 84 | H13: FALSE | I13: 46176 | J13: FALSE | K13: 46176
A14: G10-T3-S1-SP | B14: Grade 10 T3 First Summative Test + TOS + Answer Key (Standard) | C14: https://i.imgur.com/IXUG78E.jpeg | D14: =Sheet2!$E$2 -> 0 | E14: =Sheet2!$B$2 -> 0 | F14: 165 | G14: 115 | H14: FALSE | I14: 46176 | J14: FALSE | K14: 46176
A15: G10-T3-S1-CP | B15: Grade 10 T3 First Summative Test + TOS + Answer Key (Custom) | C15: https://i.imgur.com/IXUG78E.jpeg | D15: =Sheet2!$F$2 -> 0 | E15: =Sheet2!$C$2 -> 0 | F15: 350 | G15: 245 | H15: FALSE | I15: 46176 | J15: FALSE | K15: 46176
A16: G7-T3-TE-BP | B16: Grade 7 T3 Term Exam + TOS + Answer Key (Basic) | C16: https://i.imgur.com/TYIT3or.jpeg | D16: =Sheet2!$D$2 -> 0 | E16: =Sheet2!$A$2 -> 0 | F16: 120 | G16: 84 | H16: FALSE | I16: 46176 | J16: FALSE | K16: 46176
A17: G7-T3-TE-SP | B17: Grade 7 T3 Term Exam + TOS + Answer Key (Standard) | C17: https://i.imgur.com/TYIT3or.jpeg | D17: =Sheet2!$E$2 -> 0 | E17: =Sheet2!$B$2 -> 0 | F17: 165 | G17: 115 | H17: FALSE | I17: 46176 | J17: FALSE | K17: 46176
A18: G7-T3-TE-CP | B18: Grade 7 T3 Term Exam + TOS + Answer Key (Custom) | C18: https://i.imgur.com/TYIT3or.jpeg | D18: =Sheet2!$F$2 -> 0 | E18: =Sheet2!$C$2 -> 0 | F18: 350 | G18: 245 | H18: FALSE | I18: 46176 | J18: FALSE | K18: 46176
A19: G8-T3-TE-BP | B19: Grade 8 T3 Term Exam + TOS + Answer Key (Basic) | C19: https://i.imgur.com/CTCvbDz.jpeg | D19: =Sheet2!$D$2 -> 0 | E19: =Sheet2!$A$2 -> 0 | F19: 120 | G19: 84 | H19: FALSE | I19: 46176 | J19: FALSE | K19: 46176
A20: G8-T3-TE-SP | B20: Grade 8 T3 Term Exam + TOS + Answer Key (Standard) | C20: https://i.imgur.com/CTCvbDz.jpeg | D20: =Sheet2!$E$2 -> 0 | E20: =Sheet2!$B$2 -> 0 | F20: 165 | G20: 115 | H20: FALSE | I20: 46176 | J20: FALSE | K20: 46176
A21: G8-T3-TE-CP | B21: Grade 8 T3 Term Exam + TOS + Answer Key (Custom) | C21: https://i.imgur.com/CTCvbDz.jpeg | D21: =Sheet2!$F$2 -> 0 | E21: =Sheet2!$C$2 -> 0 | F21: 350 | G21: 245 | H21: FALSE | I21: 46176 | J21: FALSE | K21: 46176
A22: G9-T3-TE-BP | B22: Grade 9 T3 Term Exam + TOS + Answer Key (Basic) | C22: https://i.imgur.com/c0IwjHZ.jpeg | D22: =Sheet2!$D$2 -> 0 | E22: =Sheet2!$A$2 -> 0 | F22: 120 | G22: 84 | H22: FALSE | I22: 46176 | J22: FALSE | K22: 46176
A23: G9-T3-TE-SP | B23: Grade 9 T3 Term Exam + TOS + Answer Key (Standard) | C23: https://i.imgur.com/c0IwjHZ.jpeg | D23: =Sheet2!$E$2 -> 0 | E23: =Sheet2!$B$2 -> 0 | F23: 165 | G23: 115 | H23: FALSE | I23: 46176 | J23: FALSE | K23: 46176
A24: G9-T3-TE-CP | B24: Grade 9 T3 Term Exam + TOS + Answer Key (Custom) | C24: https://i.imgur.com/c0IwjHZ.jpeg | D24: =Sheet2!$F$2 -> 0 | E24: =Sheet2!$C$2 -> 0 | F24: 350 | G24: 245 | H24: FALSE | I24: 46176 | J24: FALSE | K24: 46176
A25: G10-T3-TE-BP | B25: Grade 10 T3 Term Exam + TOS + Answer Key (Basic) | C25: https://i.imgur.com/PsPVTBV.jpeg | D25: =Sheet2!$D$2 -> 0 | E25: =Sheet2!$A$2 -> 0 | F25: 120 | G25: 84 | H25: FALSE | I25: 46176 | J25: FALSE | K25: 46176
A26: G10-T3-TE-SP | B26: Grade 10 T3 Term Exam + TOS + Answer Key (Standard) | C26: https://i.imgur.com/PsPVTBV.jpeg | D26: =Sheet2!$E$2 -> 0 | E26: =Sheet2!$B$2 -> 0 | F26: 165 | G26: 115 | H26: FALSE | I26: 46176 | J26: FALSE | K26: 46176
A27: G10-T3-TE-CP | B27: Grade 10 T3 Term Exam + TOS + Answer Key (Custom) | C27: https://i.imgur.com/PsPVTBV.jpeg | D27: =Sheet2!$F$2 -> 0 | E27: =Sheet2!$C$2 -> 0 | F27: 350 | G27: 245 | H27: FALSE | I27: 46176 | J27: FALSE | K27: 46176
A29: G7-T1-S1-BP | B29: Grade 7 T1 First Summative Test + Answer Key (Basic) | C29: https://res.cloudinary.com/dadubemrv/image/upload/v1783262649/xa3ma5xtgdbpiti2pulm.png, https://res.cloudinary.com/dadubemrv/image/upload/v1783262653/xelrwfv3qo9fte8tcav5.png, https://res.cloudinary.com/dadubemrv/image/upload/v1783262656/erime3c8h1ngvdbdrwdu.png, https://res.cloudinary.com/dadubemrv/image/upload/v1783262658/s6wrnagjw7rwy2jvrk9h.png | D29: =CONCATENATE("*Tinatamad ka ba, walang time, o nahihirapang gumawa ng TOS at ", Sheet1!M29, " mo, ",Sheet1!O29," KasaMath? Kuha ka na ng ", Sheet1!P29,"!* **Bakit perfect para sa’yo ang ", Sheet1!P29,"?** ",Sheet2!D$17, Sheet1!Q29," days - ", Sheet1!R29,"-item Multiple Choice test with Answer Key - Para sa teachers na nagmamadali at hindi kailangan ang TOS", L29, " --- ## Step 1: I-fill out at i-submit ang Order Form. ", "{{< iframe src=""", "https://cityofsmiles.github.io/auto-order-form/?id=", LOWER(A29), """ height=""850"" >}}"," ## Step 2: Payment and Delivery ### Payment Methods Mag-send ka lang ng ₱",Sheet1!F29," para sa **", Sheet1!M29,_xlfn._LONGTEXT("**. - **Landbank**: 0695077289 (Jonathan R. Bacolod) - **GCash**: 09128389571 (Jonathan Bacolod) - **Maya**: 09128389571 (Jonathan Bacolod) **Isend ang Screenshot ng Payment kahit saan dito:** - Email: [texmathpro@gmail.com](mailto:texmathpro@gm","ail.com) - Facebook: https://m.me/jonathan.r.bacolod - Telegram: https://t.me/Jonathan_Bacolod Isesend ko ang files sa email address mo after ng payment. ### Delivery Includes: - **Test** - Test type: "), Sheet1!R29,"-item multiple choice test - Dimensions: A4 bond paper - Format: PDF, created using LaTeX - **Answer Key** - Format: PDF, created using LaTeX", Sheet2!$D$6) -> *Tinatamad ka ba, walang time, o nahihirapang gumawa ng TOS at First Summative test mo, Grade 7 KasaMath? Kuha ka na ng Basic Assessment Package!* **Bakit perfect para sa’yo ang Basic Assessment Package?** - Makakatipid ka sa oras kaya makakapaghabol pa ng lessons. - Maganda at consistent ang formatting ng test questions at figures. - Ready na ang answer key kaya mas madali at mabilis ang pagche-check. - Ready-to-print exam: sakto sa Budget of Work ang covered topics - Number of days: 15 days - 25-item Multiple Choice test with Answer Key - Para sa teachers na nagmamadali at hindi kailangan ang TOS --- 📑 **Competencies Covered** - Draw and describe regular and irregular polygons with 5, 6, 8, or 10 sides, based on measurements of sides and angles, using a ruler and protractor. - Draw triangles, quadrilaterals, and regular polygons (5, 6, 8, or 10 sides) with given angle measures. - Describe and explain the relationships between angle pairs based on their measures. - Classify polygons according to the number of sides, whether they are regular or irregular. - Classify polygons whether they are convex or non-convex. - Deduce the relationship between the exterior angle and adjacent interior angle of a polygon. --- ## Step 1: I-fill out at i-submit ang Order Form. {{< iframe src="https://cityofsmiles.github.io/auto-order-form/?id=g7-t1-s1-bp" height="850" >}} ## Step 2: Payment and Delivery ### Payment Methods Mag-send ka lang ng ₱59 para sa **First Summative test**. - **Landbank**: 0695077289 (Jonathan R. Bacolod) - **GCash**: 09128389571 (Jonathan Bacolod) - **Maya**: 09128389571 (Jonathan Bacolod) **Isend ang Screenshot ng Payment kahit saan dito:** - Email: [texmathpro@gmail.com](mailto:texmathpro@gmail.com) - Facebook: https://m.me/jonathan.r.bacolod - Telegram: https://t.me/Jonathan_Bacolod Isesend ko ang files sa email address mo after ng payment. ### Delivery Includes: - **Test** - Test type: 25-item multiple choice test - Dimensions: A4 bond paper - Format: PDF, created using LaTeX - **Answer Key** - Format: PDF, created using LaTeX --- Salamat sa pagsuporta sa **TeXMathPro, KasaMath**! Kung may tanong o suggestion ka, [kontakin mo lang ako](mailto:texmathpro@gmail.com). | F29: 59 | G29: 49 | H29: FALSE | I29: 46176 | J29: TRUE | K29: 46179 | L29: --- 📑 **Competencies Covered** - Draw and describe regular and irregular polygons with 5, 6, 8, or 10 sides, based on measurements of sides and angles, using a ruler and protractor. - Draw triangles, quadrilaterals, and regular polygons (5, 6, 8, or 10 sides) with given angle measures. - Describe and explain the relationships between angle pairs based on their measures. - Classify polygons according to the number of sides, whether they are regular or irregular. - Classify polygons whether they are convex or non-convex. - Deduce the relationship between the exterior angle and adjacent interior angle of a polygon. | M29: {=_xlfn.XLOOKUP(TRUE,ISNUMBER(SEARCH(Sheet2!A$23:A$26,A29)),Sheet2!B$23:B$26,"")} -> First Summative test | N29: {=_xlfn.XLOOKUP(TRUE,ISNUMBER(SEARCH(Sheet2!A$32:A$34,A29)),Sheet2!B$32:B$34,"")} -> First Term | O29: {=_xlfn.XLOOKUP(TRUE,ISNUMBER(SEARCH(Sheet2!A$38:A$41,A29)),Sheet2!B$38:B$41,"")} -> Grade 7 | P29: {=_xlfn.XLOOKUP(TRUE,ISNUMBER(SEARCH(Sheet2!A$45:A$47,A29)),Sheet2!B$45:B$47,"")} -> Basic Assessment Package | Q29: 15 | R29: 25
A30: G7-T1-S1-SP | B30: Grade 7 T1 First Summative Test + Answer Key + TOS (Standard) | C30: https://res.cloudinary.com/dadubemrv/image/upload/v1783262649/xa3ma5xtgdbpiti2pulm.png, https://res.cloudinary.com/dadubemrv/image/upload/v1783262653/xelrwfv3qo9fte8tcav5.png, https://res.cloudinary.com/dadubemrv/image/upload/v1783262656/erime3c8h1ngvdbdrwdu.png, https://res.cloudinary.com/dadubemrv/image/upload/v1783262658/s6wrnagjw7rwy2jvrk9h.png | D30: =CONCATENATE("*Tinatamad ka ba, walang time, o nahihirapang gumawa ng TOS at ", Sheet1!M30, " mo, ",Sheet1!O30," KasaMath? Kuha ka na ng ", Sheet1!P30,"!* **Bakit perfect para sa’yo ang ", Sheet1!P30,"?** ",Sheet2!E$17, Sheet1!Q30," days - ", Sheet1!R30,"-item Multiple Choice test with Answer Key - Bagay sa teachers na gusto ng kumpletong exam, answer key, at TOS", _xlfn._LONGTEXT(" [![Sample TOS formatted using 21st Century Skills](https://res.cloudinary.com/dadubemrv/image/upload/v1768351176/tv5zwilsnzrad6r2q6sw.png)](https://res.cloudinary.com/dadubemrv/image/upload/v1768351176/tv5zwilsnzrad6r2q6sw.png) *Sample TOS formatted us","ing 21st Century Skills*"),L30, " --- ## Step 1: I-fill out at i-submit ang Order Form. ", "{{< iframe src=""", "https://cityofsmiles.github.io/auto-order-form/?id=", LOWER(A30), """ height=""850"" >}}"," ## Step 2: Payment and Delivery ### Payment Methods Mag-send ka lang ng ₱",Sheet1!F30," para sa **", Sheet1!M30,_xlfn._LONGTEXT("**. - **Landbank**: 0695077289 (Jonathan R. Bacolod) - **GCash**: 09128389571 (Jonathan Bacolod) - **Maya**: 09128389571 (Jonathan Bacolod) **Isend ang Screenshot ng Payment kahit saan dito:** - Email: [texmathpro@gmail.com](mailto:texmathpro@gm","ail.com) - Facebook: https://m.me/jonathan.r.bacolod - Telegram: https://t.me/Jonathan_Bacolod Isesend ko ang files sa email address mo after ng payment. ### Delivery Includes: - **Test** - Test type: "), Sheet1!R30,"-item multiple choice test - Dimensions: A4 bond paper - Format: PDF, created using LaTeX - **Answer Key** - Format: PDF, created using LaTeX - **Table of Specifications** - XLSX format", Sheet2!$D$6) -> *Tinatamad ka ba, walang time, o nahihirapang gumawa ng TOS at First Summative test mo, Grade 7 KasaMath? Kuha ka na ng Standard Assessment Package!* **Bakit perfect para sa’yo ang Standard Assessment Package?** - Makakatipid ka sa oras kaya makakapaghabol pa ng lessons. - Maganda at consistent ang formatting ng test questions at figures. - Ready na ang answer key kaya mas madali at mabilis ang pagche-check. - Ready-to-print exam: sakto sa Budget of Work ang covered topics - Maaga kang makakapag-submit ng TOS sa head mo. - Table of Specifications using the 21st Century format - Number of days: 15 days - 25-item Multiple Choice test with Answer Key - Bagay sa teachers na gusto ng kumpletong exam, answer key, at TOS [![Sample TOS formatted using 21st Century Skills](https://res.cloudinary.com/dadubemrv/image/upload/v1768351176/tv5zwilsnzrad6r2q6sw.png)](https://res.cloudinary.com/dadubemrv/image/upload/v1768351176/tv5zwilsnzrad6r2q6sw.png) *Sample TOS formatted using 21st Century Skills* --- 📑 **Competencies Covered** - Draw and describe regular and irregular polygons with 5, 6, 8, or 10 sides, based on measurements of sides and angles, using a ruler and protractor. - Draw triangles, quadrilaterals, and regular polygons (5, 6, 8, or 10 sides) with given angle measures. - Describe and explain the relationships between angle pairs based on their measures. - Classify polygons according to the number of sides, whether they are regular or irregular. - Classify polygons whether they are convex or non-convex. - Deduce the relationship between the exterior angle and adjacent interior angle of a polygon. --- ## Step 1: I-fill out at i-submit ang Order Form. {{< iframe src="https://cityofsmiles.github.io/auto-order-form/?id=g7-t1-s1-sp" height="850" >}} ## Step 2: Payment and Delivery ### Payment Methods Mag-send ka lang ng ₱79 para sa **First Summative test**. - **Landbank**: 0695077289 (Jonathan R. Bacolod) - **GCash**: 09128389571 (Jonathan Bacolod) - **Maya**: 09128389571 (Jonathan Bacolod) **Isend ang Screenshot ng Payment kahit saan dito:** - Email: [texmathpro@gmail.com](mailto:texmathpro@gmail.com) - Facebook: https://m.me/jonathan.r.bacolod - Telegram: https://t.me/Jonathan_Bacolod Isesend ko ang files sa email address mo after ng payment. ### Delivery Includes: - **Test** - Test type: 25-item multiple choice test - Dimensions: A4 bond paper - Format: PDF, created using LaTeX - **Answer Key** - Format: PDF, created using LaTeX - **Table of Specifications** - XLSX format --- Salamat sa pagsuporta sa **TeXMathPro, KasaMath**! Kung may tanong o suggestion ka, [kontakin mo lang ako](mailto:texmathpro@gmail.com). | F30: 79 | G30: 69 | H30: FALSE | I30: 46176 | J30: TRUE | K30: 46179 | L30: --- 📑 **Competencies Covered** - Draw and describe regular and irregular polygons with 5, 6, 8, or 10 sides, based on measurements of sides and angles, using a ruler and protractor. - Draw triangles, quadrilaterals, and regular polygons (5, 6, 8, or 10 sides) with given angle measures. - Describe and explain the relationships between angle pairs based on their measures. - Classify polygons according to the number of sides, whether they are regular or irregular. - Classify polygons whether they are convex or non-convex. - Deduce the relationship between the exterior angle and adjacent interior angle of a polygon. | M30: {=_xlfn.XLOOKUP(TRUE,ISNUMBER(SEARCH(Sheet2!A$23:A$26,A30)),Sheet2!B$23:B$26,"")} -> First Summative test | N30: {=_xlfn.XLOOKUP(TRUE,ISNUMBER(SEARCH(Sheet2!A$32:A$34,A30)),Sheet2!B$32:B$34,"")} -> First Term | O30: {=_xlfn.XLOOKUP(TRUE,ISNUMBER(SEARCH(Sheet2!A$38:A$41,A30)),Sheet2!B$38:B$41,"")} -> Grade 7 | P30: {=_xlfn.XLOOKUP(TRUE,ISNUMBER(SEARCH(Sheet2!A$45:A$47,A30)),Sheet2!B$45:B$47,"")} -> Standard Assessment Package | Q30: 15 | R30: 25
A31: G7-T1-S1-CP | B31: Grade 7 T1 First Summative Test + Answer Key + TOS (Custom) | C31: https://res.cloudinary.com/dadubemrv/image/upload/v1783262649/xa3ma5xtgdbpiti2pulm.png, https://res.cloudinary.com/dadubemrv/image/upload/v1783262653/xelrwfv3qo9fte8tcav5.png, https://res.cloudinary.com/dadubemrv/image/upload/v1783262656/erime3c8h1ngvdbdrwdu.png, https://res.cloudinary.com/dadubemrv/image/upload/v1783262658/s6wrnagjw7rwy2jvrk9h.png | D31: =CONCATENATE("*Tinatamad ka ba, walang time, o nahihirapang gumawa ng TOS at ", Sheet1!M31, " mo, ",Sheet1!O31," KasaMath? Kuha ka na ng ", Sheet1!P31,"!* **Bakit perfect para sa’yo ang ", Sheet1!P31,"?** ",Sheet2!F$17," - Perfect sa teachers na gusto ng pasadyang exam", _xlfn._LONGTEXT(" [![Sample TOS formatted using 21st Century Skills](https://res.cloudinary.com/dadubemrv/image/upload/v1768351176/tv5zwilsnzrad6r2q6sw.png)](https://res.cloudinary.com/dadubemrv/image/upload/v1768351176/tv5zwilsnzrad6r2q6sw.png) *Sample TOS formatted us","ing 21st Century Skills*"),L31, " --- ## Step 1: I-fill out at i-submit ang Order Form. ", "{{< iframe src=""", "https://cityofsmiles.github.io/auto-order-form/?id=", LOWER(A31), """ height=""850"" >}}"," ## Step 2: Payment and Delivery ### Payment Methods Mag-send ka lang ng ₱",Sheet1!F31," para sa **", Sheet1!M31,_xlfn._LONGTEXT("**. - **Landbank**: 0695077289 (Jonathan R. Bacolod) - **GCash**: 09128389571 (Jonathan Bacolod) - **Maya**: 09128389571 (Jonathan Bacolod) **Isend ang Screenshot ng Payment kahit saan dito:** - Email: [texmathpro@gmail.com](mailto:texmathpro@gm","ail.com) - Facebook: https://m.me/jonathan.r.bacolod - Telegram: https://t.me/Jonathan_Bacolod Isesend ko ang files sa email address mo after ng payment. ### Delivery Includes: - **Test** - Test type: "), Sheet1!R31,"-item multiple choice test - Dimensions: A4 bond paper - Format: PDF, created using LaTeX - **Answer Key** - Format: PDF, created using LaTeX - **Table of Specifications** - XLSX format", Sheet2!$D$6) -> *Tinatamad ka ba, walang time, o nahihirapang gumawa ng TOS at First Summative test mo, Grade 7 KasaMath? Kuha ka na ng Custom Assessment Package!* **Bakit perfect para sa’yo ang Custom Assessment Package?** - Makakatipid ka sa oras kaya makakapaghabol pa ng lessons. - Maganda at consistent ang formatting ng test questions at figures. - Ready na ang answer key kaya mas madali at mabilis ang pagche-check. - Fully customizable exam: kahit anong topic ang pwedeng covered - Maaga kang makakapag-submit ng TOS sa head mo. - Table of Specifications using the 21st Century format - Number of days: pwede kahit ilan - Number of items: kahit ilan basta maximum of 50 - Perfect sa teachers na gusto ng pasadyang exam [![Sample TOS formatted using 21st Century Skills](https://res.cloudinary.com/dadubemrv/image/upload/v1768351176/tv5zwilsnzrad6r2q6sw.png)](https://res.cloudinary.com/dadubemrv/image/upload/v1768351176/tv5zwilsnzrad6r2q6sw.png) *Sample TOS formatted using 21st Century Skills* --- 📑 **Competencies Covered** - Draw and describe regular and irregular polygons with 5, 6, 8, or 10 sides, based on measurements of sides and angles, using a ruler and protractor. - Draw triangles, quadrilaterals, and regular polygons (5, 6, 8, or 10 sides) with given angle measures. - Describe and explain the relationships between angle pairs based on their measures. - Classify polygons according to the number of sides, whether they are regular or irregular. - Classify polygons whether they are convex or non-convex. - Deduce the relationship between the exterior angle and adjacent interior angle of a polygon. --- ## Step 1: I-fill out at i-submit ang Order Form. {{< iframe src="https://cityofsmiles.github.io/auto-order-form/?id=g7-t1-s1-cp" height="850" >}} ## Step 2: Payment and Delivery ### Payment Methods Mag-send ka lang ng ₱179 para sa **First Summative test**. - **Landbank**: 0695077289 (Jonathan R. Bacolod) - **GCash**: 09128389571 (Jonathan Bacolod) - **Maya**: 09128389571 (Jonathan Bacolod) **Isend ang Screenshot ng Payment kahit saan dito:** - Email: [texmathpro@gmail.com](mailto:texmathpro@gmail.com) - Facebook: https://m.me/jonathan.r.bacolod - Telegram: https://t.me/Jonathan_Bacolod Isesend ko ang files sa email address mo after ng payment. ### Delivery Includes: - **Test** - Test type: 25-50-item multiple choice test - Dimensions: A4 bond paper - Format: PDF, created using LaTeX - **Answer Key** - Format: PDF, created using LaTeX - **Table of Specifications** - XLSX format --- Salamat sa pagsuporta sa **TeXMathPro, KasaMath**! Kung may tanong o suggestion ka, [kontakin mo lang ako](mailto:texmathpro@gmail.com). | F31: 179 | G31: 169 | H31: FALSE | I31: 46176 | J31: TRUE | K31: 46179 | L31: --- 📑 **Competencies Covered** - Draw and describe regular and irregular polygons with 5, 6, 8, or 10 sides, based on measurements of sides and angles, using a ruler and protractor. - Draw triangles, quadrilaterals, and regular polygons (5, 6, 8, or 10 sides) with given angle measures. - Describe and explain the relationships between angle pairs based on their measures. - Classify polygons according to the number of sides, whether they are regular or irregular. - Classify polygons whether they are convex or non-convex. - Deduce the relationship between the exterior angle and adjacent interior angle of a polygon. | M31: {=_xlfn.XLOOKUP(TRUE,ISNUMBER(SEARCH(Sheet2!A$23:A$26,A31)),Sheet2!B$23:B$26,"")} -> First Summative test | N31: {=_xlfn.XLOOKUP(TRUE,ISNUMBER(SEARCH(Sheet2!A$32:A$34,A31)),Sheet2!B$32:B$34,"")} -> First Term | O31: {=_xlfn.XLOOKUP(TRUE,ISNUMBER(SEARCH(Sheet2!A$38:A$41,A31)),Sheet2!B$38:B$41,"")} -> Grade 7 | P31: {=_xlfn.XLOOKUP(TRUE,ISNUMBER(SEARCH(Sheet2!A$45:A$47,A31)),Sheet2!B$45:B$47,"")} -> Custom Assessment Package | R31: 25-50
A32: G7-T1-S2-BP | B32: Grade 7 T1 Second Summative Test + Answer Key (Basic) | C32: https://res.cloudinary.com/dadubemrv/image/upload/v1784692768/blzn2f4qf4csagllrdmj.png,https://res.cloudinary.com/dadubemrv/image/upload/v1784692772/mlwmihwoocbpcd5of6rx.png,https://res.cloudinary.com/dadubemrv/image/upload/v1784692776/adpmufdqkz5qxw5yzj0p.png | D32: =CONCATENATE("*Tinatamad ka ba, walang time, o nahihirapang gumawa ng TOS at ", Sheet1!M32, " mo, ",Sheet1!O32," KasaMath? Kuha ka na ng ", Sheet1!P32,"!* **Bakit perfect para sa’yo ang ", Sheet1!P32,"?** ",Sheet2!D$17, Sheet1!Q32," days - ", Sheet1!R32,"-item Multiple Choice test with Answer Key - Para sa teachers na nagmamadali at hindi kailangan ang TOS", L32, " --- ## Step 1: I-fill out at i-submit ang Order Form. ", "{{< iframe src=""", "https://cityofsmiles.github.io/auto-order-form/?id=", LOWER(A32), """ height=""850"" >}}"," ## Step 2: Payment and Delivery ### Payment Methods Mag-send ka lang ng ₱",Sheet1!F32," para sa **", Sheet1!M32,_xlfn._LONGTEXT("**. - **Landbank**: 0695077289 (Jonathan R. Bacolod) - **GCash**: 09128389571 (Jonathan Bacolod) - **Maya**: 09128389571 (Jonathan Bacolod) **Isend ang Screenshot ng Payment kahit saan dito:** - Email: [texmathpro@gmail.com](mailto:texmathpro@gm","ail.com) - Facebook: https://m.me/jonathan.r.bacolod - Telegram: https://t.me/Jonathan_Bacolod Isesend ko ang files sa email address mo after ng payment. ### Delivery Includes: - **Test** - Test type: "), Sheet1!R32,"-item multiple choice test - Dimensions: A4 bond paper - Format: PDF, created using LaTeX - **Answer Key** - Format: PDF, created using LaTeX", Sheet2!$D$6) -> *Tinatamad ka ba, walang time, o nahihirapang gumawa ng TOS at Second Summative test mo, Grade 7 KasaMath? Kuha ka na ng Basic Assessment Package!* **Bakit perfect para sa’yo ang Basic Assessment Package?** - Makakatipid ka sa oras kaya makakapaghabol pa ng lessons. - Maganda at consistent ang formatting ng test questions at figures. - Ready na ang answer key kaya mas madali at mabilis ang pagche-check. - Ready-to-print exam: sakto sa Budget of Work ang covered topics - Number of days: 15 days - 25-item Multiple Choice test with Answer Key - Para sa teachers na nagmamadali at hindi kailangan ang TOS --- 📑 **Competencies Covered** - Determine the measures of angles of polygons. - Determine the number of sides of polygons. - Solve problems involving percentage increase and percentage decrease. - Solve money problems involving percentages (e. g., discount, commission, sales tax, simple interest). - Create a financial plan. --- ## Step 1: I-fill out at i-submit ang Order Form. {{< iframe src="https://cityofsmiles.github.io/auto-order-form/?id=g7-t1-s2-bp" height="850" >}} ## Step 2: Payment and Delivery ### Payment Methods Mag-send ka lang ng ₱59 para sa **Second Summative test**. - **Landbank**: 0695077289 (Jonathan R. Bacolod) - **GCash**: 09128389571 (Jonathan Bacolod) - **Maya**: 09128389571 (Jonathan Bacolod) **Isend ang Screenshot ng Payment kahit saan dito:** - Email: [texmathpro@gmail.com](mailto:texmathpro@gmail.com) - Facebook: https://m.me/jonathan.r.bacolod - Telegram: https://t.me/Jonathan_Bacolod Isesend ko ang files sa email address mo after ng payment. ### Delivery Includes: - **Test** - Test type: 25-item multiple choice test - Dimensions: A4 bond paper - Format: PDF, created using LaTeX - **Answer Key** - Format: PDF, created using LaTeX --- Salamat sa pagsuporta sa **TeXMathPro, KasaMath**! Kung may tanong o suggestion ka, [kontakin mo lang ako](mailto:texmathpro@gmail.com). | F32: 59 | G32: 49 | H32: FALSE | I32: 46176 | J32: TRUE | K32: 46179 | L32: --- 📑 **Competencies Covered** - Determine the measures of angles of polygons. - Determine the number of sides of polygons. - Solve problems involving percentage increase and percentage decrease. - Solve money problems involving percentages (e. g., discount, commission, sales tax, simple interest). - Create a financial plan. | M32: {=_xlfn.XLOOKUP(TRUE,ISNUMBER(SEARCH(Sheet2!A$23:A$26,A32)),Sheet2!B$23:B$26,"")} -> Second Summative test | N32: {=_xlfn.XLOOKUP(TRUE,ISNUMBER(SEARCH(Sheet2!A$32:A$34,A32)),Sheet2!B$32:B$34,"")} -> First Term | O32: {=_xlfn.XLOOKUP(TRUE,ISNUMBER(SEARCH(Sheet2!A$38:A$41,A32)),Sheet2!B$38:B$41,"")} -> Grade 7 | P32: {=_xlfn.XLOOKUP(TRUE,ISNUMBER(SEARCH(Sheet2!A$45:A$47,A32)),Sheet2!B$45:B$47,"")} -> Basic Assessment Package | Q32: 15 | R32: 25
A33: G7-T1-S2-SP | B33: Grade 7 T1 Second Summative Test + Answer Key + TOS (Standard) | C33: https://res.cloudinary.com/dadubemrv/image/upload/v1784692768/blzn2f4qf4csagllrdmj.png,https://res.cloudinary.com/dadubemrv/image/upload/v1784692772/mlwmihwoocbpcd5of6rx.png,https://res.cloudinary.com/dadubemrv/image/upload/v1784692776/adpmufdqkz5qxw5yzj0p.png | D33: =CONCATENATE("*Tinatamad ka ba, walang time, o nahihirapang gumawa ng TOS at ", Sheet1!M33, " mo, ",Sheet1!O33," KasaMath? Kuha ka na ng ", Sheet1!P33,"!* **Bakit perfect para sa’yo ang ", Sheet1!P33,"?** ",Sheet2!E$17, Sheet1!Q33," days - ", Sheet1!R33,"-item Multiple Choice test with Answer Key - Bagay sa teachers na gusto ng kumpletong exam, answer key, at TOS", _xlfn._LONGTEXT(" [![Sample TOS formatted using 21st Century Skills](https://res.cloudinary.com/dadubemrv/image/upload/v1768351176/tv5zwilsnzrad6r2q6sw.png)](https://res.cloudinary.com/dadubemrv/image/upload/v1768351176/tv5zwilsnzrad6r2q6sw.png) *Sample TOS formatted us","ing 21st Century Skills*"),L33, " --- ## Step 1: I-fill out at i-submit ang Order Form. ", "{{< iframe src=""", "https://cityofsmiles.github.io/auto-order-form/?id=", LOWER(A33), """ height=""850"" >}}"," ## Step 2: Payment and Delivery ### Payment Methods Mag-send ka lang ng ₱",Sheet1!F33," para sa **", Sheet1!M33,_xlfn._LONGTEXT("**. - **Landbank**: 0695077289 (Jonathan R. Bacolod) - **GCash**: 09128389571 (Jonathan Bacolod) - **Maya**: 09128389571 (Jonathan Bacolod) **Isend ang Screenshot ng Payment kahit saan dito:** - Email: [texmathpro@gmail.com](mailto:texmathpro@gm","ail.com) - Facebook: https://m.me/jonathan.r.bacolod - Telegram: https://t.me/Jonathan_Bacolod Isesend ko ang files sa email address mo after ng payment. ### Delivery Includes: - **Test** - Test type: "), Sheet1!R33,"-item multiple choice test - Dimensions: A4 bond paper - Format: PDF, created using LaTeX - **Answer Key** - Format: PDF, created using LaTeX - **Table of Specifications** - XLSX format", Sheet2!$D$6) -> *Tinatamad ka ba, walang time, o nahihirapang gumawa ng TOS at Second Summative test mo, Grade 7 KasaMath? Kuha ka na ng Standard Assessment Package!* **Bakit perfect para sa’yo ang Standard Assessment Package?** - Makakatipid ka sa oras kaya makakapaghabol pa ng lessons. - Maganda at consistent ang formatting ng test questions at figures. - Ready na ang answer key kaya mas madali at mabilis ang pagche-check. - Ready-to-print exam: sakto sa Budget of Work ang covered topics - Maaga kang makakapag-submit ng TOS sa head mo. - Table of Specifications using the 21st Century format - Number of days: 15 days - 25-item Multiple Choice test with Answer Key - Bagay sa teachers na gusto ng kumpletong exam, answer key, at TOS [![Sample TOS formatted using 21st Century Skills](https://res.cloudinary.com/dadubemrv/image/upload/v1768351176/tv5zwilsnzrad6r2q6sw.png)](https://res.cloudinary.com/dadubemrv/image/upload/v1768351176/tv5zwilsnzrad6r2q6sw.png) *Sample TOS formatted using 21st Century Skills* --- 📑 **Competencies Covered** - Determine the measures of angles of polygons. - Determine the number of sides of polygons. - Solve problems involving percentage increase and percentage decrease. - Solve money problems involving percentages (e. g., discount, commission, sales tax, simple interest). - Create a financial plan. --- ## Step 1: I-fill out at i-submit ang Order Form. {{< iframe src="https://cityofsmiles.github.io/auto-order-form/?id=g7-t1-s2-sp" height="850" >}} ## Step 2: Payment and Delivery ### Payment Methods Mag-send ka lang ng ₱79 para sa **Second Summative test**. - **Landbank**: 0695077289 (Jonathan R. Bacolod) - **GCash**: 09128389571 (Jonathan Bacolod) - **Maya**: 09128389571 (Jonathan Bacolod) **Isend ang Screenshot ng Payment kahit saan dito:** - Email: [texmathpro@gmail.com](mailto:texmathpro@gmail.com) - Facebook: https://m.me/jonathan.r.bacolod - Telegram: https://t.me/Jonathan_Bacolod Isesend ko ang files sa email address mo after ng payment. ### Delivery Includes: - **Test** - Test type: 25-item multiple choice test - Dimensions: A4 bond paper - Format: PDF, created using LaTeX - **Answer Key** - Format: PDF, created using LaTeX - **Table of Specifications** - XLSX format --- Salamat sa pagsuporta sa **TeXMathPro, KasaMath**! Kung may tanong o suggestion ka, [kontakin mo lang ako](mailto:texmathpro@gmail.com). | F33: 79 | G33: 69 | H33: FALSE | I33: 46176 | J33: TRUE | K33: 46179 | L33: --- 📑 **Competencies Covered** - Determine the measures of angles of polygons. - Determine the number of sides of polygons. - Solve problems involving percentage increase and percentage decrease. - Solve money problems involving percentages (e. g., discount, commission, sales tax, simple interest). - Create a financial plan. | M33: {=_xlfn.XLOOKUP(TRUE,ISNUMBER(SEARCH(Sheet2!A$23:A$26,A33)),Sheet2!B$23:B$26,"")} -> Second Summative test | N33: {=_xlfn.XLOOKUP(TRUE,ISNUMBER(SEARCH(Sheet2!A$32:A$34,A33)),Sheet2!B$32:B$34,"")} -> First Term | O33: {=_xlfn.XLOOKUP(TRUE,ISNUMBER(SEARCH(Sheet2!A$38:A$41,A33)),Sheet2!B$38:B$41,"")} -> Grade 7 | P33: {=_xlfn.XLOOKUP(TRUE,ISNUMBER(SEARCH(Sheet2!A$45:A$47,A33)),Sheet2!B$45:B$47,"")} -> Standard Assessment Package | Q33: 15 | R33: 25
A34: G7-T1-S2-CP | B34: Grade 7 T1 Second Summative Test + Answer Key + TOS (Custom) | C34: https://res.cloudinary.com/dadubemrv/image/upload/v1784692768/blzn2f4qf4csagllrdmj.png,https://res.cloudinary.com/dadubemrv/image/upload/v1784692772/mlwmihwoocbpcd5of6rx.png,https://res.cloudinary.com/dadubemrv/image/upload/v1784692776/adpmufdqkz5qxw5yzj0p.png | D34: =CONCATENATE("*Tinatamad ka ba, walang time, o nahihirapang gumawa ng TOS at ", Sheet1!M34, " mo, ",Sheet1!O34," KasaMath? Kuha ka na ng ", Sheet1!P34,"!* **Bakit perfect para sa’yo ang ", Sheet1!P34,"?** ",Sheet2!F$17," - Perfect sa teachers na gusto ng pasadyang exam", _xlfn._LONGTEXT(" [![Sample TOS formatted using 21st Century Skills](https://res.cloudinary.com/dadubemrv/image/upload/v1768351176/tv5zwilsnzrad6r2q6sw.png)](https://res.cloudinary.com/dadubemrv/image/upload/v1768351176/tv5zwilsnzrad6r2q6sw.png) *Sample TOS formatted us","ing 21st Century Skills*"),L34, " --- ## Step 1: I-fill out at i-submit ang Order Form. ", "{{< iframe src=""", "https://cityofsmiles.github.io/auto-order-form/?id=", LOWER(A34), """ height=""850"" >}}"," ## Step 2: Payment and Delivery ### Payment Methods Mag-send ka lang ng ₱",Sheet1!F34," para sa **", Sheet1!M34,_xlfn._LONGTEXT("**. - **Landbank**: 0695077289 (Jonathan R. Bacolod) - **GCash**: 09128389571 (Jonathan Bacolod) - **Maya**: 09128389571 (Jonathan Bacolod) **Isend ang Screenshot ng Payment kahit saan dito:** - Email: [texmathpro@gmail.com](mailto:texmathpro@gm","ail.com) - Facebook: https://m.me/jonathan.r.bacolod - Telegram: https://t.me/Jonathan_Bacolod Isesend ko ang files sa email address mo after ng payment. ### Delivery Includes: - **Test** - Test type: "), Sheet1!R34,"-item multiple choice test - Dimensions: A4 bond paper - Format: PDF, created using LaTeX - **Answer Key** - Format: PDF, created using LaTeX - **Table of Specifications** - XLSX format", Sheet2!$D$6) -> *Tinatamad ka ba, walang time, o nahihirapang gumawa ng TOS at Second Summative test mo, Grade 7 KasaMath? Kuha ka na ng Custom Assessment Package!* **Bakit perfect para sa’yo ang Custom Assessment Package?** - Makakatipid ka sa oras kaya makakapaghabol pa ng lessons. - Maganda at consistent ang formatting ng test questions at figures. - Ready na ang answer key kaya mas madali at mabilis ang pagche-check. - Fully customizable exam: kahit anong topic ang pwedeng covered - Maaga kang makakapag-submit ng TOS sa head mo. - Table of Specifications using the 21st Century format - Number of days: pwede kahit ilan - Number of items: kahit ilan basta maximum of 50 - Perfect sa teachers na gusto ng pasadyang exam [![Sample TOS formatted using 21st Century Skills](https://res.cloudinary.com/dadubemrv/image/upload/v1768351176/tv5zwilsnzrad6r2q6sw.png)](https://res.cloudinary.com/dadubemrv/image/upload/v1768351176/tv5zwilsnzrad6r2q6sw.png) *Sample TOS formatted using 21st Century Skills* --- 📑 **Competencies Covered** - Determine the measures of angles of polygons. - Determine the number of sides of polygons. - Solve problems involving percentage increase and percentage decrease. - Solve money problems involving percentages (e. g., discount, commission, sales tax, simple interest). - Create a financial plan. --- ## Step 1: I-fill out at i-submit ang Order Form. {{< iframe src="https://cityofsmiles.github.io/auto-order-form/?id=g7-t1-s2-cp" height="850" >}} ## Step 2: Payment and Delivery ### Payment Methods Mag-send ka lang ng ₱179 para sa **Second Summative test**. - **Landbank**: 0695077289 (Jonathan R. Bacolod) - **GCash**: 09128389571 (Jonathan Bacolod) - **Maya**: 09128389571 (Jonathan Bacolod) **Isend ang Screenshot ng Payment kahit saan dito:** - Email: [texmathpro@gmail.com](mailto:texmathpro@gmail.com) - Facebook: https://m.me/jonathan.r.bacolod - Telegram: https://t.me/Jonathan_Bacolod Isesend ko ang files sa email address mo after ng payment. ### Delivery Includes: - **Test** - Test type: 25-50-item multiple choice test - Dimensions: A4 bond paper - Format: PDF, created using LaTeX - **Answer Key** - Format: PDF, created using LaTeX - **Table of Specifications** - XLSX format --- Salamat sa pagsuporta sa **TeXMathPro, KasaMath**! Kung may tanong o suggestion ka, [kontakin mo lang ako](mailto:texmathpro@gmail.com). | F34: 179 | G34: 169 | H34: FALSE | I34: 46176 | J34: TRUE | K34: 46179 | L34: --- 📑 **Competencies Covered** - Determine the measures of angles of polygons. - Determine the number of sides of polygons. - Solve problems involving percentage increase and percentage decrease. - Solve money problems involving percentages (e. g., discount, commission, sales tax, simple interest). - Create a financial plan. | M34: {=_xlfn.XLOOKUP(TRUE,ISNUMBER(SEARCH(Sheet2!A$23:A$26,A34)),Sheet2!B$23:B$26,"")} -> Second Summative test | N34: {=_xlfn.XLOOKUP(TRUE,ISNUMBER(SEARCH(Sheet2!A$32:A$34,A34)),Sheet2!B$32:B$34,"")} -> First Term | O34: {=_xlfn.XLOOKUP(TRUE,ISNUMBER(SEARCH(Sheet2!A$38:A$41,A34)),Sheet2!B$38:B$41,"")} -> Grade 7 | P34: {=_xlfn.XLOOKUP(TRUE,ISNUMBER(SEARCH(Sheet2!A$45:A$47,A34)),Sheet2!B$45:B$47,"")} -> Custom Assessment Package | R34: 25-50
A35: G8-T1-S1-BP | B35: Grade 8 T1 First Summative Test + TOS + Answer Key (Basic) | C35: https://i.imgur.com/dqV0sYm.jpeg | D35: =Sheet2!$D$2 -> 0 | F35: 120 | G35: 84 | H35: FALSE | I35: 46176 | J35: FALSE | K35: 46176
A36: G8-T1-S1-SP | B36: Grade 8 T1 First Summative Test + TOS + Answer Key (Standard) | C36: https://i.imgur.com/dqV0sYm.jpeg | D36: =Sheet2!$E$2 -> 0 | F36: 165 | G36: 115 | H36: FALSE | I36: 46176 | J36: FALSE | K36: 46176
A37: G8-T1-S1-CP | B37: Grade 8 T1 First Summative Test + TOS + Answer Key (Custom) | C37: https://i.imgur.com/dqV0sYm.jpeg | D37: =Sheet2!$F$2 -> 0 | F37: 350 | G37: 245 | H37: FALSE | I37: 46176 | J37: FALSE | K37: 46176
A38: G9-T1-S1-BP | B38: Grade 9 T1 First Summative Test + Answer Key (Basic) | C38: https://res.cloudinary.com/dadubemrv/image/upload/v1783263602/yd7hsdwqb5dk19s6pakw.png,https://res.cloudinary.com/dadubemrv/image/upload/v1783263605/ujoydnhzuhsnv7yic56j.png,https://res.cloudinary.com/dadubemrv/image/upload/v1783263608/d8tvcndvdvbcscplmsni.png,https://res.cloudinary.com/dadubemrv/image/upload/v1783263611/xnrnsjt720lvbgoycchm.png | D38: =CONCATENATE("*Tinatamad ka ba, walang time, o nahihirapang gumawa ng TOS at ", Sheet1!M38, " mo, ",Sheet1!O38," KasaMath? Kuha ka na ng ", Sheet1!P38,"!* **Bakit perfect para sa’yo ang ", Sheet1!P38,"?** ",Sheet2!D$17, Sheet1!Q38," days - ", Sheet1!R38,"-item Multiple Choice test with Answer Key - Para sa teachers na nagmamadali at hindi kailangan ang TOS", L38, " --- ## Step 1: I-fill out at i-submit ang Order Form. ", "{{< iframe src=""", "https://cityofsmiles.github.io/auto-order-form/?id=", LOWER(A38), """ height=""850"" >}}"," ## Step 2: Payment and Delivery ### Payment Methods Mag-send ka lang ng ₱",Sheet1!F38," para sa **", Sheet1!M38,_xlfn._LONGTEXT("**. - **Landbank**: 0695077289 (Jonathan R. Bacolod) - **GCash**: 09128389571 (Jonathan Bacolod) - **Maya**: 09128389571 (Jonathan Bacolod) **Isend ang Screenshot ng Payment kahit saan dito:** - Email: [texmathpro@gmail.com](mailto:texmathpro@gm","ail.com) - Facebook: https://m.me/jonathan.r.bacolod - Telegram: https://t.me/Jonathan_Bacolod Isesend ko ang files sa email address mo after ng payment. ### Delivery Includes: - **Test** - Test type: "), Sheet1!R38,"-item multiple choice test - Dimensions: A4 bond paper - Format: PDF, created using LaTeX - **Answer Key** - Format: PDF, created using LaTeX", Sheet2!$D$6) -> *Tinatamad ka ba, walang time, o nahihirapang gumawa ng TOS at First Summative test mo, Grade 9 KasaMath? Kuha ka na ng Basic Assessment Package!* **Bakit perfect para sa’yo ang Basic Assessment Package?** - Makakatipid ka sa oras kaya makakapaghabol pa ng lessons. - Maganda at consistent ang formatting ng test questions at figures. - Ready na ang answer key kaya mas madali at mabilis ang pagche-check. - Ready-to-print exam: sakto sa Budget of Work ang covered topics - Number of days: 15 days - 25-item Multiple Choice test with Answer Key - Para sa teachers na nagmamadali at hindi kailangan ang TOS --- 📑 **Competencies Covered** - Illustrate and describe point, line, ray, line segment, angle, and plane using models and geometric notations. - Construct perpendicular and parallel lines. - Identify the relationships between angles formed by parallel lines cut by a transversal. - Determine angle measures involving angle pairs, parallel and perpendicular lines, and parallel lines cut by a transversal. - Identify relations that are functions based on the definitions of relations and functions. - Determine the domain and range of a function expressed in different representations. --- ## Step 1: I-fill out at i-submit ang Order Form. {{< iframe src="https://cityofsmiles.github.io/auto-order-form/?id=g9-t1-s1-bp" height="850" >}} ## Step 2: Payment and Delivery ### Payment Methods Mag-send ka lang ng ₱59 para sa **First Summative test**. - **Landbank**: 0695077289 (Jonathan R. Bacolod) - **GCash**: 09128389571 (Jonathan Bacolod) - **Maya**: 09128389571 (Jonathan Bacolod) **Isend ang Screenshot ng Payment kahit saan dito:** - Email: [texmathpro@gmail.com](mailto:texmathpro@gmail.com) - Facebook: https://m.me/jonathan.r.bacolod - Telegram: https://t.me/Jonathan_Bacolod Isesend ko ang files sa email address mo after ng payment. ### Delivery Includes: - **Test** - Test type: 25-item multiple choice test - Dimensions: A4 bond paper - Format: PDF, created using LaTeX - **Answer Key** - Format: PDF, created using LaTeX --- Salamat sa pagsuporta sa **TeXMathPro, KasaMath**! Kung may tanong o suggestion ka, [kontakin mo lang ako](mailto:texmathpro@gmail.com). | F38: 59 | G38: 49 | H38: FALSE | I38: 46176 | J38: TRUE | K38: 46179 | L38: --- 📑 **Competencies Covered** - Illustrate and describe point, line, ray, line segment, angle, and plane using models and geometric notations. - Construct perpendicular and parallel lines. - Identify the relationships between angles formed by parallel lines cut by a transversal. - Determine angle measures involving angle pairs, parallel and perpendicular lines, and parallel lines cut by a transversal. - Identify relations that are functions based on the definitions of relations and functions. - Determine the domain and range of a function expressed in different representations. | M38: {=_xlfn.XLOOKUP(TRUE,ISNUMBER(SEARCH(Sheet2!A$23:A$26,A38)),Sheet2!B$23:B$26,"")} -> First Summative test | N38: {=_xlfn.XLOOKUP(TRUE,ISNUMBER(SEARCH(Sheet2!A$32:A$34,A38)),Sheet2!B$32:B$34,"")} -> First Term | O38: {=_xlfn.XLOOKUP(TRUE,ISNUMBER(SEARCH(Sheet2!A$38:A$41,A38)),Sheet2!B$38:B$41,"")} -> Grade 9 | P38: {=_xlfn.XLOOKUP(TRUE,ISNUMBER(SEARCH(Sheet2!A$45:A$47,A38)),Sheet2!B$45:B$47,"")} -> Basic Assessment Package | Q38: 15 | R38: 25
A39: G9-T1-S1-SP | B39: Grade 9 T1 First Summative Test + Answer Key + TOS (Standard) | C39: https://res.cloudinary.com/dadubemrv/image/upload/v1783263602/yd7hsdwqb5dk19s6pakw.png,https://res.cloudinary.com/dadubemrv/image/upload/v1783263605/ujoydnhzuhsnv7yic56j.png,https://res.cloudinary.com/dadubemrv/image/upload/v1783263608/d8tvcndvdvbcscplmsni.png,https://res.cloudinary.com/dadubemrv/image/upload/v1783263611/xnrnsjt720lvbgoycchm.png | D39: =CONCATENATE("*Tinatamad ka ba, walang time, o nahihirapang gumawa ng TOS at ", Sheet1!M39, " mo, ",Sheet1!O39," KasaMath? Kuha ka na ng ", Sheet1!P39,"!* **Bakit perfect para sa’yo ang ", Sheet1!P39,"?** ",Sheet2!E$17, Sheet1!Q39," days - ", Sheet1!R39,"-item Multiple Choice test with Answer Key - Bagay sa teachers na gusto ng kumpletong exam, answer key, at TOS", _xlfn._LONGTEXT(" [![Sample TOS formatted using 21st Century Skills](https://res.cloudinary.com/dadubemrv/image/upload/v1768351176/tv5zwilsnzrad6r2q6sw.png)](https://res.cloudinary.com/dadubemrv/image/upload/v1768351176/tv5zwilsnzrad6r2q6sw.png) *Sample TOS formatted us","ing 21st Century Skills*"),L39, " --- ## Step 1: I-fill out at i-submit ang Order Form. ", "{{< iframe src=""", "https://cityofsmiles.github.io/auto-order-form/?id=", LOWER(A39), """ height=""850"" >}}"," ## Step 2: Payment and Delivery ### Payment Methods Mag-send ka lang ng ₱",Sheet1!F39," para sa **", Sheet1!M39,_xlfn._LONGTEXT("**. - **Landbank**: 0695077289 (Jonathan R. Bacolod) - **GCash**: 09128389571 (Jonathan Bacolod) - **Maya**: 09128389571 (Jonathan Bacolod) **Isend ang Screenshot ng Payment kahit saan dito:** - Email: [texmathpro@gmail.com](mailto:texmathpro@gm","ail.com) - Facebook: https://m.me/jonathan.r.bacolod - Telegram: https://t.me/Jonathan_Bacolod Isesend ko ang files sa email address mo after ng payment. ### Delivery Includes: - **Test** - Test type: "), Sheet1!R39,"-item multiple choice test - Dimensions: A4 bond paper - Format: PDF, created using LaTeX - **Answer Key** - Format: PDF, created using LaTeX - **Table of Specifications** - XLSX format", Sheet2!$D$6) -> *Tinatamad ka ba, walang time, o nahihirapang gumawa ng TOS at First Summative test mo, Grade 9 KasaMath? Kuha ka na ng Standard Assessment Package!* **Bakit perfect para sa’yo ang Standard Assessment Package?** - Makakatipid ka sa oras kaya makakapaghabol pa ng lessons. - Maganda at consistent ang formatting ng test questions at figures. - Ready na ang answer key kaya mas madali at mabilis ang pagche-check. - Ready-to-print exam: sakto sa Budget of Work ang covered topics - Maaga kang makakapag-submit ng TOS sa head mo. - Table of Specifications using the 21st Century format - Number of days: 15 days - 25-item Multiple Choice test with Answer Key - Bagay sa teachers na gusto ng kumpletong exam, answer key, at TOS [![Sample TOS formatted using 21st Century Skills](https://res.cloudinary.com/dadubemrv/image/upload/v1768351176/tv5zwilsnzrad6r2q6sw.png)](https://res.cloudinary.com/dadubemrv/image/upload/v1768351176/tv5zwilsnzrad6r2q6sw.png) *Sample TOS formatted using 21st Century Skills* --- 📑 **Competencies Covered** - Illustrate and describe point, line, ray, line segment, angle, and plane using models and geometric notations. - Construct perpendicular and parallel lines. - Identify the relationships between angles formed by parallel lines cut by a transversal. - Determine angle measures involving angle pairs, parallel and perpendicular lines, and parallel lines cut by a transversal. - Identify relations that are functions based on the definitions of relations and functions. - Determine the domain and range of a function expressed in different representations. --- ## Step 1: I-fill out at i-submit ang Order Form. {{< iframe src="https://cityofsmiles.github.io/auto-order-form/?id=g9-t1-s1-sp" height="850" >}} ## Step 2: Payment and Delivery ### Payment Methods Mag-send ka lang ng ₱79 para sa **First Summative test**. - **Landbank**: 0695077289 (Jonathan R. Bacolod) - **GCash**: 09128389571 (Jonathan Bacolod) - **Maya**: 09128389571 (Jonathan Bacolod) **Isend ang Screenshot ng Payment kahit saan dito:** - Email: [texmathpro@gmail.com](mailto:texmathpro@gmail.com) - Facebook: https://m.me/jonathan.r.bacolod - Telegram: https://t.me/Jonathan_Bacolod Isesend ko ang files sa email address mo after ng payment. ### Delivery Includes: - **Test** - Test type: 25-item multiple choice test - Dimensions: A4 bond paper - Format: PDF, created using LaTeX - **Answer Key** - Format: PDF, created using LaTeX - **Table of Specifications** - XLSX format --- Salamat sa pagsuporta sa **TeXMathPro, KasaMath**! Kung may tanong o suggestion ka, [kontakin mo lang ako](mailto:texmathpro@gmail.com). | F39: 79 | G39: 69 | H39: FALSE | I39: 46176 | J39: TRUE | K39: 46179 | L39: --- 📑 **Competencies Covered** - Illustrate and describe point, line, ray, line segment, angle, and plane using models and geometric notations. - Construct perpendicular and parallel lines. - Identify the relationships between angles formed by parallel lines cut by a transversal. - Determine angle measures involving angle pairs, parallel and perpendicular lines, and parallel lines cut by a transversal. - Identify relations that are functions based on the definitions of relations and functions. - Determine the domain and range of a function expressed in different representations. | M39: {=_xlfn.XLOOKUP(TRUE,ISNUMBER(SEARCH(Sheet2!A$23:A$26,A39)),Sheet2!B$23:B$26,"")} -> First Summative test | N39: {=_xlfn.XLOOKUP(TRUE,ISNUMBER(SEARCH(Sheet2!A$32:A$34,A39)),Sheet2!B$32:B$34,"")} -> First Term | O39: {=_xlfn.XLOOKUP(TRUE,ISNUMBER(SEARCH(Sheet2!A$38:A$41,A39)),Sheet2!B$38:B$41,"")} -> Grade 9 | P39: {=_xlfn.XLOOKUP(TRUE,ISNUMBER(SEARCH(Sheet2!A$45:A$47,A39)),Sheet2!B$45:B$47,"")} -> Standard Assessment Package | Q39: 15 | R39: 25
A40: G9-T1-S1-CP | B40: Grade 9 T1 First Summative Test + Answer Key + TOS (Custom) | C40: https://res.cloudinary.com/dadubemrv/image/upload/v1783263602/yd7hsdwqb5dk19s6pakw.png,https://res.cloudinary.com/dadubemrv/image/upload/v1783263605/ujoydnhzuhsnv7yic56j.png,https://res.cloudinary.com/dadubemrv/image/upload/v1783263608/d8tvcndvdvbcscplmsni.png,https://res.cloudinary.com/dadubemrv/image/upload/v1783263611/xnrnsjt720lvbgoycchm.png | D40: =CONCATENATE("*Tinatamad ka ba, walang time, o nahihirapang gumawa ng TOS at ", Sheet1!M40, " mo, ",Sheet1!O40," KasaMath? Kuha ka na ng ", Sheet1!P40,"!* **Bakit perfect para sa’yo ang ", Sheet1!P40,"?** ",Sheet2!F$17," - Perfect sa teachers na gusto ng pasadyang exam", _xlfn._LONGTEXT(" [![Sample TOS formatted using 21st Century Skills](https://res.cloudinary.com/dadubemrv/image/upload/v1768351176/tv5zwilsnzrad6r2q6sw.png)](https://res.cloudinary.com/dadubemrv/image/upload/v1768351176/tv5zwilsnzrad6r2q6sw.png) *Sample TOS formatted us","ing 21st Century Skills*"),L40, " --- ## Step 1: I-fill out at i-submit ang Order Form. ", "{{< iframe src=""", "https://cityofsmiles.github.io/auto-order-form/?id=", LOWER(A40), """ height=""850"" >}}"," ## Step 2: Payment and Delivery ### Payment Methods Mag-send ka lang ng ₱",Sheet1!F40," para sa **", Sheet1!M40,_xlfn._LONGTEXT("**. - **Landbank**: 0695077289 (Jonathan R. Bacolod) - **GCash**: 09128389571 (Jonathan Bacolod) - **Maya**: 09128389571 (Jonathan Bacolod) **Isend ang Screenshot ng Payment kahit saan dito:** - Email: [texmathpro@gmail.com](mailto:texmathpro@gm","ail.com) - Facebook: https://m.me/jonathan.r.bacolod - Telegram: https://t.me/Jonathan_Bacolod Isesend ko ang files sa email address mo after ng payment. ### Delivery Includes: - **Test** - Test type: "), Sheet1!R40,"-item multiple choice test - Dimensions: A4 bond paper - Format: PDF, created using LaTeX - **Answer Key** - Format: PDF, created using LaTeX - **Table of Specifications** - XLSX format", Sheet2!$D$6) -> *Tinatamad ka ba, walang time, o nahihirapang gumawa ng TOS at First Summative test mo, Grade 9 KasaMath? Kuha ka na ng Custom Assessment Package!* **Bakit perfect para sa’yo ang Custom Assessment Package?** - Makakatipid ka sa oras kaya makakapaghabol pa ng lessons. - Maganda at consistent ang formatting ng test questions at figures. - Ready na ang answer key kaya mas madali at mabilis ang pagche-check. - Fully customizable exam: kahit anong topic ang pwedeng covered - Maaga kang makakapag-submit ng TOS sa head mo. - Table of Specifications using the 21st Century format - Number of days: pwede kahit ilan - Number of items: kahit ilan basta maximum of 50 - Perfect sa teachers na gusto ng pasadyang exam [![Sample TOS formatted using 21st Century Skills](https://res.cloudinary.com/dadubemrv/image/upload/v1768351176/tv5zwilsnzrad6r2q6sw.png)](https://res.cloudinary.com/dadubemrv/image/upload/v1768351176/tv5zwilsnzrad6r2q6sw.png) *Sample TOS formatted using 21st Century Skills* --- 📑 **Competencies Covered** - Illustrate and describe point, line, ray, line segment, angle, and plane using models and geometric notations. - Construct perpendicular and parallel lines. - Identify the relationships between angles formed by parallel lines cut by a transversal. - Determine angle measures involving angle pairs, parallel and perpendicular lines, and parallel lines cut by a transversal. - Identify relations that are functions based on the definitions of relations and functions. - Determine the domain and range of a function expressed in different representations. --- ## Step 1: I-fill out at i-submit ang Order Form. {{< iframe src="https://cityofsmiles.github.io/auto-order-form/?id=g9-t1-s1-cp" height="850" >}} ## Step 2: Payment and Delivery ### Payment Methods Mag-send ka lang ng ₱179 para sa **First Summative test**. - **Landbank**: 0695077289 (Jonathan R. Bacolod) - **GCash**: 09128389571 (Jonathan Bacolod) - **Maya**: 09128389571 (Jonathan Bacolod) **Isend ang Screenshot ng Payment kahit saan dito:** - Email: [texmathpro@gmail.com](mailto:texmathpro@gmail.com) - Facebook: https://m.me/jonathan.r.bacolod - Telegram: https://t.me/Jonathan_Bacolod Isesend ko ang files sa email address mo after ng payment. ### Delivery Includes: - **Test** - Test type: 25-50-item multiple choice test - Dimensions: A4 bond paper - Format: PDF, created using LaTeX - **Answer Key** - Format: PDF, created using LaTeX - **Table of Specifications** - XLSX format --- Salamat sa pagsuporta sa **TeXMathPro, KasaMath**! Kung may tanong o suggestion ka, [kontakin mo lang ako](mailto:texmathpro@gmail.com). | F40: 179 | G40: 169 | H40: FALSE | I40: 46176 | J40: TRUE | K40: 46179 | L40: --- 📑 **Competencies Covered** - Illustrate and describe point, line, ray, line segment, angle, and plane using models and geometric notations. - Construct perpendicular and parallel lines. - Identify the relationships between angles formed by parallel lines cut by a transversal. - Determine angle measures involving angle pairs, parallel and perpendicular lines, and parallel lines cut by a transversal. - Identify relations that are functions based on the definitions of relations and functions. - Determine the domain and range of a function expressed in different representations. | M40: {=_xlfn.XLOOKUP(TRUE,ISNUMBER(SEARCH(Sheet2!A$23:A$26,A40)),Sheet2!B$23:B$26,"")} -> First Summative test | N40: {=_xlfn.XLOOKUP(TRUE,ISNUMBER(SEARCH(Sheet2!A$32:A$34,A40)),Sheet2!B$32:B$34,"")} -> First Term | O40: {=_xlfn.XLOOKUP(TRUE,ISNUMBER(SEARCH(Sheet2!A$38:A$41,A40)),Sheet2!B$38:B$41,"")} -> Grade 9 | P40: {=_xlfn.XLOOKUP(TRUE,ISNUMBER(SEARCH(Sheet2!A$45:A$47,A40)),Sheet2!B$45:B$47,"")} -> Custom Assessment Package | R40: 25-50
A41: G9-T1-S2-BP | B41: Grade 9 T1 Second Summative Test + Answer Key (Basic) | C41: https://res.cloudinary.com/dadubemrv/image/upload/v1784731784/ptqhzxe6hdaphiivprrc.png,https://res.cloudinary.com/dadubemrv/image/upload/v1784731787/jc6dwnedukuiwimgdgxv.png,https://res.cloudinary.com/dadubemrv/image/upload/v1784731789/aidqozqvzsxtxmtppi1c.png | D41: =CONCATENATE("*Tinatamad ka ba, walang time, o nahihirapang gumawa ng TOS at ", Sheet1!M41, " mo, ",Sheet1!O41," KasaMath? Kuha ka na ng ", Sheet1!P41,"!* **Bakit perfect para sa’yo ang ", Sheet1!P41,"?** ",Sheet2!D$17, Sheet1!Q41," days - ", Sheet1!R41,"-item Multiple Choice test with Answer Key - Para sa teachers na nagmamadali at hindi kailangan ang TOS", L41, " --- ## Step 1: I-fill out at i-submit ang Order Form. ", "{{< iframe src=""", "https://cityofsmiles.github.io/auto-order-form/?id=", LOWER(A41), """ height=""850"" >}}"," ## Step 2: Payment and Delivery ### Payment Methods Mag-send ka lang ng ₱",Sheet1!F41," para sa **", Sheet1!M41,_xlfn._LONGTEXT("**. - **Landbank**: 0695077289 (Jonathan R. Bacolod) - **GCash**: 09128389571 (Jonathan Bacolod) - **Maya**: 09128389571 (Jonathan Bacolod) **Isend ang Screenshot ng Payment kahit saan dito:** - Email: [texmathpro@gmail.com](mailto:texmathpro@gm","ail.com) - Facebook: https://m.me/jonathan.r.bacolod - Telegram: https://t.me/Jonathan_Bacolod Isesend ko ang files sa email address mo after ng payment. ### Delivery Includes: - **Test** - Test type: "), Sheet1!R41,"-item multiple choice test - Dimensions: A4 bond paper - Format: PDF, created using LaTeX - **Answer Key** - Format: PDF, created using LaTeX", Sheet2!$D$6) -> *Tinatamad ka ba, walang time, o nahihirapang gumawa ng TOS at Second Summative test mo, Grade 9 KasaMath? Kuha ka na ng Basic Assessment Package!* **Bakit perfect para sa’yo ang Basic Assessment Package?** - Makakatipid ka sa oras kaya makakapaghabol pa ng lessons. - Maganda at consistent ang formatting ng test questions at figures. - Ready na ang answer key kaya mas madali at mabilis ang pagche-check. - Ready-to-print exam: sakto sa Budget of Work ang covered topics - Number of days: 15 days - 25-item Multiple Choice test with Answer Key - Para sa teachers na nagmamadali at hindi kailangan ang TOS --- 📑 **Competencies Covered** - Express the relationship between two variables as a function. - Determine the slopes (as rate of change) and zeros of linear functions represented in graphs, equations, and tables of values. - Graph a linear function and determine its domain, range, intercepts, and slope. - Represent linear relationships found in real-life situations using different representations. - Solve problems involving linear functions. - Determine conditions that guarantee parallelism and perpendicularity of lines. --- ## Step 1: I-fill out at i-submit ang Order Form. {{< iframe src="https://cityofsmiles.github.io/auto-order-form/?id=g9-t1-s2-bp" height="850" >}} ## Step 2: Payment and Delivery ### Payment Methods Mag-send ka lang ng ₱59 para sa **Second Summative test**. - **Landbank**: 0695077289 (Jonathan R. Bacolod) - **GCash**: 09128389571 (Jonathan Bacolod) - **Maya**: 09128389571 (Jonathan Bacolod) **Isend ang Screenshot ng Payment kahit saan dito:** - Email: [texmathpro@gmail.com](mailto:texmathpro@gmail.com) - Facebook: https://m.me/jonathan.r.bacolod - Telegram: https://t.me/Jonathan_Bacolod Isesend ko ang files sa email address mo after ng payment. ### Delivery Includes: - **Test** - Test type: 25-item multiple choice test - Dimensions: A4 bond paper - Format: PDF, created using LaTeX - **Answer Key** - Format: PDF, created using LaTeX --- Salamat sa pagsuporta sa **TeXMathPro, KasaMath**! Kung may tanong o suggestion ka, [kontakin mo lang ako](mailto:texmathpro@gmail.com). | F41: 59 | G41: 49 | H41: FALSE | I41: 46176 | J41: TRUE | K41: 46179 | L41: --- 📑 **Competencies Covered** - Express the relationship between two variables as a function. - Determine the slopes (as rate of change) and zeros of linear functions represented in graphs, equations, and tables of values. - Graph a linear function and determine its domain, range, intercepts, and slope. - Represent linear relationships found in real-life situations using different representations. - Solve problems involving linear functions. - Determine conditions that guarantee parallelism and perpendicularity of lines. | M41: {=_xlfn.XLOOKUP(TRUE,ISNUMBER(SEARCH(Sheet2!A$23:A$26,A41)),Sheet2!B$23:B$26,"")} -> Second Summative test | N41: {=_xlfn.XLOOKUP(TRUE,ISNUMBER(SEARCH(Sheet2!A$32:A$34,A41)),Sheet2!B$32:B$34,"")} -> First Term | O41: {=_xlfn.XLOOKUP(TRUE,ISNUMBER(SEARCH(Sheet2!A$38:A$41,A41)),Sheet2!B$38:B$41,"")} -> Grade 9 | P41: {=_xlfn.XLOOKUP(TRUE,ISNUMBER(SEARCH(Sheet2!A$45:A$47,A41)),Sheet2!B$45:B$47,"")} -> Basic Assessment Package | Q41: 15 | R41: 25
A42: G9-T1-S2-SP | B42: Grade 9 T1 Second Summative Test + Answer Key + TOS (Standard) | C42: https://res.cloudinary.com/dadubemrv/image/upload/v1784731784/ptqhzxe6hdaphiivprrc.png,https://res.cloudinary.com/dadubemrv/image/upload/v1784731787/jc6dwnedukuiwimgdgxv.png,https://res.cloudinary.com/dadubemrv/image/upload/v1784731789/aidqozqvzsxtxmtppi1c.png | D42: =CONCATENATE("*Tinatamad ka ba, walang time, o nahihirapang gumawa ng TOS at ", Sheet1!M42, " mo, ",Sheet1!O42," KasaMath? Kuha ka na ng ", Sheet1!P42,"!* **Bakit perfect para sa’yo ang ", Sheet1!P42,"?** ",Sheet2!E$17, Sheet1!Q42," days - ", Sheet1!R42,"-item Multiple Choice test with Answer Key - Bagay sa teachers na gusto ng kumpletong exam, answer key, at TOS", _xlfn._LONGTEXT(" [![Sample TOS formatted using 21st Century Skills](https://res.cloudinary.com/dadubemrv/image/upload/v1768351176/tv5zwilsnzrad6r2q6sw.png)](https://res.cloudinary.com/dadubemrv/image/upload/v1768351176/tv5zwilsnzrad6r2q6sw.png) *Sample TOS formatted us","ing 21st Century Skills*"),L42, " --- ## Step 1: I-fill out at i-submit ang Order Form. ", "{{< iframe src=""", "https://cityofsmiles.github.io/auto-order-form/?id=", LOWER(A42), """ height=""850"" >}}"," ## Step 2: Payment and Delivery ### Payment Methods Mag-send ka lang ng ₱",Sheet1!F42," para sa **", Sheet1!M42,_xlfn._LONGTEXT("**. - **Landbank**: 0695077289 (Jonathan R. Bacolod) - **GCash**: 09128389571 (Jonathan Bacolod) - **Maya**: 09128389571 (Jonathan Bacolod) **Isend ang Screenshot ng Payment kahit saan dito:** - Email: [texmathpro@gmail.com](mailto:texmathpro@gm","ail.com) - Facebook: https://m.me/jonathan.r.bacolod - Telegram: https://t.me/Jonathan_Bacolod Isesend ko ang files sa email address mo after ng payment. ### Delivery Includes: - **Test** - Test type: "), Sheet1!R42,"-item multiple choice test - Dimensions: A4 bond paper - Format: PDF, created using LaTeX - **Answer Key** - Format: PDF, created using LaTeX - **Table of Specifications** - XLSX format", Sheet2!$D$6) -> *Tinatamad ka ba, walang time, o nahihirapang gumawa ng TOS at Second Summative test mo, Grade 9 KasaMath? Kuha ka na ng Standard Assessment Package!* **Bakit perfect para sa’yo ang Standard Assessment Package?** - Makakatipid ka sa oras kaya makakapaghabol pa ng lessons. - Maganda at consistent ang formatting ng test questions at figures. - Ready na ang answer key kaya mas madali at mabilis ang pagche-check. - Ready-to-print exam: sakto sa Budget of Work ang covered topics - Maaga kang makakapag-submit ng TOS sa head mo. - Table of Specifications using the 21st Century format - Number of days: 15 days - 25-item Multiple Choice test with Answer Key - Bagay sa teachers na gusto ng kumpletong exam, answer key, at TOS [![Sample TOS formatted using 21st Century Skills](https://res.cloudinary.com/dadubemrv/image/upload/v1768351176/tv5zwilsnzrad6r2q6sw.png)](https://res.cloudinary.com/dadubemrv/image/upload/v1768351176/tv5zwilsnzrad6r2q6sw.png) *Sample TOS formatted using 21st Century Skills* --- 📑 **Competencies Covered** - Express the relationship between two variables as a function. - Determine the slopes (as rate of change) and zeros of linear functions represented in graphs, equations, and tables of values. - Graph a linear function and determine its domain, range, intercepts, and slope. - Represent linear relationships found in real-life situations using different representations. - Solve problems involving linear functions. - Determine conditions that guarantee parallelism and perpendicularity of lines. --- ## Step 1: I-fill out at i-submit ang Order Form. {{< iframe src="https://cityofsmiles.github.io/auto-order-form/?id=g9-t1-s2-sp" height="850" >}} ## Step 2: Payment and Delivery ### Payment Methods Mag-send ka lang ng ₱79 para sa **Second Summative test**. - **Landbank**: 0695077289 (Jonathan R. Bacolod) - **GCash**: 09128389571 (Jonathan Bacolod) - **Maya**: 09128389571 (Jonathan Bacolod) **Isend ang Screenshot ng Payment kahit saan dito:** - Email: [texmathpro@gmail.com](mailto:texmathpro@gmail.com) - Facebook: https://m.me/jonathan.r.bacolod - Telegram: https://t.me/Jonathan_Bacolod Isesend ko ang files sa email address mo after ng payment. ### Delivery Includes: - **Test** - Test type: 25-item multiple choice test - Dimensions: A4 bond paper - Format: PDF, created using LaTeX - **Answer Key** - Format: PDF, created using LaTeX - **Table of Specifications** - XLSX format --- Salamat sa pagsuporta sa **TeXMathPro, KasaMath**! Kung may tanong o suggestion ka, [kontakin mo lang ako](mailto:texmathpro@gmail.com). | F42: 79 | G42: 69 | H42: FALSE | I42: 46176 | J42: TRUE | K42: 46179 | L42: --- 📑 **Competencies Covered** - Express the relationship between two variables as a function. - Determine the slopes (as rate of change) and zeros of linear functions represented in graphs, equations, and tables of values. - Graph a linear function and determine its domain, range, intercepts, and slope. - Represent linear relationships found in real-life situations using different representations. - Solve problems involving linear functions. - Determine conditions that guarantee parallelism and perpendicularity of lines. | M42: {=_xlfn.XLOOKUP(TRUE,ISNUMBER(SEARCH(Sheet2!A$23:A$26,A42)),Sheet2!B$23:B$26,"")} -> Second Summative test | N42: {=_xlfn.XLOOKUP(TRUE,ISNUMBER(SEARCH(Sheet2!A$32:A$34,A42)),Sheet2!B$32:B$34,"")} -> First Term | O42: {=_xlfn.XLOOKUP(TRUE,ISNUMBER(SEARCH(Sheet2!A$38:A$41,A42)),Sheet2!B$38:B$41,"")} -> Grade 9 | P42: {=_xlfn.XLOOKUP(TRUE,ISNUMBER(SEARCH(Sheet2!A$45:A$47,A42)),Sheet2!B$45:B$47,"")} -> Standard Assessment Package | Q42: 15 | R42: 25
A43: G9-T1-S2-CP | B43: Grade 9 T1 Second Summative Test + Answer Key + TOS (Custom) | C43: https://res.cloudinary.com/dadubemrv/image/upload/v1784731784/ptqhzxe6hdaphiivprrc.png,https://res.cloudinary.com/dadubemrv/image/upload/v1784731787/jc6dwnedukuiwimgdgxv.png,https://res.cloudinary.com/dadubemrv/image/upload/v1784731789/aidqozqvzsxtxmtppi1c.png | D43: =CONCATENATE("*Tinatamad ka ba, walang time, o nahihirapang gumawa ng TOS at ", Sheet1!M43, " mo, ",Sheet1!O43," KasaMath? Kuha ka na ng ", Sheet1!P43,"!* **Bakit perfect para sa’yo ang ", Sheet1!P43,"?** ",Sheet2!F$17," - Perfect sa teachers na gusto ng pasadyang exam", _xlfn._LONGTEXT(" [![Sample TOS formatted using 21st Century Skills](https://res.cloudinary.com/dadubemrv/image/upload/v1768351176/tv5zwilsnzrad6r2q6sw.png)](https://res.cloudinary.com/dadubemrv/image/upload/v1768351176/tv5zwilsnzrad6r2q6sw.png) *Sample TOS formatted us","ing 21st Century Skills*"),L43, " --- ## Step 1: I-fill out at i-submit ang Order Form. ", "{{< iframe src=""", "https://cityofsmiles.github.io/auto-order-form/?id=", LOWER(A43), """ height=""850"" >}}"," ## Step 2: Payment and Delivery ### Payment Methods Mag-send ka lang ng ₱",Sheet1!F43," para sa **", Sheet1!M43,_xlfn._LONGTEXT("**. - **Landbank**: 0695077289 (Jonathan R. Bacolod) - **GCash**: 09128389571 (Jonathan Bacolod) - **Maya**: 09128389571 (Jonathan Bacolod) **Isend ang Screenshot ng Payment kahit saan dito:** - Email: [texmathpro@gmail.com](mailto:texmathpro@gm","ail.com) - Facebook: https://m.me/jonathan.r.bacolod - Telegram: https://t.me/Jonathan_Bacolod Isesend ko ang files sa email address mo after ng payment. ### Delivery Includes: - **Test** - Test type: "), Sheet1!R43,"-item multiple choice test - Dimensions: A4 bond paper - Format: PDF, created using LaTeX - **Answer Key** - Format: PDF, created using LaTeX - **Table of Specifications** - XLSX format", Sheet2!$D$6) -> *Tinatamad ka ba, walang time, o nahihirapang gumawa ng TOS at Second Summative test mo, Grade 9 KasaMath? Kuha ka na ng Custom Assessment Package!* **Bakit perfect para sa’yo ang Custom Assessment Package?** - Makakatipid ka sa oras kaya makakapaghabol pa ng lessons. - Maganda at consistent ang formatting ng test questions at figures. - Ready na ang answer key kaya mas madali at mabilis ang pagche-check. - Fully customizable exam: kahit anong topic ang pwedeng covered - Maaga kang makakapag-submit ng TOS sa head mo. - Table of Specifications using the 21st Century format - Number of days: pwede kahit ilan - Number of items: kahit ilan basta maximum of 50 - Perfect sa teachers na gusto ng pasadyang exam [![Sample TOS formatted using 21st Century Skills](https://res.cloudinary.com/dadubemrv/image/upload/v1768351176/tv5zwilsnzrad6r2q6sw.png)](https://res.cloudinary.com/dadubemrv/image/upload/v1768351176/tv5zwilsnzrad6r2q6sw.png) *Sample TOS formatted using 21st Century Skills* --- 📑 **Competencies Covered** - Express the relationship between two variables as a function. - Determine the slopes (as rate of change) and zeros of linear functions represented in graphs, equations, and tables of values. - Graph a linear function and determine its domain, range, intercepts, and slope. - Represent linear relationships found in real-life situations using different representations. - Solve problems involving linear functions. - Determine conditions that guarantee parallelism and perpendicularity of lines. --- ## Step 1: I-fill out at i-submit ang Order Form. {{< iframe src="https://cityofsmiles.github.io/auto-order-form/?id=g9-t1-s2-cp" height="850" >}} ## Step 2: Payment and Delivery ### Payment Methods Mag-send ka lang ng ₱179 para sa **Second Summative test**. - **Landbank**: 0695077289 (Jonathan R. Bacolod) - **GCash**: 09128389571 (Jonathan Bacolod) - **Maya**: 09128389571 (Jonathan Bacolod) **Isend ang Screenshot ng Payment kahit saan dito:** - Email: [texmathpro@gmail.com](mailto:texmathpro@gmail.com) - Facebook: https://m.me/jonathan.r.bacolod - Telegram: https://t.me/Jonathan_Bacolod Isesend ko ang files sa email address mo after ng payment. ### Delivery Includes: - **Test** - Test type: 25-50-item multiple choice test - Dimensions: A4 bond paper - Format: PDF, created using LaTeX - **Answer Key** - Format: PDF, created using LaTeX - **Table of Specifications** - XLSX format --- Salamat sa pagsuporta sa **TeXMathPro, KasaMath**! Kung may tanong o suggestion ka, [kontakin mo lang ako](mailto:texmathpro@gmail.com). | F43: 179 | G43: 169 | H43: FALSE | I43: 46176 | J43: TRUE | K43: 46179 | L43: --- 📑 **Competencies Covered** - Express the relationship between two variables as a function. - Determine the slopes (as rate of change) and zeros of linear functions represented in graphs, equations, and tables of values. - Graph a linear function and determine its domain, range, intercepts, and slope. - Represent linear relationships found in real-life situations using different representations. - Solve problems involving linear functions. - Determine conditions that guarantee parallelism and perpendicularity of lines. | M43: {=_xlfn.XLOOKUP(TRUE,ISNUMBER(SEARCH(Sheet2!A$23:A$26,A43)),Sheet2!B$23:B$26,"")} -> Second Summative test | N43: {=_xlfn.XLOOKUP(TRUE,ISNUMBER(SEARCH(Sheet2!A$32:A$34,A43)),Sheet2!B$32:B$34,"")} -> First Term | O43: {=_xlfn.XLOOKUP(TRUE,ISNUMBER(SEARCH(Sheet2!A$38:A$41,A43)),Sheet2!B$38:B$41,"")} -> Grade 9 | P43: {=_xlfn.XLOOKUP(TRUE,ISNUMBER(SEARCH(Sheet2!A$45:A$47,A43)),Sheet2!B$45:B$47,"")} -> Custom Assessment Package | R43: 25-50
A44: G10-T1-S1-BP | B44: Grade 10 T1 First Summative Test + TOS + Answer Key (Basic) | C44: https://res.cloudinary.com/dadubemrv/image/upload/v1771581341/mt0reu4d16nbbglfigzi.jpg | D44: =Sheet2!$D$2 -> 0 | F44: 120 | G44: 84 | H44: FALSE | I44: 46176 | J44: FALSE | K44: 46176
A45: G10-T1-S1-SP | B45: Grade 10 T1 First Summative Test + TOS + Answer Key (Standard) | C45: https://res.cloudinary.com/dadubemrv/image/upload/v1771581341/mt0reu4d16nbbglfigzi.jpg | D45: =Sheet2!$E$2 -> 0 | F45: 165 | G45: 115 | H45: FALSE | I45: 46176 | J45: FALSE | K45: 46176
A46: G10-T1-S1-CP | B46: Grade 10 T1 First Summative Test + TOS + Answer Key (Custom) | C46: https://res.cloudinary.com/dadubemrv/image/upload/v1771581341/mt0reu4d16nbbglfigzi.jpg | D46: =Sheet2!$F$2 -> 0 | F46: 350 | G46: 245 | H46: FALSE | I46: 46176 | J46: FALSE | K46: 46176
A47: G7-T1-TE-BP | B47: Grade 7 T1 Term Exam + Answer Key (Basic) | C47: https://res.cloudinary.com/dadubemrv/image/upload/v1787464873/tecspvimjjmukoar4zbb.png,https://res.cloudinary.com/dadubemrv/image/upload/v1787464876/xbrtpio296qgy3j7oujs.png,https://res.cloudinary.com/dadubemrv/image/upload/v1787464879/jg5ya8r4c7tclyqtbcix.png,https://res.cloudinary.com/dadubemrv/image/upload/v1787464881/i4flhlzmeex8qigeggdy.png,https://res.cloudinary.com/dadubemrv/image/upload/v1787464884/dcphz1r95ezhrflugxgu.png | D47: =CONCATENATE("*Tinatamad ka ba, walang time, o nahihirapang gumawa ng ", Sheet1!M47, " mo, ",Sheet1!O47," KasaMath? Kuha ka na ng ", Sheet1!P47,"!* **Bakit perfect para sa’yo ang ", Sheet1!P47,"?** ",Sheet2!D$17, Sheet1!Q47," days - ", Sheet1!R47,"-item Multiple Choice test with Answer Key - Para sa teachers na nagmamadali at hindi kailangan ang TOS", L47, " --- ## Step 1: I-fill out at i-submit ang Order Form. ", "{{< iframe src=""", "https://cityofsmiles.github.io/auto-order-form/?id=", LOWER(A47), """ height=""850"" >}}"," ## Step 2: Payment and Delivery ### Payment Methods Mag-send ka lang ng ₱",Sheet1!F47," para sa **", Sheet1!M47,_xlfn._LONGTEXT("**. - **Landbank**: 0695077289 (Jonathan R. Bacolod) - **GCash**: 09128389571 (Jonathan Bacolod) - **Maya**: 09128389571 (Jonathan Bacolod) **Isend ang Screenshot ng Payment kahit saan dito:** - Email: [texmathpro@gmail.com](mailto:texmathpro@gm","ail.com) - Facebook: https://m.me/jonathan.r.bacolod - Telegram: https://t.me/Jonathan_Bacolod Isesend ko ang files sa email address mo after ng payment. ### Delivery Includes: - **Test** - Test type: "), Sheet1!R47,"-item multiple choice test - Dimensions: A4 bond paper - Format: PDF, created using LaTeX - **Answer Key** - Format: PDF, created using LaTeX", Sheet2!$D$6) -> *Tinatamad ka ba, walang time, o nahihirapang gumawa ng Term Exam mo, Grade 7 KasaMath? Kuha ka na ng Basic Assessment Package!* **Bakit perfect para sa’yo ang Basic Assessment Package?** - Makakatipid ka sa oras kaya makakapaghabol pa ng lessons. - Maganda at consistent ang formatting ng test questions at figures. - Ready na ang answer key kaya mas madali at mabilis ang pagche-check. - Ready-to-print exam: sakto sa Budget of Work ang covered topics - Number of days: 25 days - 50-item Multiple Choice test with Answer Key - Para sa teachers na nagmamadali at hindi kailangan ang TOS --- 📑 **Competencies Covered** - Describe and explain the relationships between angle pairs based on their measures. - Deduce the relationship between the exterior angle and adjacent interior angle of a polygon. - Solve problems involving percentage increase and percentage decrease. - Solve money problems involving percentages (e. g., discount, commission, sales tax, simple interest). - Identify and explain the uses of rates. - Solve problems involving rates (e.g., speed). - Describe given rational numbers as fractions, decimals, or percentages. - Order rational numbers on a number line. - Perform operations on rational numbers. --- ## Step 1: I-fill out at i-submit ang Order Form. {{< iframe src="https://cityofsmiles.github.io/auto-order-form/?id=g7-t1-te-bp" height="850" >}} ## Step 2: Payment and Delivery ### Payment Methods Mag-send ka lang ng ₱119 para sa **Term Exam**. - **Landbank**: 0695077289 (Jonathan R. Bacolod) - **GCash**: 09128389571 (Jonathan Bacolod) - **Maya**: 09128389571 (Jonathan Bacolod) **Isend ang Screenshot ng Payment kahit saan dito:** - Email: [texmathpro@gmail.com](mailto:texmathpro@gmail.com) - Facebook: https://m.me/jonathan.r.bacolod - Telegram: https://t.me/Jonathan_Bacolod Isesend ko ang files sa email address mo after ng payment. ### Delivery Includes: - **Test** - Test type: 50-item multiple choice test - Dimensions: A4 bond paper - Format: PDF, created using LaTeX - **Answer Key** - Format: PDF, created using LaTeX --- Salamat sa pagsuporta sa **TeXMathPro, KasaMath**! Kung may tanong o suggestion ka, [kontakin mo lang ako](mailto:texmathpro@gmail.com). | F47: 119 | G47: 84 | H47: FALSE | I47: 46176 | J47: TRUE | K47: 46176 | L47: --- 📑 **Competencies Covered** - Describe and explain the relationships between angle pairs based on their measures. - Deduce the relationship between the exterior angle and adjacent interior angle of a polygon. - Solve problems involving percentage increase and percentage decrease. - Solve money problems involving percentages (e. g., discount, commission, sales tax, simple interest). - Identify and explain the uses of rates. - Solve problems involving rates (e.g., speed). - Describe given rational numbers as fractions, decimals, or percentages. - Order rational numbers on a number line. - Perform operations on rational numbers. | M47: {=_xlfn.XLOOKUP(TRUE,ISNUMBER(SEARCH(Sheet2!A$23:A$26,A47)),Sheet2!B$23:B$26,"")} -> Term Exam | N47: {=_xlfn.XLOOKUP(TRUE,ISNUMBER(SEARCH(Sheet2!A$32:A$34,A47)),Sheet2!B$32:B$34,"")} -> First Term | O47: {=_xlfn.XLOOKUP(TRUE,ISNUMBER(SEARCH(Sheet2!A$38:A$41,A47)),Sheet2!B$38:B$41,"")} -> Grade 7 | P47: {=_xlfn.XLOOKUP(TRUE,ISNUMBER(SEARCH(Sheet2!A$45:A$47,A47)),Sheet2!B$45:B$47,"")} -> Basic Assessment Package | Q47: 25 | R47: 50
A48: G7-T1-TE-SP | B48: Grade 7 T1 Term Exam + TOS + Answer Key (Standard) | C48: https://res.cloudinary.com/dadubemrv/image/upload/v1787464873/tecspvimjjmukoar4zbb.png,https://res.cloudinary.com/dadubemrv/image/upload/v1787464876/xbrtpio296qgy3j7oujs.png,https://res.cloudinary.com/dadubemrv/image/upload/v1787464879/jg5ya8r4c7tclyqtbcix.png,https://res.cloudinary.com/dadubemrv/image/upload/v1787464881/i4flhlzmeex8qigeggdy.png,https://res.cloudinary.com/dadubemrv/image/upload/v1787464884/dcphz1r95ezhrflugxgu.png | D48: =CONCATENATE("*Tinatamad ka ba, walang time, o nahihirapang gumawa ng TOS at ", Sheet1!M48, " mo, ",Sheet1!O48," KasaMath? Kuha ka na ng ", Sheet1!P48,"!* **Bakit perfect para sa’yo ang ", Sheet1!P48,"?** ",Sheet2!E$17, Sheet1!Q48," days - ", Sheet1!R48,"-item Multiple Choice test with Answer Key - Bagay sa teachers na gusto ng kumpletong exam, answer key, at TOS", _xlfn._LONGTEXT(" [![Sample TOS formatted using 21st Century Skills](https://res.cloudinary.com/dadubemrv/image/upload/v1768351176/tv5zwilsnzrad6r2q6sw.png)](https://res.cloudinary.com/dadubemrv/image/upload/v1768351176/tv5zwilsnzrad6r2q6sw.png) *Sample TOS formatted us","ing 21st Century Skills*"), L48, " --- ## Step 1: I-fill out at i-submit ang Order Form. ", "{{< iframe src=""", "https://cityofsmiles.github.io/auto-order-form/?id=", LOWER(A48), """ height=""850"" >}}"," ## Step 2: Payment and Delivery ### Payment Methods Mag-send ka lang ng ₱",Sheet1!F48," para sa **", Sheet1!M48,_xlfn._LONGTEXT("**. - **Landbank**: 0695077289 (Jonathan R. Bacolod) - **GCash**: 09128389571 (Jonathan Bacolod) - **Maya**: 09128389571 (Jonathan Bacolod) **Isend ang Screenshot ng Payment kahit saan dito:** - Email: [texmathpro@gmail.com](mailto:texmathpro@gm","ail.com) - Facebook: https://m.me/jonathan.r.bacolod - Telegram: https://t.me/Jonathan_Bacolod Isesend ko ang files sa email address mo after ng payment. ### Delivery Includes: - **Test** - Test type: "), Sheet1!R48,"-item multiple choice test - Dimensions: A4 bond paper - Format: PDF, created using LaTeX - **Answer Key** - Format: PDF, created using LaTeX - **Table of Specifications** - XLSX format", Sheet2!$D$6) -> *Tinatamad ka ba, walang time, o nahihirapang gumawa ng TOS at Term Exam mo, Grade 7 KasaMath? Kuha ka na ng Standard Assessment Package!* **Bakit perfect para sa’yo ang Standard Assessment Package?** - Makakatipid ka sa oras kaya makakapaghabol pa ng lessons. - Maganda at consistent ang formatting ng test questions at figures. - Ready na ang answer key kaya mas madali at mabilis ang pagche-check. - Ready-to-print exam: sakto sa Budget of Work ang covered topics - Maaga kang makakapag-submit ng TOS sa head mo. - Table of Specifications using the 21st Century format - Number of days: 25 days - 50-item Multiple Choice test with Answer Key - Bagay sa teachers na gusto ng kumpletong exam, answer key, at TOS [![Sample TOS formatted using 21st Century Skills](https://res.cloudinary.com/dadubemrv/image/upload/v1768351176/tv5zwilsnzrad6r2q6sw.png)](https://res.cloudinary.com/dadubemrv/image/upload/v1768351176/tv5zwilsnzrad6r2q6sw.png) *Sample TOS formatted using 21st Century Skills* --- 📑 **Competencies Covered** - Describe and explain the relationships between angle pairs based on their measures. - Deduce the relationship between the exterior angle and adjacent interior angle of a polygon. - Solve problems involving percentage increase and percentage decrease. - Solve money problems involving percentages (e. g., discount, commission, sales tax, simple interest). - Identify and explain the uses of rates. - Solve problems involving rates (e.g., speed). - Describe given rational numbers as fractions, decimals, or percentages. - Order rational numbers on a number line. - Perform operations on rational numbers. --- ## Step 1: I-fill out at i-submit ang Order Form. {{< iframe src="https://cityofsmiles.github.io/auto-order-form/?id=g7-t1-te-sp" height="850" >}} ## Step 2: Payment and Delivery ### Payment Methods Mag-send ka lang ng ₱169 para sa **Term Exam**. - **Landbank**: 0695077289 (Jonathan R. Bacolod) - **GCash**: 09128389571 (Jonathan Bacolod) - **Maya**: 09128389571 (Jonathan Bacolod) **Isend ang Screenshot ng Payment kahit saan dito:** - Email: [texmathpro@gmail.com](mailto:texmathpro@gmail.com) - Facebook: https://m.me/jonathan.r.bacolod - Telegram: https://t.me/Jonathan_Bacolod Isesend ko ang files sa email address mo after ng payment. ### Delivery Includes: - **Test** - Test type: 50-item multiple choice test - Dimensions: A4 bond paper - Format: PDF, created using LaTeX - **Answer Key** - Format: PDF, created using LaTeX - **Table of Specifications** - XLSX format --- Salamat sa pagsuporta sa **TeXMathPro, KasaMath**! Kung may tanong o suggestion ka, [kontakin mo lang ako](mailto:texmathpro@gmail.com). | F48: 169 | G48: 115 | H48: FALSE | I48: 46176 | J48: TRUE | K48: 46176 | L48: --- 📑 **Competencies Covered** - Describe and explain the relationships between angle pairs based on their measures. - Deduce the relationship between the exterior angle and adjacent interior angle of a polygon. - Solve problems involving percentage increase and percentage decrease. - Solve money problems involving percentages (e. g., discount, commission, sales tax, simple interest). - Identify and explain the uses of rates. - Solve problems involving rates (e.g., speed). - Describe given rational numbers as fractions, decimals, or percentages. - Order rational numbers on a number line. - Perform operations on rational numbers. | M48: {=_xlfn.XLOOKUP(TRUE,ISNUMBER(SEARCH(Sheet2!A$23:A$26,A48)),Sheet2!B$23:B$26,"")} -> Term Exam | N48: {=_xlfn.XLOOKUP(TRUE,ISNUMBER(SEARCH(Sheet2!A$32:A$34,A48)),Sheet2!B$32:B$34,"")} -> First Term | O48: {=_xlfn.XLOOKUP(TRUE,ISNUMBER(SEARCH(Sheet2!A$38:A$41,A48)),Sheet2!B$38:B$41,"")} -> Grade 7 | P48: {=_xlfn.XLOOKUP(TRUE,ISNUMBER(SEARCH(Sheet2!A$45:A$47,A48)),Sheet2!B$45:B$47,"")} -> Standard Assessment Package | Q48: 25 | R48: 50
A49: G7-T1-TE-CP | B49: Grade 7 T1 Term Exam + TOS + Answer Key (Custom) | C49: https://res.cloudinary.com/dadubemrv/image/upload/v1787464873/tecspvimjjmukoar4zbb.png,https://res.cloudinary.com/dadubemrv/image/upload/v1787464876/xbrtpio296qgy3j7oujs.png,https://res.cloudinary.com/dadubemrv/image/upload/v1787464879/jg5ya8r4c7tclyqtbcix.png,https://res.cloudinary.com/dadubemrv/image/upload/v1787464881/i4flhlzmeex8qigeggdy.png,https://res.cloudinary.com/dadubemrv/image/upload/v1787464884/dcphz1r95ezhrflugxgu.png | D49: =CONCATENATE("*Tinatamad ka ba, walang time, o nahihirapang gumawa ng TOS at ", Sheet1!M49, " mo, ",Sheet1!O49," KasaMath? Kuha ka na ng ", Sheet1!P49,"!* **Bakit perfect para sa’yo ang ", Sheet1!P49,"?** ",Sheet2!F$17," - Perfect sa teachers na gusto ng pasadyang exam", _xlfn._LONGTEXT(" [![Sample TOS formatted using 21st Century Skills](https://res.cloudinary.com/dadubemrv/image/upload/v1768351176/tv5zwilsnzrad6r2q6sw.png)](https://res.cloudinary.com/dadubemrv/image/upload/v1768351176/tv5zwilsnzrad6r2q6sw.png) *Sample TOS formatted us","ing 21st Century Skills*"), L49, " --- ## Step 1: I-fill out at i-submit ang Order Form. ", "{{< iframe src=""", "https://cityofsmiles.github.io/auto-order-form/?id=", LOWER(A49), """ height=""850"" >}}"," ## Step 2: Payment and Delivery ### Payment Methods Mag-send ka lang ng ₱",Sheet1!F49," para sa **", Sheet1!M49,_xlfn._LONGTEXT("**. - **Landbank**: 0695077289 (Jonathan R. Bacolod) - **GCash**: 09128389571 (Jonathan Bacolod) - **Maya**: 09128389571 (Jonathan Bacolod) **Isend ang Screenshot ng Payment kahit saan dito:** - Email: [texmathpro@gmail.com](mailto:texmathpro@gm","ail.com) - Facebook: https://m.me/jonathan.r.bacolod - Telegram: https://t.me/Jonathan_Bacolod Isesend ko ang files sa email address mo after ng payment. ### Delivery Includes: - **Test** - Test type: "), Sheet1!R49,"-item multiple choice test - Dimensions: A4 bond paper - Format: PDF, created using LaTeX - **Answer Key** - Format: PDF, created using LaTeX - **Table of Specifications** - XLSX format", Sheet2!$D$6) -> *Tinatamad ka ba, walang time, o nahihirapang gumawa ng TOS at Term Exam mo, Grade 7 KasaMath? Kuha ka na ng Custom Assessment Package!* **Bakit perfect para sa’yo ang Custom Assessment Package?** - Makakatipid ka sa oras kaya makakapaghabol pa ng lessons. - Maganda at consistent ang formatting ng test questions at figures. - Ready na ang answer key kaya mas madali at mabilis ang pagche-check. - Fully customizable exam: kahit anong topic ang pwedeng covered - Maaga kang makakapag-submit ng TOS sa head mo. - Table of Specifications using the 21st Century format - Number of days: pwede kahit ilan - Number of items: kahit ilan basta maximum of 50 - Perfect sa teachers na gusto ng pasadyang exam [![Sample TOS formatted using 21st Century Skills](https://res.cloudinary.com/dadubemrv/image/upload/v1768351176/tv5zwilsnzrad6r2q6sw.png)](https://res.cloudinary.com/dadubemrv/image/upload/v1768351176/tv5zwilsnzrad6r2q6sw.png) *Sample TOS formatted using 21st Century Skills* --- 📑 **Competencies Covered** - Describe and explain the relationships between angle pairs based on their measures. - Deduce the relationship between the exterior angle and adjacent interior angle of a polygon. - Solve problems involving percentage increase and percentage decrease. - Solve money problems involving percentages (e. g., discount, commission, sales tax, simple interest). - Identify and explain the uses of rates. - Solve problems involving rates (e.g., speed). - Describe given rational numbers as fractions, decimals, or percentages. - Order rational numbers on a number line. - Perform operations on rational numbers. --- ## Step 1: I-fill out at i-submit ang Order Form. {{< iframe src="https://cityofsmiles.github.io/auto-order-form/?id=g7-t1-te-cp" height="850" >}} ## Step 2: Payment and Delivery ### Payment Methods Mag-send ka lang ng ₱359 para sa **Term Exam**. - **Landbank**: 0695077289 (Jonathan R. Bacolod) - **GCash**: 09128389571 (Jonathan Bacolod) - **Maya**: 09128389571 (Jonathan Bacolod) **Isend ang Screenshot ng Payment kahit saan dito:** - Email: [texmathpro@gmail.com](mailto:texmathpro@gmail.com) - Facebook: https://m.me/jonathan.r.bacolod - Telegram: https://t.me/Jonathan_Bacolod Isesend ko ang files sa email address mo after ng payment. ### Delivery Includes: - **Test** - Test type: 50-item multiple choice test - Dimensions: A4 bond paper - Format: PDF, created using LaTeX - **Answer Key** - Format: PDF, created using LaTeX - **Table of Specifications** - XLSX format --- Salamat sa pagsuporta sa **TeXMathPro, KasaMath**! Kung may tanong o suggestion ka, [kontakin mo lang ako](mailto:texmathpro@gmail.com). | F49: 359 | G49: 245 | H49: FALSE | I49: 46176 | J49: TRUE | K49: 46176 | L49: --- 📑 **Competencies Covered** - Describe and explain the relationships between angle pairs based on their measures. - Deduce the relationship between the exterior angle and adjacent interior angle of a polygon. - Solve problems involving percentage increase and percentage decrease. - Solve money problems involving percentages (e. g., discount, commission, sales tax, simple interest). - Identify and explain the uses of rates. - Solve problems involving rates (e.g., speed). - Describe given rational numbers as fractions, decimals, or percentages. - Order rational numbers on a number line. - Perform operations on rational numbers. | M49: {=_xlfn.XLOOKUP(TRUE,ISNUMBER(SEARCH(Sheet2!A$23:A$26,A49)),Sheet2!B$23:B$26,"")} -> Term Exam | N49: {=_xlfn.XLOOKUP(TRUE,ISNUMBER(SEARCH(Sheet2!A$32:A$34,A49)),Sheet2!B$32:B$34,"")} -> First Term | O49: {=_xlfn.XLOOKUP(TRUE,ISNUMBER(SEARCH(Sheet2!A$38:A$41,A49)),Sheet2!B$38:B$41,"")} -> Grade 7 | P49: {=_xlfn.XLOOKUP(TRUE,ISNUMBER(SEARCH(Sheet2!A$45:A$47,A49)),Sheet2!B$45:B$47,"")} -> Custom Assessment Package | Q49: 25 | R49: 50
A50: G8-T1-TE-BP | B50: Grade 8 T1 Term Exam + TOS + Answer Key (Basic) | C50: https://i.imgur.com/Eciazvr.jpeg | D50: =Sheet2!$D$2 -> 0 | F50: 120 | G50: 84 | H50: FALSE | I50: 46176 | J50: FALSE | K50: 46176
A51: G8-T1-TE-SP | B51: Grade 8 T1 Term Exam + TOS + Answer Key (Standard) | C51: https://i.imgur.com/Eciazvr.jpeg | D51: =Sheet2!$E$2 -> 0 | F51: 165 | G51: 115 | H51: FALSE | I51: 46176 | J51: FALSE | K51: 46176
A52: G8-T1-TE-CP | B52: Grade 8 T1 Term Exam + TOS + Answer Key (Custom) | C52: https://i.imgur.com/Eciazvr.jpeg | D52: =Sheet2!$F$2 -> 0 | F52: 350 | G52: 245 | H52: FALSE | I52: 46176 | J52: FALSE | K52: 46176
A53: G9-T1-TE-BP | B53: Grade 9 T1 Term Exam + Answer Key (Basic) | C53: https://res.cloudinary.com/dadubemrv/image/upload/v1787629077/vggbz4e8touzqtnlxtnf.png,https://res.cloudinary.com/dadubemrv/image/upload/v1787629079/gxdpnle4x2alzlx3axnj.png,https://res.cloudinary.com/dadubemrv/image/upload/v1787629082/f4vzueldnbezcp9gkj8n.png,https://res.cloudinary.com/dadubemrv/image/upload/v1787629085/lthuwr9lmjlxjeosnrxp.png,https://res.cloudinary.com/dadubemrv/image/upload/v1787629088/bz6lix2ws4fbkydcs8ri.png | D53: =CONCATENATE("*Tinatamad ka ba, walang time, o nahihirapang gumawa ng ", Sheet1!M53, " mo, ",Sheet1!O53," KasaMath? Kuha ka na ng ", Sheet1!P53,"!* **Bakit perfect para sa’yo ang ", Sheet1!P53,"?** ",Sheet2!D$17, Sheet1!Q53," days - ", Sheet1!R53,"-item Multiple Choice test with Answer Key - Para sa teachers na nagmamadali at hindi kailangan ang TOS", L53, " --- ## Step 1: I-fill out at i-submit ang Order Form. ", "{{< iframe src=""", "https://cityofsmiles.github.io/auto-order-form/?id=", LOWER(A53), """ height=""850"" >}}"," ## Step 2: Payment and Delivery ### Payment Methods Mag-send ka lang ng ₱",Sheet1!F53," para sa **", Sheet1!M53,_xlfn._LONGTEXT("**. - **Landbank**: 0695077289 (Jonathan R. Bacolod) - **GCash**: 09128389571 (Jonathan Bacolod) - **Maya**: 09128389571 (Jonathan Bacolod) **Isend ang Screenshot ng Payment kahit saan dito:** - Email: [texmathpro@gmail.com](mailto:texmathpro@gm","ail.com) - Facebook: https://m.me/jonathan.r.bacolod - Telegram: https://t.me/Jonathan_Bacolod Isesend ko ang files sa email address mo after ng payment. ### Delivery Includes: - **Test** - Test type: "), Sheet1!R53,"-item multiple choice test - Dimensions: A4 bond paper - Format: PDF, created using LaTeX - **Answer Key** - Format: PDF, created using LaTeX", Sheet2!$D$6) -> *Tinatamad ka ba, walang time, o nahihirapang gumawa ng Term Exam mo, Grade 9 KasaMath? Kuha ka na ng Basic Assessment Package!* **Bakit perfect para sa’yo ang Basic Assessment Package?** - Makakatipid ka sa oras kaya makakapaghabol pa ng lessons. - Maganda at consistent ang formatting ng test questions at figures. - Ready na ang answer key kaya mas madali at mabilis ang pagche-check. - Ready-to-print exam: sakto sa Budget of Work ang covered topics - Number of days: 25 days - 50-item Multiple Choice test with Answer Key - Para sa teachers na nagmamadali at hindi kailangan ang TOS --- 📑 **Competencies Covered** - Identify the relationships between angles formed by parallel lines cut by a transversal. - Determine angle measures involving angle pairs, parallel and perpendicular lines, and parallel lines cut by a transversal. - Graph a linear function and determine its domain, range, intercepts, and slope. - Solve problems involving linear functions. - Determine conditions that guarantee parallelism and perpendicularity of lines. - Classify quadrilaterals based on formal definitions. - Determine the properties of parallelograms. - Use properties of parallelograms to find measures of angles, sides, perpendicular height, and diagonals. - Solve problems involving parallelograms, rectangles, squares and rhombuses by applying their different properties. --- ## Step 1: I-fill out at i-submit ang Order Form. {{< iframe src="https://cityofsmiles.github.io/auto-order-form/?id=g9-t1-te-bp" height="850" >}} ## Step 2: Payment and Delivery ### Payment Methods Mag-send ka lang ng ₱119 para sa **Term Exam**. - **Landbank**: 0695077289 (Jonathan R. Bacolod) - **GCash**: 09128389571 (Jonathan Bacolod) - **Maya**: 09128389571 (Jonathan Bacolod) **Isend ang Screenshot ng Payment kahit saan dito:** - Email: [texmathpro@gmail.com](mailto:texmathpro@gmail.com) - Facebook: https://m.me/jonathan.r.bacolod - Telegram: https://t.me/Jonathan_Bacolod Isesend ko ang files sa email address mo after ng payment. ### Delivery Includes: - **Test** - Test type: 50-item multiple choice test - Dimensions: A4 bond paper - Format: PDF, created using LaTeX - **Answer Key** - Format: PDF, created using LaTeX --- Salamat sa pagsuporta sa **TeXMathPro, KasaMath**! Kung may tanong o suggestion ka, [kontakin mo lang ako](mailto:texmathpro@gmail.com). | F53: 119 | G53: 84 | H53: FALSE | I53: 46176 | J53: TRUE | K53: 46176 | L53: --- 📑 **Competencies Covered** - Identify the relationships between angles formed by parallel lines cut by a transversal. - Determine angle measures involving angle pairs, parallel and perpendicular lines, and parallel lines cut by a transversal. - Graph a linear function and determine its domain, range, intercepts, and slope. - Solve problems involving linear functions. - Determine conditions that guarantee parallelism and perpendicularity of lines. - Classify quadrilaterals based on formal definitions. - Determine the properties of parallelograms. - Use properties of parallelograms to find measures of angles, sides, perpendicular height, and diagonals. - Solve problems involving parallelograms, rectangles, squares and rhombuses by applying their different properties. | M53: {=_xlfn.XLOOKUP(TRUE,ISNUMBER(SEARCH(Sheet2!A$23:A$26,A53)),Sheet2!B$23:B$26,"")} -> Term Exam | N53: {=_xlfn.XLOOKUP(TRUE,ISNUMBER(SEARCH(Sheet2!A$32:A$34,A53)),Sheet2!B$32:B$34,"")} -> First Term | O53: {=_xlfn.XLOOKUP(TRUE,ISNUMBER(SEARCH(Sheet2!A$38:A$41,A53)),Sheet2!B$38:B$41,"")} -> Grade 9 | P53: {=_xlfn.XLOOKUP(TRUE,ISNUMBER(SEARCH(Sheet2!A$45:A$47,A53)),Sheet2!B$45:B$47,"")} -> Basic Assessment Package | Q53: 25 | R53: 50
A54: G9-T1-TE-SP | B54: Grade 9 T1 Term Exam + TOS + Answer Key (Standard) | C54: https://res.cloudinary.com/dadubemrv/image/upload/v1787629077/vggbz4e8touzqtnlxtnf.png,https://res.cloudinary.com/dadubemrv/image/upload/v1787629079/gxdpnle4x2alzlx3axnj.png,https://res.cloudinary.com/dadubemrv/image/upload/v1787629082/f4vzueldnbezcp9gkj8n.png,https://res.cloudinary.com/dadubemrv/image/upload/v1787629085/lthuwr9lmjlxjeosnrxp.png,https://res.cloudinary.com/dadubemrv/image/upload/v1787629088/bz6lix2ws4fbkydcs8ri.png | D54: =CONCATENATE("*Tinatamad ka ba, walang time, o nahihirapang gumawa ng TOS at ", Sheet1!M54, " mo, ",Sheet1!O54," KasaMath? Kuha ka na ng ", Sheet1!P54,"!* **Bakit perfect para sa’yo ang ", Sheet1!P54,"?** ",Sheet2!E$17, Sheet1!Q54," days - ", Sheet1!R54,"-item Multiple Choice test with Answer Key - Bagay sa teachers na gusto ng kumpletong exam, answer key, at TOS", _xlfn._LONGTEXT(" [![Sample TOS formatted using 21st Century Skills](https://res.cloudinary.com/dadubemrv/image/upload/v1768351176/tv5zwilsnzrad6r2q6sw.png)](https://res.cloudinary.com/dadubemrv/image/upload/v1768351176/tv5zwilsnzrad6r2q6sw.png) *Sample TOS formatted us","ing 21st Century Skills*"), L54, " --- ## Step 1: I-fill out at i-submit ang Order Form. ", "{{< iframe src=""", "https://cityofsmiles.github.io/auto-order-form/?id=", LOWER(A54), """ height=""850"" >}}"," ## Step 2: Payment and Delivery ### Payment Methods Mag-send ka lang ng ₱",Sheet1!F54," para sa **", Sheet1!M54,_xlfn._LONGTEXT("**. - **Landbank**: 0695077289 (Jonathan R. Bacolod) - **GCash**: 09128389571 (Jonathan Bacolod) - **Maya**: 09128389571 (Jonathan Bacolod) **Isend ang Screenshot ng Payment kahit saan dito:** - Email: [texmathpro@gmail.com](mailto:texmathpro@gm","ail.com) - Facebook: https://m.me/jonathan.r.bacolod - Telegram: https://t.me/Jonathan_Bacolod Isesend ko ang files sa email address mo after ng payment. ### Delivery Includes: - **Test** - Test type: "), Sheet1!R54,"-item multiple choice test - Dimensions: A4 bond paper - Format: PDF, created using LaTeX - **Answer Key** - Format: PDF, created using LaTeX - **Table of Specifications** - XLSX format", Sheet2!$D$6) -> *Tinatamad ka ba, walang time, o nahihirapang gumawa ng TOS at Term Exam mo, Grade 9 KasaMath? Kuha ka na ng Standard Assessment Package!* **Bakit perfect para sa’yo ang Standard Assessment Package?** - Makakatipid ka sa oras kaya makakapaghabol pa ng lessons. - Maganda at consistent ang formatting ng test questions at figures. - Ready na ang answer key kaya mas madali at mabilis ang pagche-check. - Ready-to-print exam: sakto sa Budget of Work ang covered topics - Maaga kang makakapag-submit ng TOS sa head mo. - Table of Specifications using the 21st Century format - Number of days: 25 days - 50-item Multiple Choice test with Answer Key - Bagay sa teachers na gusto ng kumpletong exam, answer key, at TOS [![Sample TOS formatted using 21st Century Skills](https://res.cloudinary.com/dadubemrv/image/upload/v1768351176/tv5zwilsnzrad6r2q6sw.png)](https://res.cloudinary.com/dadubemrv/image/upload/v1768351176/tv5zwilsnzrad6r2q6sw.png) *Sample TOS formatted using 21st Century Skills* --- 📑 **Competencies Covered** - Identify the relationships between angles formed by parallel lines cut by a transversal. - Determine angle measures involving angle pairs, parallel and perpendicular lines, and parallel lines cut by a transversal. - Graph a linear function and determine its domain, range, intercepts, and slope. - Solve problems involving linear functions. - Determine conditions that guarantee parallelism and perpendicularity of lines. - Classify quadrilaterals based on formal definitions. - Determine the properties of parallelograms. - Use properties of parallelograms to find measures of angles, sides, perpendicular height, and diagonals. - Solve problems involving parallelograms, rectangles, squares and rhombuses by applying their different properties. --- ## Step 1: I-fill out at i-submit ang Order Form. {{< iframe src="https://cityofsmiles.github.io/auto-order-form/?id=g9-t1-te-sp" height="850" >}} ## Step 2: Payment and Delivery ### Payment Methods Mag-send ka lang ng ₱169 para sa **Term Exam**. - **Landbank**: 0695077289 (Jonathan R. Bacolod) - **GCash**: 09128389571 (Jonathan Bacolod) - **Maya**: 09128389571 (Jonathan Bacolod) **Isend ang Screenshot ng Payment kahit saan dito:** - Email: [texmathpro@gmail.com](mailto:texmathpro@gmail.com) - Facebook: https://m.me/jonathan.r.bacolod - Telegram: https://t.me/Jonathan_Bacolod Isesend ko ang files sa email address mo after ng payment. ### Delivery Includes: - **Test** - Test type: 50-item multiple choice test - Dimensions: A4 bond paper - Format: PDF, created using LaTeX - **Answer Key** - Format: PDF, created using LaTeX - **Table of Specifications** - XLSX format --- Salamat sa pagsuporta sa **TeXMathPro, KasaMath**! Kung may tanong o suggestion ka, [kontakin mo lang ako](mailto:texmathpro@gmail.com). | F54: 169 | G54: 115 | H54: FALSE | I54: 46176 | J54: TRUE | K54: 46176 | L54: --- 📑 **Competencies Covered** - Identify the relationships between angles formed by parallel lines cut by a transversal. - Determine angle measures involving angle pairs, parallel and perpendicular lines, and parallel lines cut by a transversal. - Graph a linear function and determine its domain, range, intercepts, and slope. - Solve problems involving linear functions. - Determine conditions that guarantee parallelism and perpendicularity of lines. - Classify quadrilaterals based on formal definitions. - Determine the properties of parallelograms. - Use properties of parallelograms to find measures of angles, sides, perpendicular height, and diagonals. - Solve problems involving parallelograms, rectangles, squares and rhombuses by applying their different properties. | M54: {=_xlfn.XLOOKUP(TRUE,ISNUMBER(SEARCH(Sheet2!A$23:A$26,A54)),Sheet2!B$23:B$26,"")} -> Term Exam | N54: {=_xlfn.XLOOKUP(TRUE,ISNUMBER(SEARCH(Sheet2!A$32:A$34,A54)),Sheet2!B$32:B$34,"")} -> First Term | O54: {=_xlfn.XLOOKUP(TRUE,ISNUMBER(SEARCH(Sheet2!A$38:A$41,A54)),Sheet2!B$38:B$41,"")} -> Grade 9 | P54: {=_xlfn.XLOOKUP(TRUE,ISNUMBER(SEARCH(Sheet2!A$45:A$47,A54)),Sheet2!B$45:B$47,"")} -> Standard Assessment Package | Q54: 25 | R54: 50
A55: G9-T1-TE-CP | B55: Grade 9 T1 Term Exam + TOS + Answer Key (Custom) | C55: https://res.cloudinary.com/dadubemrv/image/upload/v1787629077/vggbz4e8touzqtnlxtnf.png,https://res.cloudinary.com/dadubemrv/image/upload/v1787629079/gxdpnle4x2alzlx3axnj.png,https://res.cloudinary.com/dadubemrv/image/upload/v1787629082/f4vzueldnbezcp9gkj8n.png,https://res.cloudinary.com/dadubemrv/image/upload/v1787629085/lthuwr9lmjlxjeosnrxp.png,https://res.cloudinary.com/dadubemrv/image/upload/v1787629088/bz6lix2ws4fbkydcs8ri.png | D55: =CONCATENATE("*Tinatamad ka ba, walang time, o nahihirapang gumawa ng TOS at ", Sheet1!M55, " mo, ",Sheet1!O55," KasaMath? Kuha ka na ng ", Sheet1!P55,"!* **Bakit perfect para sa’yo ang ", Sheet1!P55,"?** ",Sheet2!F$17," - Perfect sa teachers na gusto ng pasadyang exam", _xlfn._LONGTEXT(" [![Sample TOS formatted using 21st Century Skills](https://res.cloudinary.com/dadubemrv/image/upload/v1768351176/tv5zwilsnzrad6r2q6sw.png)](https://res.cloudinary.com/dadubemrv/image/upload/v1768351176/tv5zwilsnzrad6r2q6sw.png) *Sample TOS formatted us","ing 21st Century Skills*"), L55, " --- ## Step 1: I-fill out at i-submit ang Order Form. ", "{{< iframe src=""", "https://cityofsmiles.github.io/auto-order-form/?id=", LOWER(A55), """ height=""850"" >}}"," ## Step 2: Payment and Delivery ### Payment Methods Mag-send ka lang ng ₱",Sheet1!F55," para sa **", Sheet1!M55,_xlfn._LONGTEXT("**. - **Landbank**: 0695077289 (Jonathan R. Bacolod) - **GCash**: 09128389571 (Jonathan Bacolod) - **Maya**: 09128389571 (Jonathan Bacolod) **Isend ang Screenshot ng Payment kahit saan dito:** - Email: [texmathpro@gmail.com](mailto:texmathpro@gm","ail.com) - Facebook: https://m.me/jonathan.r.bacolod - Telegram: https://t.me/Jonathan_Bacolod Isesend ko ang files sa email address mo after ng payment. ### Delivery Includes: - **Test** - Test type: "), Sheet1!R55,"-item multiple choice test - Dimensions: A4 bond paper - Format: PDF, created using LaTeX - **Answer Key** - Format: PDF, created using LaTeX - **Table of Specifications** - XLSX format", Sheet2!$D$6) -> *Tinatamad ka ba, walang time, o nahihirapang gumawa ng TOS at Term Exam mo, Grade 9 KasaMath? Kuha ka na ng Custom Assessment Package!* **Bakit perfect para sa’yo ang Custom Assessment Package?** - Makakatipid ka sa oras kaya makakapaghabol pa ng lessons. - Maganda at consistent ang formatting ng test questions at figures. - Ready na ang answer key kaya mas madali at mabilis ang pagche-check. - Fully customizable exam: kahit anong topic ang pwedeng covered - Maaga kang makakapag-submit ng TOS sa head mo. - Table of Specifications using the 21st Century format - Number of days: pwede kahit ilan - Number of items: kahit ilan basta maximum of 50 - Perfect sa teachers na gusto ng pasadyang exam [![Sample TOS formatted using 21st Century Skills](https://res.cloudinary.com/dadubemrv/image/upload/v1768351176/tv5zwilsnzrad6r2q6sw.png)](https://res.cloudinary.com/dadubemrv/image/upload/v1768351176/tv5zwilsnzrad6r2q6sw.png) *Sample TOS formatted using 21st Century Skills* --- 📑 **Competencies Covered** - Identify the relationships between angles formed by parallel lines cut by a transversal. - Determine angle measures involving angle pairs, parallel and perpendicular lines, and parallel lines cut by a transversal. - Graph a linear function and determine its domain, range, intercepts, and slope. - Solve problems involving linear functions. - Determine conditions that guarantee parallelism and perpendicularity of lines. - Classify quadrilaterals based on formal definitions. - Determine the properties of parallelograms. - Use properties of parallelograms to find measures of angles, sides, perpendicular height, and diagonals. - Solve problems involving parallelograms, rectangles, squares and rhombuses by applying their different properties. --- ## Step 1: I-fill out at i-submit ang Order Form. {{< iframe src="https://cityofsmiles.github.io/auto-order-form/?id=g9-t1-te-cp" height="850" >}} ## Step 2: Payment and Delivery ### Payment Methods Mag-send ka lang ng ₱359 para sa **Term Exam**. - **Landbank**: 0695077289 (Jonathan R. Bacolod) - **GCash**: 09128389571 (Jonathan Bacolod) - **Maya**: 09128389571 (Jonathan Bacolod) **Isend ang Screenshot ng Payment kahit saan dito:** - Email: [texmathpro@gmail.com](mailto:texmathpro@gmail.com) - Facebook: https://m.me/jonathan.r.bacolod - Telegram: https://t.me/Jonathan_Bacolod Isesend ko ang files sa email address mo after ng payment. ### Delivery Includes: - **Test** - Test type: 50-item multiple choice test - Dimensions: A4 bond paper - Format: PDF, created using LaTeX - **Answer Key** - Format: PDF, created using LaTeX - **Table of Specifications** - XLSX format --- Salamat sa pagsuporta sa **TeXMathPro, KasaMath**! Kung may tanong o suggestion ka, [kontakin mo lang ako](mailto:texmathpro@gmail.com). | F55: 359 | G55: 245 | H55: FALSE | I55: 46176 | J55: TRUE | K55: 46176 | L55: --- 📑 **Competencies Covered** - Identify the relationships between angles formed by parallel lines cut by a transversal. - Determine angle measures involving angle pairs, parallel and perpendicular lines, and parallel lines cut by a transversal. - Graph a linear function and determine its domain, range, intercepts, and slope. - Solve problems involving linear functions. - Determine conditions that guarantee parallelism and perpendicularity of lines. - Classify quadrilaterals based on formal definitions. - Determine the properties of parallelograms. - Use properties of parallelograms to find measures of angles, sides, perpendicular height, and diagonals. - Solve problems involving parallelograms, rectangles, squares and rhombuses by applying their different properties. | M55: {=_xlfn.XLOOKUP(TRUE,ISNUMBER(SEARCH(Sheet2!A$23:A$26,A55)),Sheet2!B$23:B$26,"")} -> Term Exam | N55: {=_xlfn.XLOOKUP(TRUE,ISNUMBER(SEARCH(Sheet2!A$32:A$34,A55)),Sheet2!B$32:B$34,"")} -> First Term | O55: {=_xlfn.XLOOKUP(TRUE,ISNUMBER(SEARCH(Sheet2!A$38:A$41,A55)),Sheet2!B$38:B$41,"")} -> Grade 9 | P55: {=_xlfn.XLOOKUP(TRUE,ISNUMBER(SEARCH(Sheet2!A$45:A$47,A55)),Sheet2!B$45:B$47,"")} -> Custom Assessment Package | Q55: 25 | R55: 50
A56: G10-T1-TE-BP | B56: Grade 10 T1 Term Exam + TOS + Answer Key (Basic) | C56: https://res.cloudinary.com/dadubemrv/image/upload/v1771581176/bpjq83f63jehupa4mqs7.jpg | D56: =Sheet2!$D$2 -> 0 | F56: 120 | G56: 84 | H56: FALSE | I56: 46176 | J56: FALSE | K56: 46176
A57: G10-T1-TE-SP | B57: Grade 10 T1 Term Exam + TOS + Answer Key (Standard) | C57: https://res.cloudinary.com/dadubemrv/image/upload/v1771581176/bpjq83f63jehupa4mqs7.jpg | D57: =Sheet2!$E$2 -> 0 | F57: 165 | G57: 115 | H57: FALSE | I57: 46176 | J57: FALSE | K57: 46176
A58: G10-T1-TE-CP | B58: Grade 10 T1 Term Exam + TOS + Answer Key (Custom) | C58: https://res.cloudinary.com/dadubemrv/image/upload/v1771581176/bpjq83f63jehupa4mqs7.jpg | D58: =Sheet2!$F$2 -> 0 | F58: 350 | G58: 245 | H58: FALSE | I58: 46176 | J58: FALSE | K58: 46176
A59: G7-T1-MQ | B59: Grade 7 T1 Multiple-Choice Quizzes + Answer Keys | C59: https://res.cloudinary.com/dadubemrv/image/upload/v1784259489/jon7ha1w9jssifhlph7u.png,https://res.cloudinary.com/dadubemrv/image/upload/v1784259493/l9iore0gcpvw7hcecvvt.png,https://res.cloudinary.com/dadubemrv/image/upload/v1784259496/fyqiathetzwuch9vy3t7.png | D59: =CONCATENATE(Sheet2!$C$6, S59," Multiple-choice Quizzes | | Paper Size | A4 Bond Paper | | File Format | PDF (Typeset in LaTeX) | | Price | ₱",IF(H59, G59, F59),"|", CHAR(10), CHAR(10),CHAR(10), L59, CHAR(10),CHAR(10),CHAR(10), "---",CHAR(10),CHAR(10), "📥 **I-fill out ang Order Form**",CHAR(10),CHAR(10), "{{< iframe src=""", "https://cityofsmiles.github.io/auto-order-form/?id=", LOWER(A59), """ height=""850"" >}}", CHAR(10), CHAR(10),CHAR(10),"--- 🛒 **Payment Methods** Mag-send ka lang ng ₱",Sheet1!F59," para sa **", Sheet1!M59,"**. ", Sheet2!$B$6) -> Tinatamad ka ba, walang time, o nahihirapang gumawa ng quizzes mo this term, KasaMath? ✨ Kuha ka na ng Multiple Choice Quizzes with Answer Keys para: - Tipid ka sa oras at makapag-focus sa pagtuturo. - Maganda at consistent ang formatting ng test questions at figures mo. - Ready na ang answer key at di ka na magsasagot ng questions. - Masanay ang students sa pagsagot ng multiple choice test. - Parallel ang quiz items sa questions na lalabas sa Summative test at Term Exam. --- 📑 **Product Details** | Feature | Details | |---|---| | Content |9 Multiple-choice Quizzes | | Paper Size | A4 Bond Paper | | File Format | PDF (Typeset in LaTeX) | | Price | ₱89| --- 📑 **Topics Covered** **Quiz 1.01.1: Drawing Polygons by Side and Angle Measurements** (35 items) - Lesson 1.01.1: Drawing Regular Polygons by Side and Angle Measurements - Lesson 1.01.2: Drawing Irregular Polygons by Side and Angle Measurements - Lesson 1.01.3: Constructing Triangles, Quadrilaterals, and Regular Polygons **Quiz 1.02.1: Relationships Between Angle Pairs** (35 items) - Lesson 1.02.1: Relationships Between Angle Pairs - Lesson 1.02.2: Classifying Regular and Irregular Polygons - Lesson 1.02.3: Classifying Convex and Non-Convex Polygons **Quiz 1.03.1: Exterior and Interior Angles of Polygons** (35 items) - Lesson 1.03.1: Exterior and Interior Angles of Polygons - Lesson 1.03.2: Finding Angle Measures of Polygons - Lesson 1.03.3: Determining the Number of Sides of Polygons **Quiz 1.04.1: Percentage Increase and Decrease** (35 items) - Lesson 1.04.1: Percentage Increase - Lesson 1.04.2: Percentage Decrease - Lesson 1.04.3: Money Problems Involving Percentages **Quiz 1.05.1: Creating a Financial Plan** (25 items) - Lesson 1.05.1: Creating a Financial Plan **Quiz 1.06.1: Understanding Rates** (30 items) - Lesson 1.06.1: Understanding Rates - Lesson 1.06.2: Solving Problems Involving Rates **Quiz 1.07.1: Representing Rational Numbers** (35 items) - Lesson 1.07.1: Representing Rational Numbers - Lesson 1.07.2: Ordering Rational Numbers on the Number Line **Quiz 1.08.1: Operations on Rational Numbers** (25 items) - Lesson 1.08.1: Adding Rational Numbers - Lesson 1.08.2: Subtracting Rational Numbers - Lesson 1.09.1: Multiplying Rational Numbers - Lesson 1.09.2: Dividing Rational Numbers **Quiz 1.10.1: Square Roots, Cube Roots, and Irrational Numbers** (35 items) - Lesson 1.10.1: Square Roots of Perfect Squares - Lesson 1.10.2: Cube Roots of Perfect Cubes - Lesson 1.10.3: Irrational Numbers and Their Location on the Number Line --- 📥 **I-fill out ang Order Form** {{< iframe src="https://cityofsmiles.github.io/auto-order-form/?id=g7-t1-mq" height="850" >}} --- 🛒 **Payment Methods** Mag-send ka lang ng ₱89 para sa **Multiple-choice Quizzes**. - **Landbank**: 0695077289 (Jonathan R. Bacolod) - **GCash**: 09128389571 (Jonathan Bacolod) - **Maya**: 09128389571 (Jonathan Bacolod) **Isend ang Screenshot ng Payment kahit saan dito:** - Email: [texmathpro@gmail.com](mailto:texmathpro@gmail.com) - Facebook: https://m.me/jonathan.r.bacolod - Telegram: https://t.me/Jonathan_Bacolod Isesend ko ang files sa email address mo after ng payment. --- Salamat sa pagsuporta sa **TeXMathPro, KasaMath**! Kung may tanong o suggestion ka, [kontakin mo lang ako](https://texmathpro.github.io/contact/). | F59: 89 | G59: 79 | H59: FALSE | I59: 46176 | J59: TRUE | K59: 46176 | L59: --- 📑 **Topics Covered** **Quiz 1.01.1: Drawing Polygons by Side and Angle Measurements** (35 items) - Lesson 1.01.1: Drawing Regular Polygons by Side and Angle Measurements - Lesson 1.01.2: Drawing Irregular Polygons by Side and Angle Measurements - Lesson 1.01.3: Constructing Triangles, Quadrilaterals, and Regular Polygons **Quiz 1.02.1: Relationships Between Angle Pairs** (35 items) - Lesson 1.02.1: Relationships Between Angle Pairs - Lesson 1.02.2: Classifying Regular and Irregular Polygons - Lesson 1.02.3: Classifying Convex and Non-Convex Polygons **Quiz 1.03.1: Exterior and Interior Angles of Polygons** (35 items) - Lesson 1.03.1: Exterior and Interior Angles of Polygons - Lesson 1.03.2: Finding Angle Measures of Polygons - Lesson 1.03.3: Determining the Number of Sides of Polygons **Quiz 1.04.1: Percentage Increase and Decrease** (35 items) - Lesson 1.04.1: Percentage Increase - Lesson 1.04.2: Percentage Decrease - Lesson 1.04.3: Money Problems Involving Percentages **Quiz 1.05.1: Creating a Financial Plan** (25 items) - Lesson 1.05.1: Creating a Financial Plan **Quiz 1.06.1: Understanding Rates** (30 items) - Lesson 1.06.1: Understanding Rates - Lesson 1.06.2: Solving Problems Involving Rates **Quiz 1.07.1: Representing Rational Numbers** (35 items) - Lesson 1.07.1: Representing Rational Numbers - Lesson 1.07.2: Ordering Rational Numbers on the Number Line **Quiz 1.08.1: Operations on Rational Numbers** (25 items) - Lesson 1.08.1: Adding Rational Numbers - Lesson 1.08.2: Subtracting Rational Numbers - Lesson 1.09.1: Multiplying Rational Numbers - Lesson 1.09.2: Dividing Rational Numbers **Quiz 1.10.1: Square Roots, Cube Roots, and Irrational Numbers** (35 items) - Lesson 1.10.1: Square Roots of Perfect Squares - Lesson 1.10.2: Cube Roots of Perfect Cubes - Lesson 1.10.3: Irrational Numbers and Their Location on the Number Line | M59: {=_xlfn.XLOOKUP(TRUE,ISNUMBER(SEARCH(Sheet2!A$23:A$26,A59)),Sheet2!B$23:B$26,"")} -> Multiple-choice Quizzes | N59: {=_xlfn.XLOOKUP(TRUE,ISNUMBER(SEARCH(Sheet2!A$32:A$34,A59)),Sheet2!B$32:B$34,"")} -> First Term | O59: {=_xlfn.XLOOKUP(TRUE,ISNUMBER(SEARCH(Sheet2!A$38:A$41,A59)),Sheet2!B$38:B$41,"")} -> Grade 7 | P59: {=_xlfn.XLOOKUP(TRUE,ISNUMBER(SEARCH(Sheet2!A$45:A$47,A59)),Sheet2!B$45:B$47,"")} | S59: 9
A60: G8-T1-MQ | B60: Grade 8 T1 Multiple-Choice Quizzes + Answer Keys | C60: https://res.cloudinary.com/dadubemrv/image/upload/v1771463118/oreyawsxzur1rlvsgtxv.jpg | D60: =CONCATENATE(Sheet2!$C$6, F60/25," Multiple-choice Quizzes | | Paper Size | A4 Bond Paper | | File Format | PDF (Typeset in LaTeX) | | Price | ₱",IF(H60, G60, F60),"|", CHAR(10),CHAR(10),CHAR(10), "---",CHAR(10),CHAR(10), "📥 **I-fill out ang Order Form**",CHAR(10),CHAR(10), "{{< iframe src=""", "https://cityofsmiles.github.io/auto-order-form/?id=", LOWER(A60), """ height=""850"" >}}", CHAR(10), CHAR(10),CHAR(10), L60, CHAR(10), CHAR(10),CHAR(10), Sheet2!$B$6) -> Tinatamad ka ba, walang time, o nahihirapang gumawa ng quizzes mo this term, KasaMath? ✨ Kuha ka na ng Multiple Choice Quizzes with Answer Keys para: - Tipid ka sa oras at makapag-focus sa pagtuturo. - Maganda at consistent ang formatting ng test questions at figures mo. - Ready na ang answer key at di ka na magsasagot ng questions. - Masanay ang students sa pagsagot ng multiple choice test. - Parallel ang quiz items sa questions na lalabas sa Summative test at Term Exam. --- 📑 **Product Details** | Feature | Details | |---|---| | Content |6 Multiple-choice Quizzes | | Paper Size | A4 Bond Paper | | File Format | PDF (Typeset in LaTeX) | | Price | ₱150| --- 📥 **I-fill out ang Order Form** {{< iframe src="https://cityofsmiles.github.io/auto-order-form/?id=g8-t1-mq" height="850" >}} --- **Quiz 1.1: Measures of Central Tendency for Ungrouped Data** (25 items) - Lesson 1.1.1: Mean for Ungrouped Data - Lesson 1.1.2: Median and Mode for Ungrouped Data - Lesson 1.2: Interpreting Statistical Data Using Measures of Central Tendency **Quiz 1.2: Operations on Monomials** (30 items) - Lesson 1.3: Modeling Real-Life Situations with Algebraic Expressions - Lesson 1.4.1: Adding Simple Monomials - Lesson 1.4.2: Subtracting Simple Monomials - Lesson 1.5.1: Multiplying Simple Monomials - Lesson 1.5.2: Dividing Simple Monomials - Lesson 1.5.3: Deriving the Laws of Exponents - Lesson 1.6.1: Multiplying Monomials Using the Distributive Property **Quiz 1.3: Multiplying Binomials** (30 items) - Lesson 1.6.2: Multiplying Binomials Using the Distributive Property - Lesson 1.7.1: Squaring Binomials - Lesson 1.7.2: Multiplying the Sum and Difference of Two Terms **Quiz 1.4: Factoring Polynomials** (35 items) - Lesson 1.8.1: Factoring Polynomials with a Common Monomial Factor - Lesson 1.8.2: Factoring Polynomials as Difference of Two Squares - Lesson 1.8.3: Factoring the Sum and Difference of Two Cubes - Lesson 1.8.4: Factoring Perfect Square Trinomials - Lesson 1.8.5: Factoring Trinomials with 1 as Leading Coefficient - Lesson 1.8.6: Factoring by Grouping - Lesson 1.8.7: Factoring Quadratic Trinomials - Lesson 1.9: Solving Problems Involving Special Products and Factoring of Polynomials **Quiz 1.5: Operations on Rational Algebraic Expressions** (25 items) - Lesson 1.10: Simplifying Rational Algebraic Expressions - Lesson 1.11.1: Addition of Rational Algebraic Expressions - Lesson 1.11.2: Subtraction of Rational Algebraic Expressions - Lesson 1.11.3: Multiplication of Rational Algebraic Expressions - Lesson 1.11.4: Division of Rational Algebraic Expressions - Lesson 1.12: Solving Simple Rational Algebraic Equations Using Cross-Multiplication **Quiz 1.6: Finding Patterns in Sequences** (30 items) - Lesson 1.13.1: Finding Patterns in Arithmetic Sequences - Lesson 1.13.2: Finding Patterns in Geometric Sequences - **Landbank**: 0695077289 (Jonathan R. Bacolod) - **GCash**: 09128389571 (Jonathan Bacolod) - **Maya**: 09128389571 (Jonathan Bacolod) **Isend ang Screenshot ng Payment kahit saan dito:** - Email: [texmathpro@gmail.com](mailto:texmathpro@gmail.com) - Facebook: https://m.me/jonathan.r.bacolod - Telegram: https://t.me/Jonathan_Bacolod Isesend ko ang files sa email address mo after ng payment. --- Salamat sa pagsuporta sa **TeXMathPro, KasaMath**! Kung may tanong o suggestion ka, [kontakin mo lang ako](https://texmathpro.github.io/contact/). | F60: 150 | H60: FALSE | I60: 46176 | J60: FALSE | K60: 46176 | L60: --- **Quiz 1.1: Measures of Central Tendency for Ungrouped Data** (25 items) - Lesson 1.1.1: Mean for Ungrouped Data - Lesson 1.1.2: Median and Mode for Ungrouped Data - Lesson 1.2: Interpreting Statistical Data Using Measures of Central Tendency **Quiz 1.2: Operations on Monomials** (30 items) - Lesson 1.3: Modeling Real-Life Situations with Algebraic Expressions - Lesson 1.4.1: Adding Simple Monomials - Lesson 1.4.2: Subtracting Simple Monomials - Lesson 1.5.1: Multiplying Simple Monomials - Lesson 1.5.2: Dividing Simple Monomials - Lesson 1.5.3: Deriving the Laws of Exponents - Lesson 1.6.1: Multiplying Monomials Using the Distributive Property **Quiz 1.3: Multiplying Binomials** (30 items) - Lesson 1.6.2: Multiplying Binomials Using the Distributive Property - Lesson 1.7.1: Squaring Binomials - Lesson 1.7.2: Multiplying the Sum and Difference of Two Terms **Quiz 1.4: Factoring Polynomials** (35 items) - Lesson 1.8.1: Factoring Polynomials with a Common Monomial Factor - Lesson 1.8.2: Factoring Polynomials as Difference of Two Squares - Lesson 1.8.3: Factoring the Sum and Difference of Two Cubes - Lesson 1.8.4: Factoring Perfect Square Trinomials - Lesson 1.8.5: Factoring Trinomials with 1 as Leading Coefficient - Lesson 1.8.6: Factoring by Grouping - Lesson 1.8.7: Factoring Quadratic Trinomials - Lesson 1.9: Solving Problems Involving Special Products and Factoring of Polynomials **Quiz 1.5: Operations on Rational Algebraic Expressions** (25 items) - Lesson 1.10: Simplifying Rational Algebraic Expressions - Lesson 1.11.1: Addition of Rational Algebraic Expressions - Lesson 1.11.2: Subtraction of Rational Algebraic Expressions - Lesson 1.11.3: Multiplication of Rational Algebraic Expressions - Lesson 1.11.4: Division of Rational Algebraic Expressions - Lesson 1.12: Solving Simple Rational Algebraic Equations Using Cross-Multiplication **Quiz 1.6: Finding Patterns in Sequences** (30 items) - Lesson 1.13.1: Finding Patterns in Arithmetic Sequences - Lesson 1.13.2: Finding Patterns in Geometric Sequences
A61: G9-T1-MQ | B61: Grade 9 T1 Multiple-Choice Quizzes + Answer Keys | C61: https://res.cloudinary.com/dadubemrv/image/upload/v1784868820/ozzzxppeyyvj0s2tjymk.png,https://res.cloudinary.com/dadubemrv/image/upload/v1784868830/kgezh16t4knvga2qdead.png,https://res.cloudinary.com/dadubemrv/image/upload/v1784868834/juzddujgsxbdnu454ck5.png | D61: =CONCATENATE(Sheet2!$C$6, S61," Multiple-choice Quizzes | | Paper Size | A4 Bond Paper | | File Format | PDF (Typeset in LaTeX) | | Price | ₱",IF(H61, G61, F61),"|", CHAR(10), CHAR(10),CHAR(10), L61, CHAR(10),CHAR(10),CHAR(10), "---",CHAR(10),CHAR(10), "📥 **I-fill out ang Order Form**",CHAR(10),CHAR(10), "{{< iframe src=""", "https://cityofsmiles.github.io/auto-order-form/?id=", LOWER(A61), """ height=""850"" >}}", CHAR(10), CHAR(10),CHAR(10),"--- 🛒 **Payment Methods** Mag-send ka lang ng ₱",Sheet1!F61," para sa **", Sheet1!M61,"**. ", Sheet2!$B$6) -> Tinatamad ka ba, walang time, o nahihirapang gumawa ng quizzes mo this term, KasaMath? ✨ Kuha ka na ng Multiple Choice Quizzes with Answer Keys para: - Tipid ka sa oras at makapag-focus sa pagtuturo. - Maganda at consistent ang formatting ng test questions at figures mo. - Ready na ang answer key at di ka na magsasagot ng questions. - Masanay ang students sa pagsagot ng multiple choice test. - Parallel ang quiz items sa questions na lalabas sa Summative test at Term Exam. --- 📑 **Product Details** | Feature | Details | |---|---| | Content |10 Multiple-choice Quizzes | | Paper Size | A4 Bond Paper | | File Format | PDF (Typeset in LaTeX) | | Price | ₱99| --- 📑 **Topics Covered** **Quiz 1.01.1: Basic Undefined Terms and Geometric Notation** (35 items) - Lesson 1. 1.01.1: Basic Undefined Terms and Geometric Notation - Lesson 1. 1.01.2: Constructing Parallel and Perpendicular Lines **Quiz 1.02.1: Angles Formed by Parallel Lines and a Transversal** (30 items) - Lesson 1. 1.02.1: Angles Formed by Parallel Lines and a Transversal - Lesson 1. 1.02.2: Solving Angle Measures with Parallel and Perpendicular Lines **Quiz 1.03.1: Introduction to Relations and Functions** (30 items) - Lesson 1. 1.03.1: Introduction to Relations and Functions - Lesson 1. 1.03.2: Domain of a Function - Lesson 1. 1.03.3: Range of a Function **Quiz 1.04.1: Representing Relationships as Functions** (30 items) - Lesson 1. 1.04.1: Representing Relationships as Functions - Lesson 1. 1.04.2: Slope of Linear Functions from Graphs - Lesson 1. 1.04.3: Zeros of Linear Functions from Graphs - Lesson 1. 1.04.4: Slope of Linear Functions from Equations - Lesson 1. 1.04.5: Zeros of Linear Functions from Equations - Lesson 1. 1.04.6: Slope of Linear Functions from Tables - Lesson 1. 1.04.7: Zeros of Linear Functions from Tables **Quiz 1.05.1: Graphing Linear Functions: Domain and Range** (35 items) - Lesson 1. 1.05.1: Graphing Linear Functions: Domain and Range - Lesson 1. 1.05.2: Graphing Linear Function - Intercepts and Slope - Lesson 1. 1.05.3: Representing Real-Life Linear Relationships **Quiz 1.06.1: Solving Problems Involving Linear Functions** (30 items) - Lesson 1. 1.06.1: Solving Problems Involving Linear Functions - Lesson 1. 1.06.2: Conditions that Guarantee Parallelism - Lesson 1. 1.06.3: Conditions that Guarantee Perpendicularity **Quiz 1.07.1: Classifying Quadrilaterals** (35 items) - Lesson 1. 1.07.1: Classifying Quadrilaterals - Lesson 1. 1.07.2: Properties of Parallelograms **Quiz 1.08.1: Finding Lengths in Parallelograms** (30 items) - Lesson 1. 1.08.1: Finding Side Lengths in Parallelograms - Lesson 1. 1.08.2: Finding Angle Measures in Parallelograms - Lesson 1. 1.08.3: Finding Perpendicular Heights in Parallelograms - Lesson 1. 1.08.4: Finding Diagonal Measures in Parallelograms **Quiz 1.09.1: Problem Solving with Parallelograms** (30 items) - Lesson 1. 1.09.1: Problem Solving with Parallelograms and Rectangles - Lesson 1. 1.09.2: Problem Solving with Squares and Rhombuses **Quiz 1.10.1: Proving Properties of Parallelograms** (25 items) - Lesson 1. 1.10.1: Proving Properties of Parallelograms --- 📥 **I-fill out ang Order Form** {{< iframe src="https://cityofsmiles.github.io/auto-order-form/?id=g9-t1-mq" height="850" >}} --- 🛒 **Payment Methods** Mag-send ka lang ng ₱99 para sa **Multiple-choice Quizzes**. - **Landbank**: 0695077289 (Jonathan R. Bacolod) - **GCash**: 09128389571 (Jonathan Bacolod) - **Maya**: 09128389571 (Jonathan Bacolod) **Isend ang Screenshot ng Payment kahit saan dito:** - Email: [texmathpro@gmail.com](mailto:texmathpro@gmail.com) - Facebook: https://m.me/jonathan.r.bacolod - Telegram: https://t.me/Jonathan_Bacolod Isesend ko ang files sa email address mo after ng payment. --- Salamat sa pagsuporta sa **TeXMathPro, KasaMath**! Kung may tanong o suggestion ka, [kontakin mo lang ako](https://texmathpro.github.io/contact/). | F61: 99 | G61: 89 | H61: FALSE | I61: 46176 | J61: TRUE | K61: 46176 | L61: --- 📑 **Topics Covered** **Quiz 1.01.1: Basic Undefined Terms and Geometric Notation** (35 items) - Lesson 1. 1.01.1: Basic Undefined Terms and Geometric Notation - Lesson 1. 1.01.2: Constructing Parallel and Perpendicular Lines **Quiz 1.02.1: Angles Formed by Parallel Lines and a Transversal** (30 items) - Lesson 1. 1.02.1: Angles Formed by Parallel Lines and a Transversal - Lesson 1. 1.02.2: Solving Angle Measures with Parallel and Perpendicular Lines **Quiz 1.03.1: Introduction to Relations and Functions** (30 items) - Lesson 1. 1.03.1: Introduction to Relations and Functions - Lesson 1. 1.03.2: Domain of a Function - Lesson 1. 1.03.3: Range of a Function **Quiz 1.04.1: Representing Relationships as Functions** (30 items) - Lesson 1. 1.04.1: Representing Relationships as Functions - Lesson 1. 1.04.2: Slope of Linear Functions from Graphs - Lesson 1. 1.04.3: Zeros of Linear Functions from Graphs - Lesson 1. 1.04.4: Slope of Linear Functions from Equations - Lesson 1. 1.04.5: Zeros of Linear Functions from Equations - Lesson 1. 1.04.6: Slope of Linear Functions from Tables - Lesson 1. 1.04.7: Zeros of Linear Functions from Tables **Quiz 1.05.1: Graphing Linear Functions: Domain and Range** (35 items) - Lesson 1. 1.05.1: Graphing Linear Functions: Domain and Range - Lesson 1. 1.05.2: Graphing Linear Function - Intercepts and Slope - Lesson 1. 1.05.3: Representing Real-Life Linear Relationships **Quiz 1.06.1: Solving Problems Involving Linear Functions** (30 items) - Lesson 1. 1.06.1: Solving Problems Involving Linear Functions - Lesson 1. 1.06.2: Conditions that Guarantee Parallelism - Lesson 1. 1.06.3: Conditions that Guarantee Perpendicularity **Quiz 1.07.1: Classifying Quadrilaterals** (35 items) - Lesson 1. 1.07.1: Classifying Quadrilaterals - Lesson 1. 1.07.2: Properties of Parallelograms **Quiz 1.08.1: Finding Lengths in Parallelograms** (30 items) - Lesson 1. 1.08.1: Finding Side Lengths in Parallelograms - Lesson 1. 1.08.2: Finding Angle Measures in Parallelograms - Lesson 1. 1.08.3: Finding Perpendicular Heights in Parallelograms - Lesson 1. 1.08.4: Finding Diagonal Measures in Parallelograms **Quiz 1.09.1: Problem Solving with Parallelograms** (30 items) - Lesson 1. 1.09.1: Problem Solving with Parallelograms and Rectangles - Lesson 1. 1.09.2: Problem Solving with Squares and Rhombuses **Quiz 1.10.1: Proving Properties of Parallelograms** (25 items) - Lesson 1. 1.10.1: Proving Properties of Parallelograms | M61: {=_xlfn.XLOOKUP(TRUE,ISNUMBER(SEARCH(Sheet2!A$23:A$26,A61)),Sheet2!B$23:B$26,"")} -> Multiple-choice Quizzes | N61: {=_xlfn.XLOOKUP(TRUE,ISNUMBER(SEARCH(Sheet2!A$32:A$34,A61)),Sheet2!B$32:B$34,"")} -> First Term | O61: {=_xlfn.XLOOKUP(TRUE,ISNUMBER(SEARCH(Sheet2!A$38:A$41,A61)),Sheet2!B$38:B$41,"")} -> Grade 9 | P61: {=_xlfn.XLOOKUP(TRUE,ISNUMBER(SEARCH(Sheet2!A$45:A$47,A61)),Sheet2!B$45:B$47,"")} | S61: 10
A62: G10-T1-MQ | B62: Grade 10 T1 Multiple-Choice Quizzes + Answer Keys | C62: https://res.cloudinary.com/dadubemrv/image/upload/v1771462496/coog2txapkkedhuakqjx.jpg | D62: =CONCATENATE(Sheet2!$C$6, F62/25," Multiple-choice Quizzes | | Paper Size | A4 Bond Paper | | File Format | PDF (Typeset in LaTeX) | | Price | ₱",IF(H62, G62, F62),"|", CHAR(10),CHAR(10),CHAR(10), "---",CHAR(10),CHAR(10), "📥 **I-fill out ang Order Form**",CHAR(10),CHAR(10), "{{< iframe src=""", "https://cityofsmiles.github.io/auto-order-form/?id=", LOWER(A62), """ height=""850"" >}}", CHAR(10), CHAR(10),CHAR(10), L62, CHAR(10), CHAR(10),CHAR(10), Sheet2!$B$6) -> Tinatamad ka ba, walang time, o nahihirapang gumawa ng quizzes mo this term, KasaMath? ✨ Kuha ka na ng Multiple Choice Quizzes with Answer Keys para: - Tipid ka sa oras at makapag-focus sa pagtuturo. - Maganda at consistent ang formatting ng test questions at figures mo. - Ready na ang answer key at di ka na magsasagot ng questions. - Masanay ang students sa pagsagot ng multiple choice test. - Parallel ang quiz items sa questions na lalabas sa Summative test at Term Exam. --- 📑 **Product Details** | Feature | Details | |---|---| | Content |4 Multiple-choice Quizzes | | Paper Size | A4 Bond Paper | | File Format | PDF (Typeset in LaTeX) | | Price | ₱100| --- 📥 **I-fill out ang Order Form** {{< iframe src="https://cityofsmiles.github.io/auto-order-form/?id=g10-t1-mq" height="850" >}} --- **Quiz 1.1: Arithmetic Sequence and Arithmetic Mean** (30 items) - Lesson 1.01.1: Describing and Generating Patterns in Sequences - Lesson 1.01.2: Finding the General Term of a Sequence - Lesson 1.01.3: Finding the General Term of a Sequence with Fractional and Radical Expressions - Lesson 1.02.1: Identifying Patterns in Arithmetic Sequences and Finding the Next Terms - Lesson 1.02.2: Finding the Missing Term Common Difference and Number of Terms in an Arithmetic Sequence **Quiz 1.2: Geometric Sequence and Geometric Mean** (30 items) - Lesson 1.03.1: Finding the Indicated Number of Arithmetic Means Between Two Terms - Lesson 1.03.2: Finding the General Term of an Arithmetic Sequence - Lesson 1.03.3: Finding the Sum of Terms in an Arithmetic Sequence - Lesson 1.04.1: Identifying Patterns in Geometric Sequences and Finding the Next Terms - Lesson 1.04.2: Finding the Missing Term Common Ratio and Number of Terms in a Geometric Sequence - Lesson 1.05.1: Classifying Sequences as Arithmetic Geometric or Neither - Lesson 1.05.2: Differentiating Finite and Infinite Geometric Sequences - Lesson 1.06.1: Finding the Indicated Number of Geometric Means Between Two Terms - Lesson 1.06.2: Finding the General Term of a Geometric Sequence - Lesson 1.06.3: Finding the Sum of Terms in a Finite Geometric Sequence - Lesson 1.06.4: Determining Convergence or Divergence of Infinite Geometric Series and Finding Their Sum - Lesson 1.07.1: Solving Problems Involving Arithmetic Sequences and Series - Lesson 1.07.2: Solving Problems Involving Finite Geometric Sequences and Series - Lesson 1.07.3: Solving Problems Involving Infinite Geometric Sequences and Series **Quiz 1.3: Dividing and Factoring Polynomials** (30 items) - Lesson 1.08.1: Dividing Polynomials Using Long Division - Lesson 1.08.2: Dividing Polynomials Using Synthetic Division - Lesson 1.08.3: Dividing Polynomials with Missing Terms and Finding the Divisor or Dividend Using Synthetic Division - Lesson 1.09.1: Finding the Remainder Using the Remainder Theorem - Lesson 1.09.2: Using the Factor Theorem to Determine Factors of a Polynomial - Lesson 1.09.3: Applying the Factor Theorem and Remainder Theorem to Solve Problems - Lesson 1.10.1: Finding the Factors of Polynomial Expressions of Degree 2 - Lesson 1.10.2: Finding the Factors of Polynomial Expressions of Degree 3 and Above **Quiz 1.4: Polynomial Equations** (30 items) - Lesson 1.11.1: Applying the Fundamental Theorem of Algebra to Find the Number of Roots of Polynomial Equations - Lesson 1.11.2: Describing and Finding the Integral Roots of Polynomial Equations Using the Integral Zero Theorem - Lesson 1.12.1: Determining the List of Possible Rational Roots Using the Rational Roots Theorem - Lesson 1.12.2: Describing and Finding the Rational Roots of Polynomial Equations of Degree Greater than 2 - Lesson 1.12.3: Solving Polynomial Equations of Degree Greater than 2 - Lesson 1.13.1: Solving Problems Involving Polynomials - Lesson 1.13.2: Solving Problems Involving Polynomial Equations - **Landbank**: 0695077289 (Jonathan R. Bacolod) - **GCash**: 09128389571 (Jonathan Bacolod) - **Maya**: 09128389571 (Jonathan Bacolod) **Isend ang Screenshot ng Payment kahit saan dito:** - Email: [texmathpro@gmail.com](mailto:texmathpro@gmail.com) - Facebook: https://m.me/jonathan.r.bacolod - Telegram: https://t.me/Jonathan_Bacolod Isesend ko ang files sa email address mo after ng payment. --- Salamat sa pagsuporta sa **TeXMathPro, KasaMath**! Kung may tanong o suggestion ka, [kontakin mo lang ako](https://texmathpro.github.io/contact/). | F62: 100 | H62: FALSE | I62: 46176 | J62: FALSE | K62: 46176 | L62: --- **Quiz 1.1: Arithmetic Sequence and Arithmetic Mean** (30 items) - Lesson 1.01.1: Describing and Generating Patterns in Sequences - Lesson 1.01.2: Finding the General Term of a Sequence - Lesson 1.01.3: Finding the General Term of a Sequence with Fractional and Radical Expressions - Lesson 1.02.1: Identifying Patterns in Arithmetic Sequences and Finding the Next Terms - Lesson 1.02.2: Finding the Missing Term Common Difference and Number of Terms in an Arithmetic Sequence **Quiz 1.2: Geometric Sequence and Geometric Mean** (30 items) - Lesson 1.03.1: Finding the Indicated Number of Arithmetic Means Between Two Terms - Lesson 1.03.2: Finding the General Term of an Arithmetic Sequence - Lesson 1.03.3: Finding the Sum of Terms in an Arithmetic Sequence - Lesson 1.04.1: Identifying Patterns in Geometric Sequences and Finding the Next Terms - Lesson 1.04.2: Finding the Missing Term Common Ratio and Number of Terms in a Geometric Sequence - Lesson 1.05.1: Classifying Sequences as Arithmetic Geometric or Neither - Lesson 1.05.2: Differentiating Finite and Infinite Geometric Sequences - Lesson 1.06.1: Finding the Indicated Number of Geometric Means Between Two Terms - Lesson 1.06.2: Finding the General Term of a Geometric Sequence - Lesson 1.06.3: Finding the Sum of Terms in a Finite Geometric Sequence - Lesson 1.06.4: Determining Convergence or Divergence of Infinite Geometric Series and Finding Their Sum - Lesson 1.07.1: Solving Problems Involving Arithmetic Sequences and Series - Lesson 1.07.2: Solving Problems Involving Finite Geometric Sequences and Series - Lesson 1.07.3: Solving Problems Involving Infinite Geometric Sequences and Series **Quiz 1.3: Dividing and Factoring Polynomials** (30 items) - Lesson 1.08.1: Dividing Polynomials Using Long Division - Lesson 1.08.2: Dividing Polynomials Using Synthetic Division - Lesson 1.08.3: Dividing Polynomials with Missing Terms and Finding the Divisor or Dividend Using Synthetic Division - Lesson 1.09.1: Finding the Remainder Using the Remainder Theorem - Lesson 1.09.2: Using the Factor Theorem to Determine Factors of a Polynomial - Lesson 1.09.3: Applying the Factor Theorem and Remainder Theorem to Solve Problems - Lesson 1.10.1: Finding the Factors of Polynomial Expressions of Degree 2 - Lesson 1.10.2: Finding the Factors of Polynomial Expressions of Degree 3 and Above **Quiz 1.4: Polynomial Equations** (30 items) - Lesson 1.11.1: Applying the Fundamental Theorem of Algebra to Find the Number of Roots of Polynomial Equations - Lesson 1.11.2: Describing and Finding the Integral Roots of Polynomial Equations Using the Integral Zero Theorem - Lesson 1.12.1: Determining the List of Possible Rational Roots Using the Rational Roots Theorem - Lesson 1.12.2: Describing and Finding the Rational Roots of Polynomial Equations of Degree Greater than 2 - Lesson 1.12.3: Solving Polynomial Equations of Degree Greater than 2 - Lesson 1.13.1: Solving Problems Involving Polynomials - Lesson 1.13.2: Solving Problems Involving Polynomial Equations
A64: G7-T2-PS | B64: 2nd Term Ready-to-Teach PowerPoint Slides for Grade 7 | C64: https://res.cloudinary.com/dadubemrv/image/upload/v1789124434/ypw3znza6h1upyukhyqk.png,https://res.cloudinary.com/dadubemrv/image/upload/v1789124436/qhnwdhfvt39eq9a13mxi.png,https://res.cloudinary.com/dadubemrv/image/upload/v1789124439/dwhprvrdkruwlzhahuxg.png,https://res.cloudinary.com/dadubemrv/image/upload/v1789124441/ldz4veuc0xclyzazvjpd.png,https://res.cloudinary.com/dadubemrv/image/upload/v1789124444/yfzfz41zgvucwb87fyq7.png,https://res.cloudinary.com/dadubemrv/image/upload/v1789124447/klerbqxiphufp9h8cfwl.png,https://res.cloudinary.com/dadubemrv/image/upload/v1789124449/xcdhjdkczqsesu1iibrl.png,https://res.cloudinary.com/dadubemrv/image/upload/v1789124453/zxcjggv7y3gfbei0cfsq.png,https://res.cloudinary.com/dadubemrv/image/upload/v1789124455/sppno25aptwzywkjelp6.png,https://res.cloudinary.com/dadubemrv/image/upload/v1789124457/or7gbtcpifyljcwcleen.png,https://res.cloudinary.com/dadubemrv/image/upload/v1789124460/ybcgggun5pcdfuminz9d.png,https://res.cloudinary.com/dadubemrv/image/upload/v1789124462/iembev4wsxwznuwmx9u0.png | D64: =CONCATENATE("*Stressed ka na ba kakagawa ng ", Sheet1!N64, " PowerPoint presentations mo, ", Sheet1!O64," KasaMath? Kuha ka na ng ", Sheet1!M64,"!* **Bakit perfect para sa’yo ang ", Sheet1!M64,_xlfn._LONGTEXT("?** - Zero Prep Time: Open mo lang at ready ka nang magturo. - Plug-and-Teach: Complete na ang discussion, examples, practice, at activities. - Professional Look: Malinis, colorful, at classroom-friendly ang design. - Student-Friendly: Visual at madaling"," sundan kahit habang nagdi-discuss ang teacher. - More Teaching, Less Typing: Wala nang ilang oras na paggawa ng slides from scratch. - Editable PPTX: I-customize mo para sa style at needs ng klase mo. **Product Details**: - Pieces: "), Sheet1!S64, " slides, one for each lesson - Format: pptx - Price: ₱", Sheet1!F64, " --- ## Step 1: I-fill out at i-submit ang Order Form.", "{{< iframe src=""", "https://cityofsmiles.github.io/auto-order-form/?id=", LOWER(A64), """ height=""850"" >}}"," ## Step 2: Payment and Delivery ### Payment Methods Mag-send ka lang ng ₱",Sheet1!F64," para sa **", Sheet1!M64,_xlfn._LONGTEXT("**. - **Landbank**: 0695077289 (Jonathan R. Bacolod) - **GCash**: 09128389571 (Jonathan Bacolod) - **Maya**: 09128389571 (Jonathan Bacolod) **Isend ang Screenshot ng Payment kahit saan dito:** - Email: [texmathpro@gmail.com](mailto:texmathpro@gmai","l.com) - Facebook: https://m.me/jonathan.r.bacolod - Telegram: https://t.me/Jonathan_Bacolod Isesend ko ang files sa email address mo after ng payment. ### Delivery Includes: - "), Sheet1!S64," ",Sheet1!M64," - Format: PDF", Sheet2!$D$6) -> *Stressed ka na ba kakagawa ng Second Term PowerPoint presentations mo, Grade 7 KasaMath? Kuha ka na ng Ready-to-Teach PowerPoint Slides!* **Bakit perfect para sa’yo ang Ready-to-Teach PowerPoint Slides?** - Zero Prep Time: Open mo lang at ready ka nang magturo. - Plug-and-Teach: Complete na ang discussion, examples, practice, at activities. - Professional Look: Malinis, colorful, at classroom-friendly ang design. - Student-Friendly: Visual at madaling sundan kahit habang nagdi-discuss ang teacher. - More Teaching, Less Typing: Wala nang ilang oras na paggawa ng slides from scratch. - Editable PPTX: I-customize mo para sa style at needs ng klase mo. **Product Details**: - Pieces: 24 slides, one for each lesson - Format: pptx - Price: ₱240 --- ## Step 1: I-fill out at i-submit ang Order Form.{{< iframe src="https://cityofsmiles.github.io/auto-order-form/?id=g7-t2-ps" height="850" >}} ## Step 2: Payment and Delivery ### Payment Methods Mag-send ka lang ng ₱240 para sa **Ready-to-Teach PowerPoint Slides**. - **Landbank**: 0695077289 (Jonathan R. Bacolod) - **GCash**: 09128389571 (Jonathan Bacolod) - **Maya**: 09128389571 (Jonathan Bacolod) **Isend ang Screenshot ng Payment kahit saan dito:** - Email: [texmathpro@gmail.com](mailto:texmathpro@gmail.com) - Facebook: https://m.me/jonathan.r.bacolod - Telegram: https://t.me/Jonathan_Bacolod Isesend ko ang files sa email address mo after ng payment. ### Delivery Includes: - 24 Ready-to-Teach PowerPoint Slides - Format: PDF --- Salamat sa pagsuporta sa **TeXMathPro, KasaMath**! Kung may tanong o suggestion ka, [kontakin mo lang ako](mailto:texmathpro@gmail.com). | E64: =CONCATENATE("*Stressed ka na ba kakagawa ng ", Sheet1!N64, " PowerPoint presentations mo, ", Sheet1!O64," KasaMath? Kuha ka na ng ", Sheet1!M64,"!* **Bakit perfect para sa’yo ang ", Sheet1!M64,_xlfn._LONGTEXT("?** - Zero Prep Time: Open mo lang at ready ka nang magturo. - Plug-and-Teach: Complete na ang discussion, examples, practice, at activities. - Professional Look: Malinis, colorful, at classroom-friendly ang design. - Student-Friendly: Visual at madaling"," sundan kahit habang nagdi-discuss ang teacher. - More Teaching, Less Typing: Wala nang ilang oras na paggawa ng slides from scratch. - Editable PPTX: I-customize mo para sa style at needs ng klase mo. - Super Tipid pa dahil Early Bird ka! **Product Det","ails**: - Pieces: "), Sheet1!S64, " slides, one for each lesson - Format: pptx - Price: ₱", Sheet1!G64, " --- ## Step 1: I-fill out at i-submit ang Order Form.", "{{< iframe src=""", "https://cityofsmiles.github.io/auto-order-form/?id=", LOWER(A64), """ height=""850"" >}}"," ## Step 2: Payment and Delivery ### Payment Methods Mag-send ka lang ng ₱",Sheet1!G64," para sa **", Sheet1!M64,_xlfn._LONGTEXT("**. - **Landbank**: 0695077289 (Jonathan R. Bacolod) - **GCash**: 09128389571 (Jonathan Bacolod) - **Maya**: 09128389571 (Jonathan Bacolod) **Isend ang Screenshot ng Payment kahit saan dito:** - Email: [texmathpro@gmail.com](mailto:texmathpro@gmai","l.com) - Facebook: https://m.me/jonathan.r.bacolod - Telegram: https://t.me/Jonathan_Bacolod Isesend ko ang files sa email address mo after ng payment. ### Delivery Includes: - "), Sheet1!S64," ",Sheet1!M64," - Format: PDF", Sheet2!$D$6) -> *Stressed ka na ba kakagawa ng Second Term PowerPoint presentations mo, Grade 7 KasaMath? Kuha ka na ng Ready-to-Teach PowerPoint Slides!* **Bakit perfect para sa’yo ang Ready-to-Teach PowerPoint Slides?** - Zero Prep Time: Open mo lang at ready ka nang magturo. - Plug-and-Teach: Complete na ang discussion, examples, practice, at activities. - Professional Look: Malinis, colorful, at classroom-friendly ang design. - Student-Friendly: Visual at madaling sundan kahit habang nagdi-discuss ang teacher. - More Teaching, Less Typing: Wala nang ilang oras na paggawa ng slides from scratch. - Editable PPTX: I-customize mo para sa style at needs ng klase mo. - Super Tipid pa dahil Early Bird ka! **Product Details**: - Pieces: 24 slides, one for each lesson - Format: pptx - Price: ₱120 --- ## Step 1: I-fill out at i-submit ang Order Form.{{< iframe src="https://cityofsmiles.github.io/auto-order-form/?id=g7-t2-ps" height="850" >}} ## Step 2: Payment and Delivery ### Payment Methods Mag-send ka lang ng ₱120 para sa **Ready-to-Teach PowerPoint Slides**. - **Landbank**: 0695077289 (Jonathan R. Bacolod) - **GCash**: 09128389571 (Jonathan Bacolod) - **Maya**: 09128389571 (Jonathan Bacolod) **Isend ang Screenshot ng Payment kahit saan dito:** - Email: [texmathpro@gmail.com](mailto:texmathpro@gmail.com) - Facebook: https://m.me/jonathan.r.bacolod - Telegram: https://t.me/Jonathan_Bacolod Isesend ko ang files sa email address mo after ng payment. ### Delivery Includes: - 24 Ready-to-Teach PowerPoint Slides - Format: PDF --- Salamat sa pagsuporta sa **TeXMathPro, KasaMath**! Kung may tanong o suggestion ka, [kontakin mo lang ako](mailto:texmathpro@gmail.com). | F64: =S64*10 -> 240 | G64: =S64*5 -> 120 | H64: FALSE | I64: 46281 | J64: TRUE | K64: 46268 | M64: {=_xlfn.XLOOKUP(TRUE,ISNUMBER(SEARCH(Sheet2!A$23:A$29,A64)),Sheet2!B$23:B$29,"")} -> Ready-to-Teach PowerPoint Slides | N64: {=_xlfn.XLOOKUP(TRUE,ISNUMBER(SEARCH(Sheet2!A$32:A$34,A64)),Sheet2!B$32:B$34,"")} -> Second Term | O64: {=_xlfn.XLOOKUP(TRUE,ISNUMBER(SEARCH(Sheet2!A$38:A$41,A64)),Sheet2!B$38:B$41,"")} -> Grade 7 | S64: 24
A65: G9-T2-PS | B65: 2nd Term Ready-to-Teach PowerPoint Slides for Grade 9 | C65: https://res.cloudinary.com/dadubemrv/image/upload/v1789133530/inq3nqndxtvbwfkdnfsf.png,https://res.cloudinary.com/dadubemrv/image/upload/v1789133532/mahviqq0km6glb5dxiee.png,https://res.cloudinary.com/dadubemrv/image/upload/v1789133535/ioce6w9g54al3trnm9n0.png,https://res.cloudinary.com/dadubemrv/image/upload/v1789133538/u0pgfeghsvtibnw4cm3q.png,https://res.cloudinary.com/dadubemrv/image/upload/v1789133540/exqikiuk0hbow0tmjz80.png,https://res.cloudinary.com/dadubemrv/image/upload/v1789133543/vr7skihgfcfksfe57cyt.png,https://res.cloudinary.com/dadubemrv/image/upload/v1789133546/m2edtwdwfp3o0xkrnxvj.png,https://res.cloudinary.com/dadubemrv/image/upload/v1789133548/wfusexvrblmvufjfljev.png,https://res.cloudinary.com/dadubemrv/image/upload/v1789133551/oeegcioaczlwd5sph4aa.png,https://res.cloudinary.com/dadubemrv/image/upload/v1789133553/ov64cvucdcbab5i8pn8g.png,https://res.cloudinary.com/dadubemrv/image/upload/v1789133556/uzzcq4ff0emghvu03rhi.png,https://res.cloudinary.com/dadubemrv/image/upload/v1789133558/zosb9z2jcpfx397dtihw.png,https://res.cloudinary.com/dadubemrv/image/upload/v1789133563/d2j4jtjvyvj1mfq2veib.png,https://res.cloudinary.com/dadubemrv/image/upload/v1789133565/xx4f2gbwhgayt6neorjs.png,https://res.cloudinary.com/dadubemrv/image/upload/v1789133567/u78t12jjm26oq9oflyai.png,https://res.cloudinary.com/dadubemrv/image/upload/v1789133569/zhpmh0k3s2rtkmq0mpuy.png | D65: =CONCATENATE("*Stressed ka na ba kakagawa ng ", Sheet1!N65, " PowerPoint presentations mo, ", Sheet1!O65," KasaMath? Kuha ka na ng ", Sheet1!M65,"!* **Bakit perfect para sa’yo ang ", Sheet1!M65,_xlfn._LONGTEXT("?** - Zero Prep Time: Open mo lang at ready ka nang magturo. - Plug-and-Teach: Complete na ang discussion, examples, practice, at activities. - Professional Look: Malinis, colorful, at classroom-friendly ang design. - Student-Friendly: Visual at madaling"," sundan kahit habang nagdi-discuss ang teacher. - More Teaching, Less Typing: Wala nang ilang oras na paggawa ng slides from scratch. - Editable PPTX: I-customize mo para sa style at needs ng klase mo. **Product Details**: - Pieces: "), Sheet1!S65, " slides, one for each lesson - Format: pptx - Price: ₱", Sheet1!F65, " --- ## Step 1: I-fill out at i-submit ang Order Form.", "{{< iframe src=""", "https://cityofsmiles.github.io/auto-order-form/?id=", LOWER(A65), """ height=""850"" >}}"," ## Step 2: Payment and Delivery ### Payment Methods Mag-send ka lang ng ₱",Sheet1!F65," para sa **", Sheet1!M65,_xlfn._LONGTEXT("**. - **Landbank**: 0695077289 (Jonathan R. Bacolod) - **GCash**: 09128389571 (Jonathan Bacolod) - **Maya**: 09128389571 (Jonathan Bacolod) **Isend ang Screenshot ng Payment kahit saan dito:** - Email: [texmathpro@gmail.com](mailto:texmathpro@gmai","l.com) - Facebook: https://m.me/jonathan.r.bacolod - Telegram: https://t.me/Jonathan_Bacolod Isesend ko ang files sa email address mo after ng payment. ### Delivery Includes: - "), Sheet1!S65," ",Sheet1!M65," - Format: PDF", Sheet2!$D$6) -> *Stressed ka na ba kakagawa ng Second Term PowerPoint presentations mo, Grade 9 KasaMath? Kuha ka na ng Ready-to-Teach PowerPoint Slides!* **Bakit perfect para sa’yo ang Ready-to-Teach PowerPoint Slides?** - Zero Prep Time: Open mo lang at ready ka nang magturo. - Plug-and-Teach: Complete na ang discussion, examples, practice, at activities. - Professional Look: Malinis, colorful, at classroom-friendly ang design. - Student-Friendly: Visual at madaling sundan kahit habang nagdi-discuss ang teacher. - More Teaching, Less Typing: Wala nang ilang oras na paggawa ng slides from scratch. - Editable PPTX: I-customize mo para sa style at needs ng klase mo. **Product Details**: - Pieces: 21 slides, one for each lesson - Format: pptx - Price: ₱210 --- ## Step 1: I-fill out at i-submit ang Order Form.{{< iframe src="https://cityofsmiles.github.io/auto-order-form/?id=g9-t2-ps" height="850" >}} ## Step 2: Payment and Delivery ### Payment Methods Mag-send ka lang ng ₱210 para sa **Ready-to-Teach PowerPoint Slides**. - **Landbank**: 0695077289 (Jonathan R. Bacolod) - **GCash**: 09128389571 (Jonathan Bacolod) - **Maya**: 09128389571 (Jonathan Bacolod) **Isend ang Screenshot ng Payment kahit saan dito:** - Email: [texmathpro@gmail.com](mailto:texmathpro@gmail.com) - Facebook: https://m.me/jonathan.r.bacolod - Telegram: https://t.me/Jonathan_Bacolod Isesend ko ang files sa email address mo after ng payment. ### Delivery Includes: - 21 Ready-to-Teach PowerPoint Slides - Format: PDF --- Salamat sa pagsuporta sa **TeXMathPro, KasaMath**! Kung may tanong o suggestion ka, [kontakin mo lang ako](mailto:texmathpro@gmail.com). | E65: =CONCATENATE("*Stressed ka na ba kakagawa ng ", Sheet1!N65, " PowerPoint presentations mo, ", Sheet1!O65," KasaMath? Kuha ka na ng ", Sheet1!M65,"!* **Bakit perfect para sa’yo ang ", Sheet1!M65,_xlfn._LONGTEXT("?** - Zero Prep Time: Open mo lang at ready ka nang magturo. - Plug-and-Teach: Complete na ang discussion, examples, practice, at activities. - Professional Look: Malinis, colorful, at classroom-friendly ang design. - Student-Friendly: Visual at madaling"," sundan kahit habang nagdi-discuss ang teacher. - More Teaching, Less Typing: Wala nang ilang oras na paggawa ng slides from scratch. - Editable PPTX: I-customize mo para sa style at needs ng klase mo. - Super Tipid pa dahil Early Bird ka! **Product Det","ails**: - Pieces: "), Sheet1!S65, " slides, one for each lesson - Format: pptx - Price: ₱", Sheet1!G65, " --- ## Step 1: I-fill out at i-submit ang Order Form.", "{{< iframe src=""", "https://cityofsmiles.github.io/auto-order-form/?id=", LOWER(A65), """ height=""850"" >}}"," ## Step 2: Payment and Delivery ### Payment Methods Mag-send ka lang ng ₱",Sheet1!G65," para sa **", Sheet1!M65,_xlfn._LONGTEXT("**. - **Landbank**: 0695077289 (Jonathan R. Bacolod) - **GCash**: 09128389571 (Jonathan Bacolod) - **Maya**: 09128389571 (Jonathan Bacolod) **Isend ang Screenshot ng Payment kahit saan dito:** - Email: [texmathpro@gmail.com](mailto:texmathpro@gmai","l.com) - Facebook: https://m.me/jonathan.r.bacolod - Telegram: https://t.me/Jonathan_Bacolod Isesend ko ang files sa email address mo after ng payment. ### Delivery Includes: - "), Sheet1!S65," ",Sheet1!M65," - Format: PDF", Sheet2!$D$6) -> *Stressed ka na ba kakagawa ng Second Term PowerPoint presentations mo, Grade 9 KasaMath? Kuha ka na ng Ready-to-Teach PowerPoint Slides!* **Bakit perfect para sa’yo ang Ready-to-Teach PowerPoint Slides?** - Zero Prep Time: Open mo lang at ready ka nang magturo. - Plug-and-Teach: Complete na ang discussion, examples, practice, at activities. - Professional Look: Malinis, colorful, at classroom-friendly ang design. - Student-Friendly: Visual at madaling sundan kahit habang nagdi-discuss ang teacher. - More Teaching, Less Typing: Wala nang ilang oras na paggawa ng slides from scratch. - Editable PPTX: I-customize mo para sa style at needs ng klase mo. - Super Tipid pa dahil Early Bird ka! **Product Details**: - Pieces: 21 slides, one for each lesson - Format: pptx - Price: ₱105 --- ## Step 1: I-fill out at i-submit ang Order Form.{{< iframe src="https://cityofsmiles.github.io/auto-order-form/?id=g9-t2-ps" height="850" >}} ## Step 2: Payment and Delivery ### Payment Methods Mag-send ka lang ng ₱105 para sa **Ready-to-Teach PowerPoint Slides**. - **Landbank**: 0695077289 (Jonathan R. Bacolod) - **GCash**: 09128389571 (Jonathan Bacolod) - **Maya**: 09128389571 (Jonathan Bacolod) **Isend ang Screenshot ng Payment kahit saan dito:** - Email: [texmathpro@gmail.com](mailto:texmathpro@gmail.com) - Facebook: https://m.me/jonathan.r.bacolod - Telegram: https://t.me/Jonathan_Bacolod Isesend ko ang files sa email address mo after ng payment. ### Delivery Includes: - 21 Ready-to-Teach PowerPoint Slides - Format: PDF --- Salamat sa pagsuporta sa **TeXMathPro, KasaMath**! Kung may tanong o suggestion ka, [kontakin mo lang ako](mailto:texmathpro@gmail.com). | F65: =S65*10 -> 210 | G65: =S65*5 -> 105 | H65: FALSE | I65: 46281 | J65: TRUE | K65: 46268 | M65: {=_xlfn.XLOOKUP(TRUE,ISNUMBER(SEARCH(Sheet2!A$23:A$29,A65)),Sheet2!B$23:B$29,"")} -> Ready-to-Teach PowerPoint Slides | N65: {=_xlfn.XLOOKUP(TRUE,ISNUMBER(SEARCH(Sheet2!A$32:A$34,A65)),Sheet2!B$32:B$34,"")} -> Second Term | O65: {=_xlfn.XLOOKUP(TRUE,ISNUMBER(SEARCH(Sheet2!A$38:A$41,A65)),Sheet2!B$38:B$41,"")} -> Grade 9 | S65: 21
A66: G7-T2-SN | B66: 2nd Term Comprehensive Study Notes for Grade 7 | C66: https://res.cloudinary.com/dadubemrv/image/upload/v1789021349/tciyvgftvhrumpsctos5.jpg | D66: =CONCATENATE("*Tamad ba magsulat ng ", Sheet1!N66, " lessons ang ", Sheet1!O66," students mo, KasaMath? Kuha ka na ng ", Sheet1!M66,"!* **Bakit perfect para sa’yo ang ", Sheet1!M66,_xlfn._LONGTEXT("?** - Zero Prep Time: Di mo kailangan magpuyat kaka-prepare ng ipapasulat mo. - Plug-and-Play: Ready to print na bilang handouts, exam reviewers, o activity sheets. - Publication-Quality: Malinis at maganda ang pagkaka-typeset ng Math formulas, tables, at"," symbols - Curriculum-Aligned: Pasok sa DBOW Competencies ang contents **Product Details**: - Pieces: "), Sheet1!S66, " notes, one for each competency - Dimensions: A4 bond paper - Format: PDF - Price: ₱", Sheet1!F66, " --- ## Step 1: I-fill out at i-submit ang Order Form.", "{{< iframe src=""", "https://cityofsmiles.github.io/auto-order-form/?id=", LOWER(A66), """ height=""850"" >}}"," ## Step 2: Payment and Delivery ### Payment Methods Mag-send ka lang ng ₱",Sheet1!F66," para sa **", Sheet1!M66,_xlfn._LONGTEXT("**. - **Landbank**: 0695077289 (Jonathan R. Bacolod) - **GCash**: 09128389571 (Jonathan Bacolod) - **Maya**: 09128389571 (Jonathan Bacolod) **Isend ang Screenshot ng Payment kahit saan dito:** - Email: [texmathpro@gmail.com](mailto:texmathpro@gmai","l.com) - Facebook: https://m.me/jonathan.r.bacolod - Telegram: https://t.me/Jonathan_Bacolod Isesend ko ang files sa email address mo after ng payment. ### Delivery Includes: - "), Sheet1!S66," ",Sheet1!M66," - Format: PDF", Sheet2!$D$6) -> *Tamad ba magsulat ng Second Term lessons ang Grade 7 students mo, KasaMath? Kuha ka na ng Comprehensive Study Notes!* **Bakit perfect para sa’yo ang Comprehensive Study Notes?** - Zero Prep Time: Di mo kailangan magpuyat kaka-prepare ng ipapasulat mo. - Plug-and-Play: Ready to print na bilang handouts, exam reviewers, o activity sheets. - Publication-Quality: Malinis at maganda ang pagkaka-typeset ng Math formulas, tables, at symbols - Curriculum-Aligned: Pasok sa DBOW Competencies ang contents **Product Details**: - Pieces: 18 notes, one for each competency - Dimensions: A4 bond paper - Format: PDF - Price: ₱180 --- ## Step 1: I-fill out at i-submit ang Order Form.{{< iframe src="https://cityofsmiles.github.io/auto-order-form/?id=g7-t2-sn" height="850" >}} ## Step 2: Payment and Delivery ### Payment Methods Mag-send ka lang ng ₱180 para sa **Comprehensive Study Notes**. - **Landbank**: 0695077289 (Jonathan R. Bacolod) - **GCash**: 09128389571 (Jonathan Bacolod) - **Maya**: 09128389571 (Jonathan Bacolod) **Isend ang Screenshot ng Payment kahit saan dito:** - Email: [texmathpro@gmail.com](mailto:texmathpro@gmail.com) - Facebook: https://m.me/jonathan.r.bacolod - Telegram: https://t.me/Jonathan_Bacolod Isesend ko ang files sa email address mo after ng payment. ### Delivery Includes: - 18 Comprehensive Study Notes - Format: PDF --- Salamat sa pagsuporta sa **TeXMathPro, KasaMath**! Kung may tanong o suggestion ka, [kontakin mo lang ako](mailto:texmathpro@gmail.com). | E66: =CONCATENATE("*Tamad ba magsulat ng ", Sheet1!N66, " lessons ang ", Sheet1!O66," students mo, KasaMath? Kuha ka na ng ", Sheet1!M66,"!* **Bakit perfect para sa’yo ang ", Sheet1!M66,_xlfn._LONGTEXT("?** - Zero Prep Time: Di mo kailangan magpuyat kaka-prepare ng ipapasulat mo. - Plug-and-Play: Ready to print na bilang handouts, exam reviewers, o activity sheets. - Publication-Quality: Malinis at maganda ang pagkaka-typeset ng Math formulas, tables, at"," symbols - Curriculum-Aligned: Pasok sa DBOW Competencies ang contents - Super tipid dahil Early Bird ka **Product Details**: - Pieces: "), Sheet1!S66, " notes, one for each competency - Dimensions: A4 bond paper - Format: PDF - Price: ₱", Sheet1!G66, " --- ## Step 1: I-fill out at i-submit ang Order Form.", "{{< iframe src=""", "https://cityofsmiles.github.io/auto-order-form/?id=", LOWER(A66), """ height=""850"" >}}"," ## Step 2: Payment and Delivery ### Payment Methods Mag-send ka lang ng ₱",Sheet1!G66," para sa **", Sheet1!M66,_xlfn._LONGTEXT("**. - **Landbank**: 0695077289 (Jonathan R. Bacolod) - **GCash**: 09128389571 (Jonathan Bacolod) - **Maya**: 09128389571 (Jonathan Bacolod) **Isend ang Screenshot ng Payment kahit saan dito:** - Email: [texmathpro@gmail.com](mailto:texmathpro@gmai","l.com) - Facebook: https://m.me/jonathan.r.bacolod - Telegram: https://t.me/Jonathan_Bacolod Isesend ko ang files sa email address mo after ng payment. ### Delivery Includes: - "), Sheet1!S66," ",Sheet1!M66," - Format: PDF", Sheet2!$D$6) -> *Tamad ba magsulat ng Second Term lessons ang Grade 7 students mo, KasaMath? Kuha ka na ng Comprehensive Study Notes!* **Bakit perfect para sa’yo ang Comprehensive Study Notes?** - Zero Prep Time: Di mo kailangan magpuyat kaka-prepare ng ipapasulat mo. - Plug-and-Play: Ready to print na bilang handouts, exam reviewers, o activity sheets. - Publication-Quality: Malinis at maganda ang pagkaka-typeset ng Math formulas, tables, at symbols - Curriculum-Aligned: Pasok sa DBOW Competencies ang contents - Super tipid dahil Early Bird ka **Product Details**: - Pieces: 18 notes, one for each competency - Dimensions: A4 bond paper - Format: PDF - Price: ₱90 --- ## Step 1: I-fill out at i-submit ang Order Form.{{< iframe src="https://cityofsmiles.github.io/auto-order-form/?id=g7-t2-sn" height="850" >}} ## Step 2: Payment and Delivery ### Payment Methods Mag-send ka lang ng ₱90 para sa **Comprehensive Study Notes**. - **Landbank**: 0695077289 (Jonathan R. Bacolod) - **GCash**: 09128389571 (Jonathan Bacolod) - **Maya**: 09128389571 (Jonathan Bacolod) **Isend ang Screenshot ng Payment kahit saan dito:** - Email: [texmathpro@gmail.com](mailto:texmathpro@gmail.com) - Facebook: https://m.me/jonathan.r.bacolod - Telegram: https://t.me/Jonathan_Bacolod Isesend ko ang files sa email address mo after ng payment. ### Delivery Includes: - 18 Comprehensive Study Notes - Format: PDF --- Salamat sa pagsuporta sa **TeXMathPro, KasaMath**! Kung may tanong o suggestion ka, [kontakin mo lang ako](mailto:texmathpro@gmail.com). | F66: =S66*10 -> 180 | G66: =S66*5 -> 90 | H66: FALSE | I66: 46281 | J66: TRUE | K66: 46268 | M66: {=_xlfn.XLOOKUP(TRUE,ISNUMBER(SEARCH(Sheet2!A$23:A$28,A66)),Sheet2!B$23:B$28,"")} -> Comprehensive Study Notes | N66: {=_xlfn.XLOOKUP(TRUE,ISNUMBER(SEARCH(Sheet2!A$32:A$34,A66)),Sheet2!B$32:B$34,"")} -> Second Term | O66: {=_xlfn.XLOOKUP(TRUE,ISNUMBER(SEARCH(Sheet2!A$38:A$41,A66)),Sheet2!B$38:B$41,"")} -> Grade 7 | S66: 18
A67: G9-T2-SN | B67: 2nd Term Comprehensive Study Notes for Grade 9 | C67: https://res.cloudinary.com/dadubemrv/image/upload/v1789093364/d294yhizyzhlnrbjm9v8.jpg | D67: =CONCATENATE("*Tamad ba magsulat ng ", Sheet1!N67, " lessons ang ", Sheet1!O67," students mo, KasaMath? Kuha ka na ng ", Sheet1!M67,"!* **Bakit perfect para sa’yo ang ", Sheet1!M67,_xlfn._LONGTEXT("?** - Zero Prep Time: Di mo kailangan magpuyat kaka-prepare ng ipapasulat mo. - Plug-and-Play: Ready to print na bilang handouts, exam reviewers, o activity sheets. - Publication-Quality: Malinis at maganda ang pagkaka-typeset ng Math formulas, tables, at"," symbols - Curriculum-Aligned: Pasok sa DBOW Competencies ang contents **Product Details**: - Pieces: "), Sheet1!S67, " notes, one for each competency - Dimensions: A4 bond paper - Format: PDF - Price: ₱", Sheet1!F67, " --- ## Step 1: I-fill out at i-submit ang Order Form.", "{{< iframe src=""", "https://cityofsmiles.github.io/auto-order-form/?id=", LOWER(A67), """ height=""850"" >}}"," ## Step 2: Payment and Delivery ### Payment Methods Mag-send ka lang ng ₱",Sheet1!F67," para sa **", Sheet1!M67,_xlfn._LONGTEXT("**. - **Landbank**: 0695077289 (Jonathan R. Bacolod) - **GCash**: 09128389571 (Jonathan Bacolod) - **Maya**: 09128389571 (Jonathan Bacolod) **Isend ang Screenshot ng Payment kahit saan dito:** - Email: [texmathpro@gmail.com](mailto:texmathpro@gmai","l.com) - Facebook: https://m.me/jonathan.r.bacolod - Telegram: https://t.me/Jonathan_Bacolod Isesend ko ang files sa email address mo after ng payment. ### Delivery Includes: - "), Sheet1!S67," ",Sheet1!M67," - Format: PDF", Sheet2!$D$6) -> *Tamad ba magsulat ng Second Term lessons ang Grade 9 students mo, KasaMath? Kuha ka na ng Comprehensive Study Notes!* **Bakit perfect para sa’yo ang Comprehensive Study Notes?** - Zero Prep Time: Di mo kailangan magpuyat kaka-prepare ng ipapasulat mo. - Plug-and-Play: Ready to print na bilang handouts, exam reviewers, o activity sheets. - Publication-Quality: Malinis at maganda ang pagkaka-typeset ng Math formulas, tables, at symbols - Curriculum-Aligned: Pasok sa DBOW Competencies ang contents **Product Details**: - Pieces: 16 notes, one for each competency - Dimensions: A4 bond paper - Format: PDF - Price: ₱160 --- ## Step 1: I-fill out at i-submit ang Order Form.{{< iframe src="https://cityofsmiles.github.io/auto-order-form/?id=g9-t2-sn" height="850" >}} ## Step 2: Payment and Delivery ### Payment Methods Mag-send ka lang ng ₱160 para sa **Comprehensive Study Notes**. - **Landbank**: 0695077289 (Jonathan R. Bacolod) - **GCash**: 09128389571 (Jonathan Bacolod) - **Maya**: 09128389571 (Jonathan Bacolod) **Isend ang Screenshot ng Payment kahit saan dito:** - Email: [texmathpro@gmail.com](mailto:texmathpro@gmail.com) - Facebook: https://m.me/jonathan.r.bacolod - Telegram: https://t.me/Jonathan_Bacolod Isesend ko ang files sa email address mo after ng payment. ### Delivery Includes: - 16 Comprehensive Study Notes - Format: PDF --- Salamat sa pagsuporta sa **TeXMathPro, KasaMath**! Kung may tanong o suggestion ka, [kontakin mo lang ako](mailto:texmathpro@gmail.com). | E67: =CONCATENATE("*Tamad ba magsulat ng ", Sheet1!N67, " lessons ang ", Sheet1!O67," students mo, KasaMath? Kuha ka na ng ", Sheet1!M67,"!* **Bakit perfect para sa’yo ang ", Sheet1!M67,_xlfn._LONGTEXT("?** - Zero Prep Time: Di mo kailangan magpuyat kaka-prepare ng ipapasulat mo. - Plug-and-Play: Ready to print na bilang handouts, exam reviewers, o activity sheets. - Publication-Quality: Malinis at maganda ang pagkaka-typeset ng Math formulas, tables, at"," symbols - Curriculum-Aligned: Pasok sa DBOW Competencies ang contents - Super tipid dahil Early Bird ka **Product Details**: - Pieces: "), Sheet1!S67, " notes, one for each competency - Dimensions: A4 bond paper - Format: PDF - Price: ₱", Sheet1!G67, " --- ## Step 1: I-fill out at i-submit ang Order Form.", "{{< iframe src=""", "https://cityofsmiles.github.io/auto-order-form/?id=", LOWER(A67), """ height=""850"" >}}"," ## Step 2: Payment and Delivery ### Payment Methods Mag-send ka lang ng ₱",Sheet1!G67," para sa **", Sheet1!M67,_xlfn._LONGTEXT("**. - **Landbank**: 0695077289 (Jonathan R. Bacolod) - **GCash**: 09128389571 (Jonathan Bacolod) - **Maya**: 09128389571 (Jonathan Bacolod) **Isend ang Screenshot ng Payment kahit saan dito:** - Email: [texmathpro@gmail.com](mailto:texmathpro@gmai","l.com) - Facebook: https://m.me/jonathan.r.bacolod - Telegram: https://t.me/Jonathan_Bacolod Isesend ko ang files sa email address mo after ng payment. ### Delivery Includes: - "), Sheet1!S67," ",Sheet1!M67," - Format: PDF", Sheet2!$D$6) -> *Tamad ba magsulat ng Second Term lessons ang Grade 9 students mo, KasaMath? Kuha ka na ng Comprehensive Study Notes!* **Bakit perfect para sa’yo ang Comprehensive Study Notes?** - Zero Prep Time: Di mo kailangan magpuyat kaka-prepare ng ipapasulat mo. - Plug-and-Play: Ready to print na bilang handouts, exam reviewers, o activity sheets. - Publication-Quality: Malinis at maganda ang pagkaka-typeset ng Math formulas, tables, at symbols - Curriculum-Aligned: Pasok sa DBOW Competencies ang contents - Super tipid dahil Early Bird ka **Product Details**: - Pieces: 16 notes, one for each competency - Dimensions: A4 bond paper - Format: PDF - Price: ₱80 --- ## Step 1: I-fill out at i-submit ang Order Form.{{< iframe src="https://cityofsmiles.github.io/auto-order-form/?id=g9-t2-sn" height="850" >}} ## Step 2: Payment and Delivery ### Payment Methods Mag-send ka lang ng ₱80 para sa **Comprehensive Study Notes**. - **Landbank**: 0695077289 (Jonathan R. Bacolod) - **GCash**: 09128389571 (Jonathan Bacolod) - **Maya**: 09128389571 (Jonathan Bacolod) **Isend ang Screenshot ng Payment kahit saan dito:** - Email: [texmathpro@gmail.com](mailto:texmathpro@gmail.com) - Facebook: https://m.me/jonathan.r.bacolod - Telegram: https://t.me/Jonathan_Bacolod Isesend ko ang files sa email address mo after ng payment. ### Delivery Includes: - 16 Comprehensive Study Notes - Format: PDF --- Salamat sa pagsuporta sa **TeXMathPro, KasaMath**! Kung may tanong o suggestion ka, [kontakin mo lang ako](mailto:texmathpro@gmail.com). | F67: =S67*10 -> 160 | G67: =S67*5 -> 80 | H67: FALSE | I67: 46281 | J67: TRUE | K67: 46268 | M67: {=_xlfn.XLOOKUP(TRUE,ISNUMBER(SEARCH(Sheet2!A$23:A$28,A67)),Sheet2!B$23:B$28,"")} -> Comprehensive Study Notes | N67: {=_xlfn.XLOOKUP(TRUE,ISNUMBER(SEARCH(Sheet2!A$32:A$34,A67)),Sheet2!B$32:B$34,"")} -> Second Term | O67: {=_xlfn.XLOOKUP(TRUE,ISNUMBER(SEARCH(Sheet2!A$38:A$41,A67)),Sheet2!B$38:B$41,"")} -> Grade 9 | S67: 16
A68: G7-T2-AK | B68: 2nd Term Activity Answer Keys for Grade 7 | C68: https://res.cloudinary.com/dadubemrv/image/upload/v1788323365/t7oohow4h6hdk0okxogv.jpg | D68: =CONCATENATE("*Tinatamad ka ba, walang time, o nahihirapang gumawa ng ", Sheet1!M68, " mo para sa ", Sheet1!N68, ", ", Sheet1!O68," KasaMath? Kuha ka na ng ", Sheet1!M68,"!* **Bakit perfect para sa’yo ang ", Sheet1!M68,_xlfn._LONGTEXT("?** - Tipid ka sa oras dahil di mo na kailangang sagutan ang activities habang sumasagot ang mga estudyante. - Di na sumakit ang ulo mo sa checking ng activities dahil mga bata na ang magchecheck. - Iwas cheating sa mga bata dahil madali mong makikita"," kung kinokopya nila ang sagot habang nagchecheck. **Product Details**: - Pieces: "), Sheet1!S68, " keys, one for each lesson - Dimensions: A4 bond paper - Format: PDF, created using LaTeX - Price: ₱", Sheet1!F68, " --- ## Step 1: I-fill out at i-submit ang Order Form. ", "{{< iframe src=""", "https://cityofsmiles.github.io/auto-order-form/?id=", LOWER(A68), """ height=""850"" >}}"," ## Step 2: Payment and Delivery ### Payment Methods Mag-send ka lang ng ₱",Sheet1!F68," para sa **", Sheet1!M68,_xlfn._LONGTEXT("**. - **Landbank**: 0695077289 (Jonathan R. Bacolod) - **GCash**: 09128389571 (Jonathan Bacolod) - **Maya**: 09128389571 (Jonathan Bacolod) **Isend ang Screenshot ng Payment kahit saan dito:** - Email: [texmathpro@gmail.com](mailto:texmathpro@gm","ail.com) - Facebook: https://m.me/jonathan.r.bacolod - Telegram: https://t.me/Jonathan_Bacolod Isesend ko ang files sa email address mo after ng payment. ### Delivery Includes: - **"), Sheet1!M68,"** - Format: PDF, created using LaTeX", Sheet2!$D$6) -> *Tinatamad ka ba, walang time, o nahihirapang gumawa ng Activity Answer Keys mo para sa Second Term, Grade 7 KasaMath? Kuha ka na ng Activity Answer Keys!* **Bakit perfect para sa’yo ang Activity Answer Keys?** - Tipid ka sa oras dahil di mo na kailangang sagutan ang activities habang sumasagot ang mga estudyante. - Di na sumakit ang ulo mo sa checking ng activities dahil mga bata na ang magchecheck. - Iwas cheating sa mga bata dahil madali mong makikita kung kinokopya nila ang sagot habang nagchecheck. **Product Details**: - Pieces: 24 keys, one for each lesson - Dimensions: A4 bond paper - Format: PDF, created using LaTeX - Price: ₱240 --- ## Step 1: I-fill out at i-submit ang Order Form. {{< iframe src="https://cityofsmiles.github.io/auto-order-form/?id=g7-t2-ak" height="850" >}} ## Step 2: Payment and Delivery ### Payment Methods Mag-send ka lang ng ₱240 para sa **Activity Answer Keys**. - **Landbank**: 0695077289 (Jonathan R. Bacolod) - **GCash**: 09128389571 (Jonathan Bacolod) - **Maya**: 09128389571 (Jonathan Bacolod) **Isend ang Screenshot ng Payment kahit saan dito:** - Email: [texmathpro@gmail.com](mailto:texmathpro@gmail.com) - Facebook: https://m.me/jonathan.r.bacolod - Telegram: https://t.me/Jonathan_Bacolod Isesend ko ang files sa email address mo after ng payment. ### Delivery Includes: - **Activity Answer Keys** - Format: PDF, created using LaTeX --- Salamat sa pagsuporta sa **TeXMathPro, KasaMath**! Kung may tanong o suggestion ka, [kontakin mo lang ako](mailto:texmathpro@gmail.com). | E68: =CONCATENATE("*Tinatamad ka ba, walang time, o nahihirapang gumawa ng ", Sheet1!M68, " mo para sa ", Sheet1!N68, ", ", Sheet1!O68," KasaMath? Kuha ka na ng ", Sheet1!M68,"!* **Bakit perfect para sa’yo ang ", Sheet1!M68,_xlfn._LONGTEXT("?** - Tipid ka sa oras dahil di mo na kailangang sagutan ang activities habang sumasagot ang mga estudyante. - Tipid ka rin sa pera dahil discounted (Early Bird Promo)! - Di na sumakit ang ulo mo sa checking ng activities dahil mga bata na ang magchech","eck. - Iwas cheating sa mga bata dahil madali mong makikita kung kinokopya nila ang sagot habang nagchecheck. **Product Details**: - Pieces: "), Sheet1!S68, " keys, one for each lesson - Dimensions: A4 bond paper - Format: PDF, created using LaTeX - Price: ₱", Sheet1!G68, " --- ## Step 1: I-fill out at i-submit ang Order Form. ", "{{< iframe src=""", "https://cityofsmiles.github.io/auto-order-form/?id=", LOWER(A68), """ height=""850"" >}}"," ## Step 2: Payment and Delivery ### Payment Methods Mag-send ka lang ng ₱",Sheet1!G68," para sa **", Sheet1!M68,_xlfn._LONGTEXT("**. - **Landbank**: 0695077289 (Jonathan R. Bacolod) - **GCash**: 09128389571 (Jonathan Bacolod) - **Maya**: 09128389571 (Jonathan Bacolod) **Isend ang Screenshot ng Payment kahit saan dito:** - Email: [texmathpro@gmail.com](mailto:texmathpro@gm","ail.com) - Facebook: https://m.me/jonathan.r.bacolod - Telegram: https://t.me/Jonathan_Bacolod Isesend ko ang files sa email address mo after ng payment. ### Delivery Includes: - **"), Sheet1!M68,"** - Format: PDF, created using LaTeX", Sheet2!$D$6) -> *Tinatamad ka ba, walang time, o nahihirapang gumawa ng Activity Answer Keys mo para sa Second Term, Grade 7 KasaMath? Kuha ka na ng Activity Answer Keys!* **Bakit perfect para sa’yo ang Activity Answer Keys?** - Tipid ka sa oras dahil di mo na kailangang sagutan ang activities habang sumasagot ang mga estudyante. - Tipid ka rin sa pera dahil discounted (Early Bird Promo)! - Di na sumakit ang ulo mo sa checking ng activities dahil mga bata na ang magchecheck. - Iwas cheating sa mga bata dahil madali mong makikita kung kinokopya nila ang sagot habang nagchecheck. **Product Details**: - Pieces: 24 keys, one for each lesson - Dimensions: A4 bond paper - Format: PDF, created using LaTeX - Price: ₱72 --- ## Step 1: I-fill out at i-submit ang Order Form. {{< iframe src="https://cityofsmiles.github.io/auto-order-form/?id=g7-t2-ak" height="850" >}} ## Step 2: Payment and Delivery ### Payment Methods Mag-send ka lang ng ₱72 para sa **Activity Answer Keys**. - **Landbank**: 0695077289 (Jonathan R. Bacolod) - **GCash**: 09128389571 (Jonathan Bacolod) - **Maya**: 09128389571 (Jonathan Bacolod) **Isend ang Screenshot ng Payment kahit saan dito:** - Email: [texmathpro@gmail.com](mailto:texmathpro@gmail.com) - Facebook: https://m.me/jonathan.r.bacolod - Telegram: https://t.me/Jonathan_Bacolod Isesend ko ang files sa email address mo after ng payment. ### Delivery Includes: - **Activity Answer Keys** - Format: PDF, created using LaTeX --- Salamat sa pagsuporta sa **TeXMathPro, KasaMath**! Kung may tanong o suggestion ka, [kontakin mo lang ako](mailto:texmathpro@gmail.com). | F68: =S68*10 -> 240 | G68: =S68*3 -> 72 | H68: FALSE | I68: 46281 | J68: TRUE | K68: 46268 | M68: {=_xlfn.XLOOKUP(TRUE,ISNUMBER(SEARCH(Sheet2!A$23:A$27,A68)),Sheet2!B$23:B$27,"")} -> Activity Answer Keys | N68: {=_xlfn.XLOOKUP(TRUE,ISNUMBER(SEARCH(Sheet2!A$32:A$34,A68)),Sheet2!B$32:B$34,"")} -> Second Term | O68: {=_xlfn.XLOOKUP(TRUE,ISNUMBER(SEARCH(Sheet2!A$38:A$41,A68)),Sheet2!B$38:B$41,"")} -> Grade 7 | S68: 24
A69: G9-T2-AK | B69: 2nd Term Activity Answer Keys for Grade 9 | C69: https://res.cloudinary.com/dadubemrv/image/upload/v1788606986/e1zod9iypipnti9jstcl.jpg | D69: =CONCATENATE("*Tinatamad ka ba, walang time, o nahihirapang gumawa ng ", Sheet1!M69, " mo para sa ", Sheet1!N69, ", ", Sheet1!O69," KasaMath? Kuha ka na ng ", Sheet1!M69,"!* **Bakit perfect para sa’yo ang ", Sheet1!M69,_xlfn._LONGTEXT("?** - Tipid ka sa oras dahil di mo na kailangang sagutan ang activities habang sumasagot ang mga estudyante. - Di na sumakit ang ulo mo sa checking ng activities dahil mga bata na ang magchecheck. - Iwas cheating sa mga bata dahil madali mong makikita"," kung kinokopya nila ang sagot habang nagchecheck. **Product Details**: - Pieces: "), Sheet1!S69, " keys, one for each lesson - Dimensions: A4 bond paper - Format: PDF, created using LaTeX - Price: ₱", Sheet1!F69, " --- ## Step 1: I-fill out at i-submit ang Order Form. ", "{{< iframe src=""", "https://cityofsmiles.github.io/auto-order-form/?id=", LOWER(A69), """ height=""850"" >}}"," ## Step 2: Payment and Delivery ### Payment Methods Mag-send ka lang ng ₱",Sheet1!F69," para sa **", Sheet1!M69,_xlfn._LONGTEXT("**. - **Landbank**: 0695077289 (Jonathan R. Bacolod) - **GCash**: 09128389571 (Jonathan Bacolod) - **Maya**: 09128389571 (Jonathan Bacolod) **Isend ang Screenshot ng Payment kahit saan dito:** - Email: [texmathpro@gmail.com](mailto:texmathpro@gm","ail.com) - Facebook: https://m.me/jonathan.r.bacolod - Telegram: https://t.me/Jonathan_Bacolod Isesend ko ang files sa email address mo after ng payment. ### Delivery Includes: - **"), Sheet1!M69,"** - Format: PDF, created using LaTeX", Sheet2!$D$6) -> *Tinatamad ka ba, walang time, o nahihirapang gumawa ng Activity Answer Keys mo para sa Second Term, Grade 9 KasaMath? Kuha ka na ng Activity Answer Keys!* **Bakit perfect para sa’yo ang Activity Answer Keys?** - Tipid ka sa oras dahil di mo na kailangang sagutan ang activities habang sumasagot ang mga estudyante. - Di na sumakit ang ulo mo sa checking ng activities dahil mga bata na ang magchecheck. - Iwas cheating sa mga bata dahil madali mong makikita kung kinokopya nila ang sagot habang nagchecheck. **Product Details**: - Pieces: 20 keys, one for each lesson - Dimensions: A4 bond paper - Format: PDF, created using LaTeX - Price: ₱200 --- ## Step 1: I-fill out at i-submit ang Order Form. {{< iframe src="https://cityofsmiles.github.io/auto-order-form/?id=g9-t2-ak" height="850" >}} ## Step 2: Payment and Delivery ### Payment Methods Mag-send ka lang ng ₱200 para sa **Activity Answer Keys**. - **Landbank**: 0695077289 (Jonathan R. Bacolod) - **GCash**: 09128389571 (Jonathan Bacolod) - **Maya**: 09128389571 (Jonathan Bacolod) **Isend ang Screenshot ng Payment kahit saan dito:** - Email: [texmathpro@gmail.com](mailto:texmathpro@gmail.com) - Facebook: https://m.me/jonathan.r.bacolod - Telegram: https://t.me/Jonathan_Bacolod Isesend ko ang files sa email address mo after ng payment. ### Delivery Includes: - **Activity Answer Keys** - Format: PDF, created using LaTeX --- Salamat sa pagsuporta sa **TeXMathPro, KasaMath**! Kung may tanong o suggestion ka, [kontakin mo lang ako](mailto:texmathpro@gmail.com). | E69: =CONCATENATE("*Tinatamad ka ba, walang time, o nahihirapang gumawa ng ", Sheet1!M69, " mo para sa ", Sheet1!N69, ", ", Sheet1!O69," KasaMath? Kuha ka na ng ", Sheet1!M69,"!* **Bakit perfect para sa’yo ang ", Sheet1!M69,_xlfn._LONGTEXT("?** - Tipid ka sa oras dahil di mo na kailangang sagutan ang activities habang sumasagot ang mga estudyante. - Tipid ka rin sa pera dahil discounted (Early Bird Promo)! - Di na sumakit ang ulo mo sa checking ng activities dahil mga bata na ang magchech","eck. - Iwas cheating sa mga bata dahil madali mong makikita kung kinokopya nila ang sagot habang nagchecheck. **Product Details**: - Pieces: "), Sheet1!S69, " keys, one for each lesson - Dimensions: A4 bond paper - Format: PDF, created using LaTeX - Price: ₱", Sheet1!G69, " --- ## Step 1: I-fill out at i-submit ang Order Form. ", "{{< iframe src=""", "https://cityofsmiles.github.io/auto-order-form/?id=", LOWER(A69), """ height=""850"" >}}"," ## Step 2: Payment and Delivery ### Payment Methods Mag-send ka lang ng ₱",Sheet1!G69," para sa **", Sheet1!M69,_xlfn._LONGTEXT("**. - **Landbank**: 0695077289 (Jonathan R. Bacolod) - **GCash**: 09128389571 (Jonathan Bacolod) - **Maya**: 09128389571 (Jonathan Bacolod) **Isend ang Screenshot ng Payment kahit saan dito:** - Email: [texmathpro@gmail.com](mailto:texmathpro@gm","ail.com) - Facebook: https://m.me/jonathan.r.bacolod - Telegram: https://t.me/Jonathan_Bacolod Isesend ko ang files sa email address mo after ng payment. ### Delivery Includes: - **"), Sheet1!M69,"** - Format: PDF, created using LaTeX", Sheet2!$D$6) -> *Tinatamad ka ba, walang time, o nahihirapang gumawa ng Activity Answer Keys mo para sa Second Term, Grade 9 KasaMath? Kuha ka na ng Activity Answer Keys!* **Bakit perfect para sa’yo ang Activity Answer Keys?** - Tipid ka sa oras dahil di mo na kailangang sagutan ang activities habang sumasagot ang mga estudyante. - Tipid ka rin sa pera dahil discounted (Early Bird Promo)! - Di na sumakit ang ulo mo sa checking ng activities dahil mga bata na ang magchecheck. - Iwas cheating sa mga bata dahil madali mong makikita kung kinokopya nila ang sagot habang nagchecheck. **Product Details**: - Pieces: 20 keys, one for each lesson - Dimensions: A4 bond paper - Format: PDF, created using LaTeX - Price: ₱60 --- ## Step 1: I-fill out at i-submit ang Order Form. {{< iframe src="https://cityofsmiles.github.io/auto-order-form/?id=g9-t2-ak" height="850" >}} ## Step 2: Payment and Delivery ### Payment Methods Mag-send ka lang ng ₱60 para sa **Activity Answer Keys**. - **Landbank**: 0695077289 (Jonathan R. Bacolod) - **GCash**: 09128389571 (Jonathan Bacolod) - **Maya**: 09128389571 (Jonathan Bacolod) **Isend ang Screenshot ng Payment kahit saan dito:** - Email: [texmathpro@gmail.com](mailto:texmathpro@gmail.com) - Facebook: https://m.me/jonathan.r.bacolod - Telegram: https://t.me/Jonathan_Bacolod Isesend ko ang files sa email address mo after ng payment. ### Delivery Includes: - **Activity Answer Keys** - Format: PDF, created using LaTeX --- Salamat sa pagsuporta sa **TeXMathPro, KasaMath**! Kung may tanong o suggestion ka, [kontakin mo lang ako](mailto:texmathpro@gmail.com). | F69: =S69*10 -> 200 | G69: =S69*3 -> 60 | H69: FALSE | I69: 46281 | J69: TRUE | K69: 46268 | M69: {=_xlfn.XLOOKUP(TRUE,ISNUMBER(SEARCH(Sheet2!A$23:A$27,A69)),Sheet2!B$23:B$27,"")} -> Activity Answer Keys | N69: {=_xlfn.XLOOKUP(TRUE,ISNUMBER(SEARCH(Sheet2!A$32:A$34,A69)),Sheet2!B$32:B$34,"")} -> Second Term | O69: {=_xlfn.XLOOKUP(TRUE,ISNUMBER(SEARCH(Sheet2!A$38:A$41,A69)),Sheet2!B$38:B$41,"")} -> Grade 9 | S69: 20
A70: G7-T2-S1-BP | B70: Grade 7 T2 First Summative Test + TOS + Answer Key (Standard) | C70: https://i.imgur.com/44eqx0V.jpeg | D70: =Sheet2!$E$2 -> 0 | E70: =Sheet2!$B$2 -> 0 | F70: 165 | G70: 115 | H70: FALSE | I70: 46176 | J70: FALSE | K70: 46268
A71: G7-T2-S1-BP | B71: Grade 7 T2 First Summative Test + TOS + Answer Key (Custom) | C71: https://i.imgur.com/44eqx0V.jpeg | D71: =Sheet2!$F$2 -> 0 | E71: =Sheet2!$C$2 -> 0 | F71: 350 | G71: 245 | H71: FALSE | I71: 46176 | J71: FALSE | K71: 46176
A72: G7-T2-S1-BP | B72: Grade 8 T2 First Summative Test + TOS + Answer Key (Basic) | C72: https://i.imgur.com/KDUYUX7.jpeg | D72: =Sheet2!$D$2 -> 0 | E72: =Sheet2!$A$2 -> 0 | F72: 120 | G72: 84 | H72: FALSE | I72: 46176 | J72: FALSE | K72: 46176
A73: G7-T2-S1-BP | B73: Grade 8 T2 First Summative Test + TOS + Answer Key (Standard) | C73: https://i.imgur.com/KDUYUX7.jpeg | D73: =Sheet2!$E$2 -> 0 | E73: =Sheet2!$B$2 -> 0 | F73: 165 | G73: 115 | H73: FALSE | I73: 46176 | J73: FALSE | K73: 46176
A74: G7-T2-S1-BP | B74: Grade 8 T2 First Summative Test + TOS + Answer Key (Custom) | C74: https://i.imgur.com/KDUYUX7.jpeg | D74: =Sheet2!$F$2 -> 0 | E74: =Sheet2!$C$2 -> 0 | F74: 350 | G74: 245 | H74: FALSE | I74: 46176 | J74: FALSE | K74: 46176
A75: G7-T2-S1-BP | B75: Grade 9 T2 First Summative Test + TOS + Answer Key (Basic) | C75: https://i.imgur.com/PRWYDB8.jpeg | D75: =Sheet2!$D$2 -> 0 | E75: =Sheet2!$A$2 -> 0 | F75: 120 | G75: 84 | H75: FALSE | I75: 46176 | J75: FALSE | K75: 46176
A76: G7-T2-S1-BP | B76: Grade 9 T2 First Summative Test + TOS + Answer Key (Standard) | C76: https://i.imgur.com/PRWYDB8.jpeg | D76: =Sheet2!$E$2 -> 0 | E76: =Sheet2!$B$2 -> 0 | F76: 165 | G76: 115 | H76: FALSE | I76: 46176 | J76: FALSE | K76: 46176
A77: G7-T2-S1-BP | B77: Grade 9 T2 First Summative Test + TOS + Answer Key (Custom) | C77: https://i.imgur.com/PRWYDB8.jpeg | D77: =Sheet2!$F$2 -> 0 | E77: =Sheet2!$C$2 -> 0 | F77: 350 | G77: 245 | H77: FALSE | I77: 46176 | J77: FALSE | K77: 46176
A78: G7-T2-S1-BP | B78: Grade 10 T2 First Summative Test + TOS + Answer Key (Basic) | C78: https://i.imgur.com/P1inplO.jpeg | D78: =Sheet2!$D$2 -> 0 | E78: =Sheet2!$A$2 -> 0 | F78: 120 | G78: 84 | H78: FALSE | I78: 46176 | J78: FALSE | K78: 46176
A79: G7-T2-S1-BP | B79: Grade 10 T2 First Summative Test + TOS + Answer Key (Standard) | C79: https://i.imgur.com/P1inplO.jpeg | D79: =Sheet2!$E$2 -> 0 | E79: =Sheet2!$B$2 -> 0 | F79: 165 | G79: 115 | H79: FALSE | I79: 46176 | J79: FALSE | K79: 46176
A80: G7-T2-S1-BP | B80: Grade 10 T2 First Summative Test + TOS + Answer Key (Custom) | C80: https://i.imgur.com/P1inplO.jpeg | D80: =Sheet2!$F$2 -> 0 | E80: =Sheet2!$C$2 -> 0 | F80: 350 | G80: 245 | H80: FALSE | I80: 46176 | J80: FALSE | K80: 46176
A81: G7-T2-S1-BP | B81: Grade 7 T2 Term Exam + TOS + Answer Key (Basic) | C81: https://i.imgur.com/uDMIvrF.jpeg | D81: =Sheet2!$D$2 -> 0 | E81: =Sheet2!$A$2 -> 0 | F81: 120 | G81: 84 | H81: FALSE | I81: 46176 | J81: FALSE | K81: 46176
A82: G7-T2-S1-BP | B82: Grade 7 T2 Term Exam + TOS + Answer Key (Standard) | C82: https://i.imgur.com/uDMIvrF.jpeg | D82: =Sheet2!$E$2 -> 0 | E82: =Sheet2!$B$2 -> 0 | F82: 165 | G82: 115 | H82: FALSE | I82: 46176 | J82: FALSE | K82: 46176
A83: G7-T2-S1-BP | B83: Grade 7 T2 Term Exam + TOS + Answer Key (Custom) | C83: https://i.imgur.com/uDMIvrF.jpeg | D83: =Sheet2!$F$2 -> 0 | E83: =Sheet2!$C$2 -> 0 | F83: 350 | G83: 245 | H83: FALSE | I83: 46176 | J83: FALSE | K83: 46176
A84: G8-T2-TE-BP | B84: Grade 8 T2 Term Exam + TOS + Answer Key (Basic) | C84: https://i.imgur.com/8n2VCOb.jpeg | D84: =Sheet2!$D$2 -> 0 | E84: =Sheet2!$A$2 -> 0 | F84: 120 | G84: 84 | H84: FALSE | I84: 46176 | J84: FALSE | K84: 46176
A85: G8-T2-TE-SP | B85: Grade 8 T2 Term Exam + TOS + Answer Key (Standard) | C85: https://i.imgur.com/8n2VCOb.jpeg | D85: =Sheet2!$E$2 -> 0 | E85: =Sheet2!$B$2 -> 0 | F85: 165 | G85: 115 | H85: FALSE | I85: 46176 | J85: FALSE | K85: 46176
A86: G8-T2-TE-CP | B86: Grade 8 T2 Term Exam + TOS + Answer Key (Custom) | C86: https://i.imgur.com/8n2VCOb.jpeg | D86: =Sheet2!$F$2 -> 0 | E86: =Sheet2!$C$2 -> 0 | F86: 350 | G86: 245 | H86: FALSE | I86: 46176 | J86: FALSE | K86: 46176
A87: G9-T2-TE-BP | B87: Grade 9 T2 Term Exam + TOS + Answer Key (Basic) | C87: https://i.imgur.com/sVIQDun.jpeg | D87: =Sheet2!$D$2 -> 0 | E87: =Sheet2!$A$2 -> 0 | F87: 120 | G87: 84 | H87: FALSE | I87: 46176 | J87: FALSE | K87: 46176
A88: G9-T2-TE-SP | B88: Grade 9 T2 Term Exam + TOS + Answer Key (Standard) | C88: https://i.imgur.com/sVIQDun.jpeg | D88: =Sheet2!$E$2 -> 0 | E88: =Sheet2!$B$2 -> 0 | F88: 165 | G88: 115 | H88: FALSE | I88: 46176 | J88: FALSE | K88: 46176
A89: G9-T2-TE-CP | B89: Grade 9 T2 Term Exam + TOS + Answer Key (Custom) | C89: https://i.imgur.com/sVIQDun.jpeg | D89: =Sheet2!$F$2 -> 0 | E89: =Sheet2!$C$2 -> 0 | F89: 350 | G89: 245 | H89: FALSE | I89: 46176 | J89: FALSE | K89: 46176
A90: G10-T2-TE-BP | B90: Grade 10 T2 Term Exam + TOS + Answer Key (Basic) | C90: https://i.imgur.com/T2J0K9c.jpeg | D90: =Sheet2!$D$2 -> 0 | E90: =Sheet2!$A$2 -> 0 | F90: 120 | G90: 84 | H90: FALSE | I90: 46176 | J90: FALSE | K90: 46176
A91: G10-T2-TE-SP | B91: Grade 10 T2 Term Exam + TOS + Answer Key (Standard) | C91: https://i.imgur.com/T2J0K9c.jpeg | D91: =Sheet2!$E$2 -> 0 | E91: =Sheet2!$B$2 -> 0 | F91: 165 | G91: 115 | H91: FALSE | I91: 46176 | J91: FALSE | K91: 46176
A92: G10-T2-TE-CP | B92: Grade 10 T2 Term Exam + TOS + Answer Key (Custom) | C92: https://i.imgur.com/T2J0K9c.jpeg | D92: =Sheet2!$F$2 -> 0 | E92: =Sheet2!$C$2 -> 0 | F92: 350 | G92: 245 | H92: FALSE | I92: 46176 | J92: FALSE | K92: 46176

Sheet Sheet2
A1: Discounted Basic | B1: Discounted Standard | C1: Discounted Premium | D1: Regular Basic | E1: Regular Standard | F1: Regular Premium
A5: Activity Answer key | B5: How to Order | C5: Multiple-choice Quizzes | D5: Salamat
B6: - **Landbank**: 0695077289 (Jonathan R. Bacolod) - **GCash**: 09128389571 (Jonathan Bacolod) - **Maya**: 09128389571 (Jonathan Bacolod) **Isend ang Screenshot ng Payment kahit saan dito:** - Email: [texmathpro@gmail.com](mailto:texmathpro@gmail.com) - Facebook: https://m.me/jonathan.r.bacolod - Telegram: https://t.me/Jonathan_Bacolod Isesend ko ang files sa email address mo after ng payment. --- Salamat sa pagsuporta sa **TeXMathPro, KasaMath**! Kung may tanong o suggestion ka, [kontakin mo lang ako](https://texmathpro.github.io/contact/). | C6: Tinatamad ka ba, walang time, o nahihirapang gumawa ng quizzes mo this term, KasaMath? ✨ Kuha ka na ng Multiple Choice Quizzes with Answer Keys para: - Tipid ka sa oras at makapag-focus sa pagtuturo. - Maganda at consistent ang formatting ng test questions at figures mo. - Ready na ang answer key at di ka na magsasagot ng questions. - Masanay ang students sa pagsagot ng multiple choice test. - Parallel ang quiz items sa questions na lalabas sa Summative test at Term Exam. --- 📑 **Product Details** | Feature | Details | |---|---| | Content | | D6: =CONCATENATE(" --- Salamat sa pagsuporta sa **TeXMathPro, KasaMath**! Kung may tanong o suggestion ka, [kontakin mo lang ako](mailto:texmathpro@gmail.com).") -> --- Salamat sa pagsuporta sa **TeXMathPro, KasaMath**! Kung may tanong o suggestion ka, [kontakin mo lang ako](mailto:texmathpro@gmail.com).
B9: Grade 7 | C9: Grade 8 | D9: Grade 9 | E9: Grade 10 | F9: isPublished | G9: TRUE | H9: FALSE | I9: TRUE | J9: FALSE
A10: 1st Term | B10: https://drive.google.com/file/d/150NUP_Nq2tev-Qn00VInZTAaPrUAssmQ/view?usp=drivesdk | C10: https://drive.google.com/file/d/150NUP_Nq2tev-Qn00VInZTAaPrUAssmQ/view?usp=drivesdk | D10: https://drive.google.com/file/d/1x4fsJFRIZ1vsqPk6OXbzsGErE1XdDNJQ/view?usp=drivesdk | E10: https://drive.google.com/file/d/150NUP_Nq2tev-Qn00VInZTAaPrUAssmQ/view?usp=drivesdk | F10: TRUE | G10: =IF($F10, CONCATENATE("- [", B$9, " Handouts for the ",$A10, "](", B10, ")"), "") -> - [Grade 7 Handouts for the 1st Term](https://drive.google.com/file/d/150NUP_Nq2tev-Qn00VInZTAaPrUAssmQ/view?usp=drivesdk) | H10: =IF(H$9,IF($F10, CONCATENATE("- [", C$9, " Handouts for the ",$A10, "](", C10, ")"), ""),"") | I10: =IF($F10, CONCATENATE("- [", D$9, " Handouts for the ",$A10, "](", D10, ")"), "") -> - [Grade 9 Handouts for the 1st Term](https://drive.google.com/file/d/1x4fsJFRIZ1vsqPk6OXbzsGErE1XdDNJQ/view?usp=drivesdk) | J10: =IF(H$9,IF($F10, CONCATENATE("- [", E$9, " Handouts for the ",$A10, "](", E10, ")"), ""),"")
A11: 2nd Term | B11: https://drive.google.com/file/d/1-KDJsZditKS4m47wiWkkrUHdmr6OGHRS/view?usp=drivesdk | C11: https://drive.google.com/file/d/1-KDJsZditKS4m47wiWkkrUHdmr6OGHRS/view?usp=drivesdk | D11: https://drive.google.com/file/d/1EE_6jJP56HUvwmqvAvF3kXdhOI1EKpPi/view?usp=drivesdk | E11: https://drive.google.com/file/d/1-KDJsZditKS4m47wiWkkrUHdmr6OGHRS/view?usp=drivesdk | F11: TRUE | G11: =IF($F11, CONCATENATE("- [", B$9, " Handouts for the ",$A11, "](", B11, ")"), "") -> - [Grade 7 Handouts for the 2nd Term](https://drive.google.com/file/d/1-KDJsZditKS4m47wiWkkrUHdmr6OGHRS/view?usp=drivesdk) | H11: =IF(H$9,IF($F11, CONCATENATE("- [", C$9, " Handouts for the ",$A11, "](", C11, ")"), ""),"") | I11: =IF($F11, CONCATENATE("- [", D$9, " Handouts for the ",$A11, "](", D11, ")"), "") -> - [Grade 9 Handouts for the 2nd Term](https://drive.google.com/file/d/1EE_6jJP56HUvwmqvAvF3kXdhOI1EKpPi/view?usp=drivesdk) | J11: =IF(H$9,IF($F11, CONCATENATE("- [", E$9, " Handouts for the ",$A11, "](", E11, ")"), ""),"")
A12: 3rd Term | B12: https://drive.google.com/file/d/150NUP_Nq2tev-Qn00VInZTAaPrUAssmQ/view?usp=drivesdk | C12: https://drive.google.com/file/d/150NUP_Nq2tev-Qn00VInZTAaPrUAssmQ/view?usp=drivesdk | D12: https://drive.google.com/file/d/150NUP_Nq2tev-Qn00VInZTAaPrUAssmQ/view?usp=drivesdk | E12: https://drive.google.com/file/d/150NUP_Nq2tev-Qn00VInZTAaPrUAssmQ/view?usp=drivesdk | F12: FALSE | G12: =IF($F12, CONCATENATE("- [", B$9, " Handouts for the ",$A12, "](", B12, ")"), "") | H12: =IF(H$9,IF($F12, CONCATENATE("- [", C$9, " Handouts for the ",$A12, "](", C12, ")"), ""),"") | I12: =IF($F12, CONCATENATE("- [", D$9, " Handouts for the ",$A12, "](", D12, ")"), "") | J12: =IF(H$9,IF($F12, CONCATENATE("- [", E$9, " Handouts for the ",$A12, "](", E12, ")"), ""),"")
A13: 4th Term | B13: https://drive.google.com/file/d/1-KDJsZditKS4m47wiWkkrUHdmr6OGHRS/view?usp=drivesdk | C13: https://drive.google.com/file/d/1-KDJsZditKS4m47wiWkkrUHdmr6OGHRS/view?usp=drivesdk | D13: https://drive.google.com/file/d/1-KDJsZditKS4m47wiWkkrUHdmr6OGHRS/view?usp=drivesdk | E13: https://drive.google.com/file/d/1-KDJsZditKS4m47wiWkkrUHdmr6OGHRS/view?usp=drivesdk | F13: FALSE | G13: =IF($F13, CONCATENATE("- [", B$9, " Handouts for the ",$A13, "](", B13, ")"), "") | H13: =IF($F13, CONCATENATE("- [", C$9, " Handouts for the ",$A13, "](", C13, ")"), "") | I13: =IF($F13, CONCATENATE("- [", D$9, " Handouts for the ",$A13, "](", D13, ")"), "") | J13: =IF($F13, CONCATENATE("- [", E$9, " Handouts for the ",$A13, "](", E13, ")"), "")
A16: Discounted Basic | B16: Discounted Standard | C16: Discounted Premium | D16: Regular Basic | E16: Regular Standard | F16: Regular Premium
